Workbook

Sheet Cleaned_Orders
A1: order_id | B1: order_date | C1: ship_date | D1: customer_id | E1: customer_name | F1: segment | G1: region | H1: state | I1: city | J1: category | K1: sub_category | L1: product_name | M1: ship_mode | N1: quantity | O1: unit_price | P1: discount | Q1: sales | R1: cost | S1: profit | T1: payment_status | U1: order_status | V1: cleaned_discount | W1: calculated_sales | X1: calculated_profit | Y1: profit_margin | Z1: shipping_delay_days | AA1: order_month | AB1: order_year | AC1: original_data_flags | AD1: flag_details | AE1: data_quality_flag
A2: ORD-2024-10001 | B2: 45494 | C2: 45500 | D2: CUST-4655 | E2: =PROPER(TRIM(SUBSTITUTE(Raw_Text_Fields!B3,CHAR(160)," "))) -> Karan Malhotra | F2: =PROPER(TRIM(SUBSTITUTE(Raw_Text_Fields!C3,CHAR(160)," "))) -> Consumer | G2: =PROPER(TRIM(SUBSTITUTE(Raw_Text_Fields!D3,CHAR(160)," "))) -> North | H2: =PROPER(TRIM(SUBSTITUTE(Raw_Text_Fields!E3,CHAR(160)," "))) -> Rajasthan | I2: =PROPER(TRIM(SUBSTITUTE(Raw_Text_Fields!F3,CHAR(160)," "))) -> Jaipur | J2: =PROPER(TRIM(SUBSTITUTE(Raw_Text_Fields!G3,CHAR(160)," "))) -> Office Supplies | K2: =PROPER(TRIM(SUBSTITUTE(Raw_Text_Fields!H3,CHAR(160)," "))) -> Paper | L2: Pro Paper 122 | M2: =PROPER(TRIM(SUBSTITUTE(Raw_Text_Fields!I3,CHAR(160)," "))) -> Second Class | N2: 8 | O2: 2976.45 | P2: 0.2 | Q2: 19049.28 | R2: 15841.89 | S2: 3207.39 | T2: =PROPER(TRIM(SUBSTITUTE(Raw_Text_Fields!J3,CHAR(160)," "))) -> Paid | U2: =PROPER(TRIM(SUBSTITUTE(Raw_Text_Fields!K3,CHAR(160)," "))) -> Completed | V2: =IF(OR(P2<0,P2>0.5),0,P2) -> 0.2 | W2: =N2*O2*(1-V2) -> 19049.28 | X2: =W2-R2 -> 3207.39 | Y2: =IFERROR(X2/W2,0) -> 0.16837329 | Z2: =C2-B2 -> 6 | AA2: =IF(B2="","",TEXT(B2,"mmm")) -> Jul | AB2: =IF(B2="","",YEAR(B2)) -> 2024 | AD2: =IF(LEFT(AC2&IF(B2="","; Missing Order Date","")&IF(C2="","; Missing Ship Date","")&IF(P2<0,"; Invalid Discount (Negative)","")&IF(P2>0.5,"; Invalid Discount (Too High)","")&IF(Z2<0,"; Invalid Shipping Record (Ship Before Order)","")&IF(ABS(Q2-W2)>1,"; Sales Mismatch","")&IF(ABS(S2-X2)>1,"; Profit Mismatch","")&IF(COUNTIF($A$2:$A$913,A2)>1,"; Duplicate Order ID Conflict",""),2)="; ",MID(AC2&IF(B2="","; Missing Order Date","")&IF(C2="","; Missing Ship Date","")&IF(P2<0,"; Invalid Discount (Negative)","")&IF(P2>0.5,"; Invalid Discount (Too High)","")&IF(Z2<0,"; Invalid Shipping Record (Ship Before Order)","")&IF(ABS(Q2-W2)>1,"; Sales Mismatch","")&IF(ABS(S2-X2)>1,"; Profit Mismatch","")&IF(COUNTIF($A$2:$A$913,A2)>1,"; Duplicate Order ID Conflict",""),3,500),AC2&IF(B2="","; Missing Order Date","")&IF(C2="","; Missing Ship Date","")&IF(P2<0,"; Invalid Discount (Negative)","")&IF(P2>0.5,"; Invalid Discount (Too High)","")&IF(Z2<0,"; Invalid Shipping Record (Ship Before Order)","")&IF(ABS(Q2-W2)>1,"; Sales Mismatch","")&IF(ABS(S2-X2)>1,"; Profit Mismatch","")&IF(COUNTIF($A$2:$A$913,A2)>1,"; Duplicate Order ID Conflict","")) | AE2: =IF(OR(ISNUMBER(SEARCH("Invalid Discount",AD2)),ISNUMBER(SEARCH("Invalid Shipping Record",AD2)),ISNUMBER(SEARCH("Sales Mismatch",AD2)),ISNUMBER(SEARCH("Profit Mismatch",AD2)),ISNUMBER(SEARCH("Duplicate Order ID Conflict",AD2)),ISNUMBER(SEARCH("Missing Order Date",AD2)),ISNUMBER(SEARCH("Missing Ship Date",AD2))),"Invalid",IF(AD2<>"","Warning","Clean")) -> Clean
A3: ORD-2024-10002 | B3: 45535 | C3: 45540 | D3: CUST-2054 | E3: =PROPER(TRIM(SUBSTITUTE(Raw_Text_Fields!B4,CHAR(160)," "))) -> Mira Das | F3: =PROPER(TRIM(SUBSTITUTE(Raw_Text_Fields!C4,CHAR(160)," "))) -> Small Business | G3: =PROPER(TRIM(SUBSTITUTE(Raw_Text_Fields!D4,CHAR(160)," "))) -> East | H3: =PROPER(TRIM(SUBSTITUTE(Raw_Text_Fields!E4,CHAR(160)," "))) -> Odisha | I3: =PROPER(TRIM(SUBSTITUTE(Raw_Text_Fields!F4,CHAR(160)," "))) -> Bhubaneswar | J3: =PROPER(TRIM(SUBSTITUTE(Raw_Text_Fields!G4,CHAR(160)," "))) -> Furniture | K3: =PROPER(TRIM(SUBSTITUTE(Raw_Text_Fields!H4,CHAR(160)," "))) -> Tables | L3: Pro Tables 258 | M3: =PROPER(TRIM(SUBSTITUTE(Raw_Text_Fields!I4,CHAR(160)," "))) -> Same Day | N3: 3 | O3: 2437.5 | P3: 0 | Q3: 7312.5 | R3: 4904.73 | S3: 2407.77 | T3: =PROPER(TRIM(SUBSTITUTE(Raw_Text_Fields!J4,CHAR(160)," "))) -> Paid | U3: =PROPER(TRIM(SUBSTITUTE(Raw_Text_Fields!K4,CHAR(160)," "))) -> Completed | V3: =IF(OR(P3<0,P3>0.5),0,P3) -> 0 | W3: =N3*O3*(1-V3) -> 7312.5 | X3: =W3-R3 -> 2407.77 | Y3: =IFERROR(X3/W3,0) -> 0.32926769 | Z3: =C3-B3 -> 5 | AA3: =IF(B3="","",TEXT(B3,"mmm")) -> Aug | AB3: =IF(B3="","",YEAR(B3)) -> 2024 | AD3: =IF(LEFT(AC3&IF(B3="","; Missing Order Date","")&IF(C3="","; Missing Ship Date","")&IF(P3<0,"; Invalid Discount (Negative)","")&IF(P3>0.5,"; Invalid Discount (Too High)","")&IF(Z3<0,"; Invalid Shipping Record (Ship Before Order)","")&IF(ABS(Q3-W3)>1,"; Sales Mismatch","")&IF(ABS(S3-X3)>1,"; Profit Mismatch","")&IF(COUNTIF($A$2:$A$913,A3)>1,"; Duplicate Order ID Conflict",""),2)="; ",MID(AC3&IF(B3="","; Missing Order Date","")&IF(C3="","; Missing Ship Date","")&IF(P3<0,"; Invalid Discount (Negative)","")&IF(P3>0.5,"; Invalid Discount (Too High)","")&IF(Z3<0,"; Invalid Shipping Record (Ship Before Order)","")&IF(ABS(Q3-W3)>1,"; Sales Mismatch","")&IF(ABS(S3-X3)>1,"; Profit Mismatch","")&IF(COUNTIF($A$2:$A$913,A3)>1,"; Duplicate Order ID Conflict",""),3,500),AC3&IF(B3="","; Missing Order Date","")&IF(C3="","; Missing Ship Date","")&IF(P3<0,"; Invalid Discount (Negative)","")&IF(P3>0.5,"; Invalid Discount (Too High)","")&IF(Z3<0,"; Invalid Shipping Record (Ship Before Order)","")&IF(ABS(Q3-W3)>1,"; Sales Mismatch","")&IF(ABS(S3-X3)>1,"; Profit Mismatch","")&IF(COUNTIF($A$2:$A$913,A3)>1,"; Duplicate Order ID Conflict","")) | AE3: =IF(OR(ISNUMBER(SEARCH("Invalid Discount",AD3)),ISNUMBER(SEARCH("Invalid Shipping Record",AD3)),ISNUMBER(SEARCH("Sales Mismatch",AD3)),ISNUMBER(SEARCH("Profit Mismatch",AD3)),ISNUMBER(SEARCH("Duplicate Order ID Conflict",AD3)),ISNUMBER(SEARCH("Missing Order Date",AD3)),ISNUMBER(SEARCH("Missing Ship Date",AD3))),"Invalid",IF(AD3<>"","Warning","Clean")) -> Clean
A4: ORD-2024-10003 | B4: 45451 | C4: 45458 | D4: CUST-6843 | E4: =PROPER(TRIM(SUBSTITUTE(Raw_Text_Fields!B5,CHAR(160)," "))) -> Isha Nair | F4: =PROPER(TRIM(SUBSTITUTE(Raw_Text_Fields!C5,CHAR(160)," "))) -> Consumer | G4: =PROPER(TRIM(SUBSTITUTE(Raw_Text_Fields!D5,CHAR(160)," "))) -> East | H4: =PROPER(TRIM(SUBSTITUTE(Raw_Text_Fields!E5,CHAR(160)," "))) -> Odisha | I4: =PROPER(TRIM(SUBSTITUTE(Raw_Text_Fields!F5,CHAR(160)," "))) -> Bhubaneswar | J4: =PROPER(TRIM(SUBSTITUTE(Raw_Text_Fields!G5,CHAR(160)," "))) -> Office Supplies | K4: =PROPER(TRIM(SUBSTITUTE(Raw_Text_Fields!H5,CHAR(160)," "))) -> Art | L4: Elite Art 525 | M4: =PROPER(TRIM(SUBSTITUTE(Raw_Text_Fields!I5,CHAR(160)," "))) -> First Class | N4: 4 | O4: 1065.43 | P4: 0.55 | Q4: 4261.72 | R4: 2465.69 | S4: 1796.03 | T4: =PROPER(TRIM(SUBSTITUTE(Raw_Text_Fields!J5,CHAR(160)," "))) -> Paid | U4: =PROPER(TRIM(SUBSTITUTE(Raw_Text_Fields!K5,CHAR(160)," "))) -> Completed | V4: =IF(OR(P4<0,P4>0.5),0,P4) -> 0 | W4: =N4*O4*(1-V4) -> 4261.72 | X4: =W4-R4 -> 1796.03 | Y4: =IFERROR(X4/W4,0) -> 0.42143313 | Z4: =C4-B4 -> 7 | AA4: =IF(B4="","",TEXT(B4,"mmm")) -> Jun | AB4: =IF(B4="","",YEAR(B4)) -> 2024 | AD4: =IF(LEFT(AC4&IF(B4="","; Missing Order Date","")&IF(C4="","; Missing Ship Date","")&IF(P4<0,"; Invalid Discount (Negative)","")&IF(P4>0.5,"; Invalid Discount (Too High)","")&IF(Z4<0,"; Invalid Shipping Record (Ship Before Order)","")&IF(ABS(Q4-W4)>1,"; Sales Mismatch","")&IF(ABS(S4-X4)>1,"; Profit Mismatch","")&IF(COUNTIF($A$2:$A$913,A4)>1,"; Duplicate Order ID Conflict",""),2)="; ",MID(AC4&IF(B4="","; Missing Order Date","")&IF(C4="","; Missing Ship Date","")&IF(P4<0,"; Invalid Discount (Negative)","")&IF(P4>0.5,"; Invalid Discount (Too High)","")&IF(Z4<0,"; Invalid Shipping Record (Ship Before Order)","")&IF(ABS(Q4-W4)>1,"; Sales Mismatch","")&IF(ABS(S4-X4)>1,"; Profit Mismatch","")&IF(COUNTIF($A$2:$A$913,A4)>1,"; Duplicate Order ID Conflict",""),3,500),AC4&IF(B4="","; Missing Order Date","")&IF(C4="","; Missing Ship Date","")&IF(P4<0,"; Invalid Discount (Negative)","")&IF(P4>0.5,"; Invalid Discount (Too High)","")&IF(Z4<0,"; Invalid Shipping Record (Ship Before Order)","")&IF(ABS(Q4-W4)>1,"; Sales Mismatch","")&IF(ABS(S4-X4)>1,"; Profit Mismatch","")&IF(COUNTIF($A$2:$A$913,A4)>1,"; Duplicate Order ID Conflict","")) -> Invalid Discount (Too High) | AE4: =IF(OR(ISNUMBER(SEARCH("Invalid Discount",AD4)),ISNUMBER(SEARCH("Invalid Shipping Record",AD4)),ISNUMBER(SEARCH("Sales Mismatch",AD4)),ISNUMBER(SEARCH("Profit Mismatch",AD4)),ISNUMBER(SEARCH("Duplicate Order ID Conflict",AD4)),ISNUMBER(SEARCH("Missing Order Date",AD4)),ISNUMBER(SEARCH("Missing Ship Date",AD4))),"Invalid",IF(AD4<>"","Warning","Clean")) -> Invalid
A5: ORD-2024-10004 | B5: 45624 | C5: 45625 | D5: CUST-3722 | E5: =PROPER(TRIM(SUBSTITUTE(Raw_Text_Fields!B6,CHAR(160)," "))) -> Arjun Bose | F5: =PROPER(TRIM(SUBSTITUTE(Raw_Text_Fields!C6,CHAR(160)," "))) -> Small Business | G5: =PROPER(TRIM(SUBSTITUTE(Raw_Text_Fields!D6,CHAR(160)," "))) -> South | H5: =PROPER(TRIM(SUBSTITUTE(Raw_Text_Fields!E6,CHAR(160)," "))) -> Telangana | I5: =PROPER(TRIM(SUBSTITUTE(Raw_Text_Fields!F6,CHAR(160)," "))) -> Hyderabad | J5: =PROPER(TRIM(SUBSTITUTE(Raw_Text_Fields!G6,CHAR(160)," "))) -> Furniture | K5: =PROPER(TRIM(SUBSTITUTE(Raw_Text_Fields!H6,CHAR(160)," "))) -> Furnishings | L5: Smart Furnishings 294 | M5: =PROPER(TRIM(SUBSTITUTE(Raw_Text_Fields!I6,CHAR(160)," "))) -> Standard Class | N5: 6 | O5: 1848.43 | P5: 0.25 | Q5: 8317.93 | R5: 6796.77 | S5: 1521.16 | T5: =PROPER(TRIM(SUBSTITUTE(Raw_Text_Fields!J6,CHAR(160)," "))) -> Paid | U5: =PROPER(TRIM(SUBSTITUTE(Raw_Text_Fields!K6,CHAR(160)," "))) -> Completed | V5: =IF(OR(P5<0,P5>0.5),0,P5) -> 0.25 | W5: =N5*O5*(1-V5) -> 8317.935 | X5: =W5-R5 -> 1521.165 | Y5: =IFERROR(X5/W5,0) -> 0.18287772 | Z5: =C5-B5 -> 1 | AA5: =IF(B5="","",TEXT(B5,"mmm")) -> Nov | AB5: =IF(B5="","",YEAR(B5)) -> 2024 | AD5: =IF(LEFT(AC5&IF(B5="","; Missing Order Date","")&IF(C5="","; Missing Ship Date","")&IF(P5<0,"; Invalid Discount (Negative)","")&IF(P5>0.5,"; Invalid Discount (Too High)","")&IF(Z5<0,"; Invalid Shipping Record (Ship Before Order)","")&IF(ABS(Q5-W5)>1,"; Sales Mismatch","")&IF(ABS(S5-X5)>1,"; Profit Mismatch","")&IF(COUNTIF($A$2:$A$913,A5)>1,"; Duplicate Order ID Conflict",""),2)="; ",MID(AC5&IF(B5="","; Missing Order Date","")&IF(C5="","; Missing Ship Date","")&IF(P5<0,"; Invalid Discount (Negative)","")&IF(P5>0.5,"; Invalid Discount (Too High)","")&IF(Z5<0,"; Invalid Shipping Record (Ship Before Order)","")&IF(ABS(Q5-W5)>1,"; Sales Mismatch","")&IF(ABS(S5-X5)>1,"; Profit Mismatch","")&IF(COUNTIF($A$2:$A$913,A5)>1,"; Duplicate Order ID Conflict",""),3,500),AC5&IF(B5="","; Missing Order Date","")&IF(C5="","; Missing Ship Date","")&IF(P5<0,"; Invalid Discount (Negative)","")&IF(P5>0.5,"; Invalid Discount (Too High)","")&IF(Z5<0,"; Invalid Shipping Record (Ship Before Order)","")&IF(ABS(Q5-W5)>1,"; Sales Mismatch","")&IF(ABS(S5-X5)>1,"; Profit Mismatch","")&IF(COUNTIF($A$2:$A$913,A5)>1,"; Duplicate Order ID Conflict","")) | AE5: =IF(OR(ISNUMBER(SEARCH("Invalid Discount",AD5)),ISNUMBER(SEARCH("Invalid Shipping Record",AD5)),ISNUMBER(SEARCH("Sales Mismatch",AD5)),ISNUMBER(SEARCH("Profit Mismatch",AD5)),ISNUMBER(SEARCH("Duplicate Order ID Conflict",AD5)),ISNUMBER(SEARCH("Missing Order Date",AD5)),ISNUMBER(SEARCH("Missing Ship Date",AD5))),"Invalid",IF(AD5<>"","Warning","Clean")) -> Clean
A6: ORD-2025-10005 | B6: 45898 | C6: 45901 | D6: CUST-8130 | E6: =PROPER(TRIM(SUBSTITUTE(Raw_Text_Fields!B7,CHAR(160)," "))) -> Ananya Rao | F6: =PROPER(TRIM(SUBSTITUTE(Raw_Text_Fields!C7,CHAR(160)," "))) -> Small Business | G6: =PROPER(TRIM(SUBSTITUTE(Raw_Text_Fields!D7,CHAR(160)," "))) -> West | H6: =PROPER(TRIM(SUBSTITUTE(Raw_Text_Fields!E7,CHAR(160)," "))) -> Maharashtra | I6: =PROPER(TRIM(SUBSTITUTE(Raw_Text_Fields!F7,CHAR(160)," "))) -> Mumbai | J6: =PROPER(TRIM(SUBSTITUTE(Raw_Text_Fields!G7,CHAR(160)," "))) -> Furniture | K6: =PROPER(TRIM(SUBSTITUTE(Raw_Text_Fields!H7,CHAR(160)," "))) -> Chairs | L6: Elite Chairs 543 | M6: =PROPER(TRIM(SUBSTITUTE(Raw_Text_Fields!I7,CHAR(160)," "))) -> First Class | N6: 7 | O6: 2973.76 | P6: 0 | Q6: 20816.32 | R6: 17705.37 | S6: 3110.95 | T6: =PROPER(TRIM(SUBSTITUTE(Raw_Text_Fields!J7,CHAR(160)," "))) -> Paid | U6: =PROPER(TRIM(SUBSTITUTE(Raw_Text_Fields!K7,CHAR(160)," "))) -> Cancelled | V6: =IF(OR(P6<0,P6>0.5),0,P6) -> 0 | W6: =N6*O6*(1-V6) -> 20816.32 | X6: =W6-R6 -> 3110.95 | Y6: =IFERROR(X6/W6,0) -> 0.14944764 | Z6: =C6-B6 -> 3 | AA6: =IF(B6="","",TEXT(B6,"mmm")) -> Aug | AB6: =IF(B6="","",YEAR(B6)) -> 2025 | AD6: =IF(LEFT(AC6&IF(B6="","; Missing Order Date","")&IF(C6="","; Missing Ship Date","")&IF(P6<0,"; Invalid Discount (Negative)","")&IF(P6>0.5,"; Invalid Discount (Too High)","")&IF(Z6<0,"; Invalid Shipping Record (Ship Before Order)","")&IF(ABS(Q6-W6)>1,"; Sales Mismatch","")&IF(ABS(S6-X6)>1,"; Profit Mismatch","")&IF(COUNTIF($A$2:$A$913,A6)>1,"; Duplicate Order ID Conflict",""),2)="; ",MID(AC6&IF(B6="","; Missing Order Date","")&IF(C6="","; Missing Ship Date","")&IF(P6<0,"; Invalid Discount (Negative)","")&IF(P6>0.5,"; Invalid Discount (Too High)","")&IF(Z6<0,"; Invalid Shipping Record (Ship Before Order)","")&IF(ABS(Q6-W6)>1,"; Sales Mismatch","")&IF(ABS(S6-X6)>1,"; Profit Mismatch","")&IF(COUNTIF($A$2:$A$913,A6)>1,"; Duplicate Order ID Conflict",""),3,500),AC6&IF(B6="","; Missing Order Date","")&IF(C6="","; Missing Ship Date","")&IF(P6<0,"; Invalid Discount (Negative)","")&IF(P6>0.5,"; Invalid Discount (Too High)","")&IF(Z6<0,"; Invalid Shipping Record (Ship Before Order)","")&IF(ABS(Q6-W6)>1,"; Sales Mismatch","")&IF(ABS(S6-X6)>1,"; Profit Mismatch","")&IF(COUNTIF($A$2:$A$913,A6)>1,"; Duplicate Order ID Conflict","")) | AE6: =IF(OR(ISNUMBER(SEARCH("Invalid Discount",AD6)),ISNUMBER(SEARCH("Invalid Shipping Record",AD6)),ISNUMBER(SEARCH("Sales Mismatch",AD6)),ISNUMBER(SEARCH("Profit Mismatch",AD6)),ISNUMBER(SEARCH("Duplicate Order ID Conflict",AD6)),ISNUMBER(SEARCH("Missing Order Date",AD6)),ISNUMBER(SEARCH("Missing Ship Date",AD6))),"Invalid",IF(AD6<>"","Warning","Clean")) -> Clean
A7: ORD-2024-10006 | B7: 45436 | C7: 45440 | D7: CUST-6056 | E7: =PROPER(TRIM(SUBSTITUTE(Raw_Text_Fields!B8,CHAR(160)," "))) -> Vikram Iyer | F7: =PROPER(TRIM(SUBSTITUTE(Raw_Text_Fields!C8,CHAR(160)," "))) -> Small Business | G7: =PROPER(TRIM(SUBSTITUTE(Raw_Text_Fields!D8,CHAR(160)," "))) -> West | H7: =PROPER(TRIM(SUBSTITUTE(Raw_Text_Fields!E8,CHAR(160)," "))) -> Madhya Pradesh | I7: =PROPER(TRIM(SUBSTITUTE(Raw_Text_Fields!F8,CHAR(160)," "))) -> Indore | J7: =PROPER(TRIM(SUBSTITUTE(Raw_Text_Fields!G8,CHAR(160)," "))) -> Technology | K7: =PROPER(TRIM(SUBSTITUTE(Raw_Text_Fields!H8,CHAR(160)," "))) -> Accessories | L7: Pro Accessories 821 | M7: =PROPER(TRIM(SUBSTITUTE(Raw_Text_Fields!I8,CHAR(160)," "))) -> Same Day | N7: 3 | O7: 1053.11 | P7: 0.2 | Q7: 2527.46 | R7: 1533.58 | S7: 993.88 | T7: =PROPER(TRIM(SUBSTITUTE(Raw_Text_Fields!J8,CHAR(160)," "))) -> Paid | U7: =PROPER(TRIM(SUBSTITUTE(Raw_Text_Fields!K8,CHAR(160)," "))) -> Completed | V7: =IF(OR(P7<0,P7>0.5),0,P7) -> 0.2 | W7: =N7*O7*(1-V7) -> 2527.464 | X7: =W7-R7 -> 993.884 | Y7: =IFERROR(X7/W7,0) -> 0.39323369 | Z7: =C7-B7 -> 4 | AA7: =IF(B7="","",TEXT(B7,"mmm")) -> May | AB7: =IF(B7="","",YEAR(B7)) -> 2024 | AD7: =IF(LEFT(AC7&IF(B7="","; Missing Order Date","")&IF(C7="","; Missing Ship Date","")&IF(P7<0,"; Invalid Discount (Negative)","")&IF(P7>0.5,"; Invalid Discount (Too High)","")&IF(Z7<0,"; Invalid Shipping Record (Ship Before Order)","")&IF(ABS(Q7-W7)>1,"; Sales Mismatch","")&IF(ABS(S7-X7)>1,"; Profit Mismatch","")&IF(COUNTIF($A$2:$A$913,A7)>1,"; Duplicate Order ID Conflict",""),2)="; ",MID(AC7&IF(B7="","; Missing Order Date","")&IF(C7="","; Missing Ship Date","")&IF(P7<0,"; Invalid Discount (Negative)","")&IF(P7>0.5,"; Invalid Discount (Too High)","")&IF(Z7<0,"; Invalid Shipping Record (Ship Before Order)","")&IF(ABS(Q7-W7)>1,"; Sales Mismatch","")&IF(ABS(S7-X7)>1,"; Profit Mismatch","")&IF(COUNTIF($A$2:$A$913,A7)>1,"; Duplicate Order ID Conflict",""),3,500),AC7&IF(B7="","; Missing Order Date","")&IF(C7="","; Missing Ship Date","")&IF(P7<0,"; Invalid Discount (Negative)","")&IF(P7>0.5,"; Invalid Discount (Too High)","")&IF(Z7<0,"; Invalid Shipping Record (Ship Before Order)","")&IF(ABS(Q7-W7)>1,"; Sales Mismatch","")&IF(ABS(S7-X7)>1,"; Profit Mismatch","")&IF(COUNTIF($A$2:$A$913,A7)>1,"; Duplicate Order ID Conflict","")) | AE7: =IF(OR(ISNUMBER(SEARCH("Invalid Discount",AD7)),ISNUMBER(SEARCH("Invalid Shipping Record",AD7)),ISNUMBER(SEARCH("Sales Mismatch",AD7)),ISNUMBER(SEARCH("Profit Mismatch",AD7)),ISNUMBER(SEARCH("Duplicate Order ID Conflict",AD7)),ISNUMBER(SEARCH("Missing Order Date",AD7)),ISNUMBER(SEARCH("Missing Ship Date",AD7))),"Invalid",IF(AD7<>"","Warning","Clean")) -> Clean
A8: ORD-2025-10007 | B8: 45757 | C8: 45763 | D8: CUST-3656 | E8: =PROPER(TRIM(SUBSTITUTE(Raw_Text_Fields!B9,CHAR(160)," "))) -> Neha Gupta | F8: =PROPER(TRIM(SUBSTITUTE(Raw_Text_Fields!C9,CHAR(160)," "))) -> Consumer | G8: =PROPER(TRIM(SUBSTITUTE(Raw_Text_Fields!D9,CHAR(160)," "))) -> East | H8: =PROPER(TRIM(SUBSTITUTE(Raw_Text_Fields!E9,CHAR(160)," "))) -> Odisha | I8: =PROPER(TRIM(SUBSTITUTE(Raw_Text_Fields!F9,CHAR(160)," "))) -> Bhubaneswar | J8: =PROPER(TRIM(SUBSTITUTE(Raw_Text_Fields!G9,CHAR(160)," "))) -> Technology | K8: =PROPER(TRIM(SUBSTITUTE(Raw_Text_Fields!H9,CHAR(160)," "))) -> Copiers | L8: Eco Copiers 790 | M8: =PROPER(TRIM(SUBSTITUTE(Raw_Text_Fields!I9,CHAR(160)," "))) -> Standard Class | N8: 4 | O8: 1719.87 | P8: 0.15 | Q8: 5847.56 | R8: 4727.25 | S8: 1120.31 | T8: =PROPER(TRIM(SUBSTITUTE(Raw_Text_Fields!J9,CHAR(160)," "))) -> Paid | U8: =PROPER(TRIM(SUBSTITUTE(Raw_Text_Fields!K9,CHAR(160)," "))) -> Completed | V8: =IF(OR(P8<0,P8>0.5),0,P8) -> 0.15 | W8: =N8*O8*(1-V8) -> 5847.558 | X8: =W8-R8 -> 1120.308 | Y8: =IFERROR(X8/W8,0) -> 0.19158562 | Z8: =C8-B8 -> 6 | AA8: =IF(B8="","",TEXT(B8,"mmm")) -> Apr | AB8: =IF(B8="","",YEAR(B8)) -> 2025 | AD8: =IF(LEFT(AC8&IF(B8="","; Missing Order Date","")&IF(C8="","; Missing Ship Date","")&IF(P8<0,"; Invalid Discount (Negative)","")&IF(P8>0.5,"; Invalid Discount (Too High)","")&IF(Z8<0,"; Invalid Shipping Record (Ship Before Order)","")&IF(ABS(Q8-W8)>1,"; Sales Mismatch","")&IF(ABS(S8-X8)>1,"; Profit Mismatch","")&IF(COUNTIF($A$2:$A$913,A8)>1,"; Duplicate Order ID Conflict",""),2)="; ",MID(AC8&IF(B8="","; Missing Order Date","")&IF(C8="","; Missing Ship Date","")&IF(P8<0,"; Invalid Discount (Negative)","")&IF(P8>0.5,"; Invalid Discount (Too High)","")&IF(Z8<0,"; Invalid Shipping Record (Ship Before Order)","")&IF(ABS(Q8-W8)>1,"; Sales Mismatch","")&IF(ABS(S8-X8)>1,"; Profit Mismatch","")&IF(COUNTIF($A$2:$A$913,A8)>1,"; Duplicate Order ID Conflict",""),3,500),AC8&IF(B8="","; Missing Order Date","")&IF(C8="","; Missing Ship Date","")&IF(P8<0,"; Invalid Discount (Negative)","")&IF(P8>0.5,"; Invalid Discount (Too High)","")&IF(Z8<0,"; Invalid Shipping Record (Ship Before Order)","")&IF(ABS(Q8-W8)>1,"; Sales Mismatch","")&IF(ABS(S8-X8)>1,"; Profit Mismatch","")&IF(COUNTIF($A$2:$A$913,A8)>1,"; Duplicate Order ID Conflict","")) | AE8: =IF(OR(ISNUMBER(SEARCH("Invalid Discount",AD8)),ISNUMBER(SEARCH("Invalid Shipping Record",AD8)),ISNUMBER(SEARCH("Sales Mismatch",AD8)),ISNUMBER(SEARCH("Profit Mismatch",AD8)),ISNUMBER(SEARCH("Duplicate Order ID Conflict",AD8)),ISNUMBER(SEARCH("Missing Order Date",AD8)),ISNUMBER(SEARCH("Missing Ship Date",AD8))),"Invalid",IF(AD8<>"","Warning","Clean")) -> Clean
A9: ORD-2025-10008 | B9: 45711 | C9: 45714 | D9: CUST-4683 | E9: =PROPER(TRIM(SUBSTITUTE(Raw_Text_Fields!B10,CHAR(160)," "))) -> Isha Nair | F9: =PROPER(TRIM(SUBSTITUTE(Raw_Text_Fields!C10,CHAR(160)," "))) -> Small Business | G9: =PROPER(TRIM(SUBSTITUTE(Raw_Text_Fields!D10,CHAR(160)," "))) -> South | H9: =PROPER(TRIM(SUBSTITUTE(Raw_Text_Fields!E10,CHAR(160)," "))) -> Andhra Pradesh | I9: =PROPER(TRIM(SUBSTITUTE(Raw_Text_Fields!F10,CHAR(160)," "))) -> Vijayawada | J9: =PROPER(TRIM(SUBSTITUTE(Raw_Text_Fields!G10,CHAR(160)," "))) -> Office Supplies | K9: =PROPER(TRIM(SUBSTITUTE(Raw_Text_Fields!H10,CHAR(160)," "))) -> Art | L9: Eco Art 848 | M9: =PROPER(TRIM(SUBSTITUTE(Raw_Text_Fields!I10,CHAR(160)," "))) -> First Class | N9: 1 | O9: 2980.71 | P9: 0 | Q9: 2980.71 | R9: 2357.22 | S9: 623.49 | T9: =PROPER(TRIM(SUBSTITUTE(Raw_Text_Fields!J10,CHAR(160)," "))) -> Paid | U9: =PROPER(TRIM(SUBSTITUTE(Raw_Text_Fields!K10,CHAR(160)," "))) -> Completed | V9: =IF(OR(P9<0,P9>0.5),0,P9) -> 0 | W9: =N9*O9*(1-V9) -> 2980.71 | X9: =W9-R9 -> 623.49 | Y9: =IFERROR(X9/W9,0) -> 0.209175 | Z9: =C9-B9 -> 3 | AA9: =IF(B9="","",TEXT(B9,"mmm")) -> Feb | AB9: =IF(B9="","",YEAR(B9)) -> 2025 | AD9: =IF(LEFT(AC9&IF(B9="","; Missing Order Date","")&IF(C9="","; Missing Ship Date","")&IF(P9<0,"; Invalid Discount (Negative)","")&IF(P9>0.5,"; Invalid Discount (Too High)","")&IF(Z9<0,"; Invalid Shipping Record (Ship Before Order)","")&IF(ABS(Q9-W9)>1,"; Sales Mismatch","")&IF(ABS(S9-X9)>1,"; Profit Mismatch","")&IF(COUNTIF($A$2:$A$913,A9)>1,"; Duplicate Order ID Conflict",""),2)="; ",MID(AC9&IF(B9="","; Missing Order Date","")&IF(C9="","; Missing Ship Date","")&IF(P9<0,"; Invalid Discount (Negative)","")&IF(P9>0.5,"; Invalid Discount (Too High)","")&IF(Z9<0,"; Invalid Shipping Record (Ship Before Order)","")&IF(ABS(Q9-W9)>1,"; Sales Mismatch","")&IF(ABS(S9-X9)>1,"; Profit Mismatch","")&IF(COUNTIF($A$2:$A$913,A9)>1,"; Duplicate Order ID Conflict",""),3,500),AC9&IF(B9="","; Missing Order Date","")&IF(C9="","; Missing Ship Date","")&IF(P9<0,"; Invalid Discount (Negative)","")&IF(P9>0.5,"; Invalid Discount (Too High)","")&IF(Z9<0,"; Invalid Shipping Record (Ship Before Order)","")&IF(ABS(Q9-W9)>1,"; Sales Mismatch","")&IF(ABS(S9-X9)>1,"; Profit Mismatch","")&IF(COUNTIF($A$2:$A$913,A9)>1,"; Duplicate Order ID Conflict","")) | AE9: =IF(OR(ISNUMBER(SEARCH("Invalid Discount",AD9)),ISNUMBER(SEARCH("Invalid Shipping Record",AD9)),ISNUMBER(SEARCH("Sales Mismatch",AD9)),ISNUMBER(SEARCH("Profit Mismatch",AD9)),ISNUMBER(SEARCH("Duplicate Order ID Conflict",AD9)),ISNUMBER(SEARCH("Missing Order Date",AD9)),ISNUMBER(SEARCH("Missing Ship Date",AD9))),"Invalid",IF(AD9<>"","Warning","Clean")) -> Clean
A10: ORD-2024-10009 | B10: 45601 | C10: 45606 | D10: CUST-2598 | E10: =PROPER(TRIM(SUBSTITUTE(Raw_Text_Fields!B11,CHAR(160)," "))) -> Aditi Sen | F10: =PROPER(TRIM(SUBSTITUTE(Raw_Text_Fields!C11,CHAR(160)," "))) -> Corporate | G10: =PROPER(TRIM(SUBSTITUTE(Raw_Text_Fields!D11,CHAR(160)," "))) -> South | H10: =PROPER(TRIM(SUBSTITUTE(Raw_Text_Fields!E11,CHAR(160)," "))) -> Telangana | I10: =PROPER(TRIM(SUBSTITUTE(Raw_Text_Fields!F11,CHAR(160)," "))) -> Hyderabad | J10: =PROPER(TRIM(SUBSTITUTE(Raw_Text_Fields!G11,CHAR(160)," "))) -> Office Supplies | K10: =PROPER(TRIM(SUBSTITUTE(Raw_Text_Fields!H11,CHAR(160)," "))) -> Labels | L10: Classic Labels 815 | M10: =PROPER(TRIM(SUBSTITUTE(Raw_Text_Fields!I11,CHAR(160)," "))) -> First Class | N10: 8 | O10: 3134.2 | P10: 0 | Q10: 25073.6 | R10: 17347.23 | S10: 7726.37 | T10: =PROPER(TRIM(SUBSTITUTE(Raw_Text_Fields!J11,CHAR(160)," "))) -> Paid | U10: =PROPER(TRIM(SUBSTITUTE(Raw_Text_Fields!K11,CHAR(160)," "))) -> Completed | V10: =IF(OR(P10<0,P10>0.5),0,P10) -> 0 | W10: =N10*O10*(1-V10) -> 25073.6 | X10: =W10-R10 -> 7726.37 | Y10: =IFERROR(X10/W10,0) -> 0.30814761 | Z10: =C10-B10 -> 5 | AA10: =IF(B10="","",TEXT(B10,"mmm")) -> Nov | AB10: =IF(B10="","",YEAR(B10)) -> 2024 | AD10: =IF(LEFT(AC10&IF(B10="","; Missing Order Date","")&IF(C10="","; Missing Ship Date","")&IF(P10<0,"; Invalid Discount (Negative)","")&IF(P10>0.5,"; Invalid Discount (Too High)","")&IF(Z10<0,"; Invalid Shipping Record (Ship Before Order)","")&IF(ABS(Q10-W10)>1,"; Sales Mismatch","")&IF(ABS(S10-X10)>1,"; Profit Mismatch","")&IF(COUNTIF($A$2:$A$913,A10)>1,"; Duplicate Order ID Conflict",""),2)="; ",MID(AC10&IF(B10="","; Missing Order Date","")&IF(C10="","; Missing Ship Date","")&IF(P10<0,"; Invalid Discount (Negative)","")&IF(P10>0.5,"; Invalid Discount (Too High)","")&IF(Z10<0,"; Invalid Shipping Record (Ship Before Order)","")&IF(ABS(Q10-W10)>1,"; Sales Mismatch","")&IF(ABS(S10-X10)>1,"; Profit Mismatch","")&IF(COUNTIF($A$2:$A$913,A10)>1,"; Duplicate Order ID Conflict",""),3,500),AC10&IF(B10="","; Missing Order Date","")&IF(C10="","; Missing Ship Date","")&IF(P10<0,"; Invalid Discount (Negative)","")&IF(P10>0.5,"; Invalid Discount (Too High)","")&IF(Z10<0,"; Invalid Shipping Record (Ship Before Order)","")&IF(ABS(Q10-W10)>1,"; Sales Mismatch","")&IF(ABS(S10-X10)>1,"; Profit Mismatch","")&IF(COUNTIF($A$2:$A$913,A10)>1,"; Duplicate Order ID Conflict","")) | AE10: =IF(OR(ISNUMBER(SEARCH("Invalid Discount",AD10)),ISNUMBER(SEARCH("Invalid Shipping Record",AD10)),ISNUMBER(SEARCH("Sales Mismatch",AD10)),ISNUMBER(SEARCH("Profit Mismatch",AD10)),ISNUMBER(SEARCH("Duplicate Order ID Conflict",AD10)),ISNUMBER(SEARCH("Missing Order Date",AD10)),ISNUMBER(SEARCH("Missing Ship Date",AD10))),"Invalid",IF(AD10<>"","Warning","Clean")) -> Clean
A11: ORD-2025-10010 | B11: 45907 | C11: 45912 | D11: CUST-2483 | E11: =PROPER(TRIM(SUBSTITUTE(Raw_Text_Fields!B12,CHAR(160)," "))) -> Mira Das | F11: =PROPER(TRIM(SUBSTITUTE(Raw_Text_Fields!C12,CHAR(160)," "))) -> Home Office | G11: =PROPER(TRIM(SUBSTITUTE(Raw_Text_Fields!D12,CHAR(160)," "))) -> South | H11: =PROPER(TRIM(SUBSTITUTE(Raw_Text_Fields!E12,CHAR(160)," "))) -> Telangana | I11: =PROPER(TRIM(SUBSTITUTE(Raw_Text_Fields!F12,CHAR(160)," "))) -> Hyderabad | J11: =PROPER(TRIM(SUBSTITUTE(Raw_Text_Fields!G12,CHAR(160)," "))) -> Office Supplies | K11: =PROPER(TRIM(SUBSTITUTE(Raw_Text_Fields!H12,CHAR(160)," "))) -> Paper | L11: Pro Paper 622 | M11: =PROPER(TRIM(SUBSTITUTE(Raw_Text_Fields!I12,CHAR(160)," "))) -> Second Class | N11: 9 | O11: 852.04 | P11: 0.2 | Q11: 6134.69 | R11: 3800.19 | S11: 2334.5 | T11: =PROPER(TRIM(SUBSTITUTE(Raw_Text_Fields!J12,CHAR(160)," "))) -> Paid | U11: =PROPER(TRIM(SUBSTITUTE(Raw_Text_Fields!K12,CHAR(160)," "))) -> Completed | V11: =IF(OR(P11<0,P11>0.5),0,P11) -> 0.2 | W11: =N11*O11*(1-V11) -> 6134.688 | X11: =W11-R11 -> 2334.498 | Y11: =IFERROR(X11/W11,0) -> 0.38054062 | Z11: =C11-B11 -> 5 | AA11: =IF(B11="","",TEXT(B11,"mmm")) -> Sep | AB11: =IF(B11="","",YEAR(B11)) -> 2025 | AD11: =IF(LEFT(AC11&IF(B11="","; Missing Order Date","")&IF(C11="","; Missing Ship Date","")&IF(P11<0,"; Invalid Discount (Negative)","")&IF(P11>0.5,"; Invalid Discount (Too High)","")&IF(Z11<0,"; Invalid Shipping Record (Ship Before Order)","")&IF(ABS(Q11-W11)>1,"; Sales Mismatch","")&IF(ABS(S11-X11)>1,"; Profit Mismatch","")&IF(COUNTIF($A$2:$A$913,A11)>1,"; Duplicate Order ID Conflict",""),2)="; ",MID(AC11&IF(B11="","; Missing Order Date","")&IF(C11="","; Missing Ship Date","")&IF(P11<0,"; Invalid Discount (Negative)","")&IF(P11>0.5,"; Invalid Discount (Too High)","")&IF(Z11<0,"; Invalid Shipping Record (Ship Before Order)","")&IF(ABS(Q11-W11)>1,"; Sales Mismatch","")&IF(ABS(S11-X11)>1,"; Profit Mismatch","")&IF(COUNTIF($A$2:$A$913,A11)>1,"; Duplicate Order ID Conflict",""),3,500),AC11&IF(B11="","; Missing Order Date","")&IF(C11="","; Missing Ship Date","")&IF(P11<0,"; Invalid Discount (Negative)","")&IF(P11>0.5,"; Invalid Discount (Too High)","")&IF(Z11<0,"; Invalid Shipping Record (Ship Before Order)","")&IF(ABS(Q11-W11)>1,"; Sales Mismatch","")&IF(ABS(S11-X11)>1,"; Profit Mismatch","")&IF(COUNTIF($A$2:$A$913,A11)>1,"; Duplicate Order ID Conflict","")) | AE11: =IF(OR(ISNUMBER(SEARCH("Invalid Discount",AD11)),ISNUMBER(SEARCH("Invalid Shipping Record",AD11)),ISNUMBER(SEARCH("Sales Mismatch",AD11)),ISNUMBER(SEARCH("Profit Mismatch",AD11)),ISNUMBER(SEARCH("Duplicate Order ID Conflict",AD11)),ISNUMBER(SEARCH("Missing Order Date",AD11)),ISNUMBER(SEARCH("Missing Ship Date",AD11))),"Invalid",IF(AD11<>"","Warning","Clean")) -> Clean
A12: ORD-2025-10011 | B12: 45797 | C12: 45797 | D12: CUST-8092 | E12: =PROPER(TRIM(SUBSTITUTE(Raw_Text_Fields!B13,CHAR(160)," "))) -> Ananya Rao | F12: =PROPER(TRIM(SUBSTITUTE(Raw_Text_Fields!C13,CHAR(160)," "))) -> Corporate | G12: =PROPER(TRIM(SUBSTITUTE(Raw_Text_Fields!D13,CHAR(160)," "))) -> East | H12: =PROPER(TRIM(SUBSTITUTE(Raw_Text_Fields!E13,CHAR(160)," "))) -> West Bengal | I12: =PROPER(TRIM(SUBSTITUTE(Raw_Text_Fields!F13,CHAR(160)," "))) -> Kolkata | J12: =PROPER(TRIM(SUBSTITUTE(Raw_Text_Fields!G13,CHAR(160)," "))) -> Office Supplies | K12: =PROPER(TRIM(SUBSTITUTE(Raw_Text_Fields!H13,CHAR(160)," "))) -> Labels | L12: Prime Labels 644 | M12: =PROPER(TRIM(SUBSTITUTE(Raw_Text_Fields!I13,CHAR(160)," "))) -> Second Class | N12: 3 | O12: 3534.83 | P12: 0.05 | Q12: 10074.27 | R12: 6048.27 | S12: 4026 | T12: =PROPER(TRIM(SUBSTITUTE(Raw_Text_Fields!J13,CHAR(160)," "))) -> Refunded | U12: =PROPER(TRIM(SUBSTITUTE(Raw_Text_Fields!K13,CHAR(160)," "))) -> Returned | V12: =IF(OR(P12<0,P12>0.5),0,P12) -> 0.05 | W12: =N12*O12*(1-V12) -> 10074.265 | X12: =W12-R12 -> 4025.9955 | Y12: =IFERROR(X12/W12,0) -> 0.39963167 | Z12: =C12-B12 -> 0 | AA12: =IF(B12="","",TEXT(B12,"mmm")) -> May | AB12: =IF(B12="","",YEAR(B12)) -> 2025 | AD12: =IF(LEFT(AC12&IF(B12="","; Missing Order Date","")&IF(C12="","; Missing Ship Date","")&IF(P12<0,"; Invalid Discount (Negative)","")&IF(P12>0.5,"; Invalid Discount (Too High)","")&IF(Z12<0,"; Invalid Shipping Record (Ship Before Order)","")&IF(ABS(Q12-W12)>1,"; Sales Mismatch","")&IF(ABS(S12-X12)>1,"; Profit Mismatch","")&IF(COUNTIF($A$2:$A$913,A12)>1,"; Duplicate Order ID Conflict",""),2)="; ",MID(AC12&IF(B12="","; Missing Order Date","")&IF(C12="","; Missing Ship Date","")&IF(P12<0,"; Invalid Discount (Negative)","")&IF(P12>0.5,"; Invalid Discount (Too High)","")&IF(Z12<0,"; Invalid Shipping Record (Ship Before Order)","")&IF(ABS(Q12-W12)>1,"; Sales Mismatch","")&IF(ABS(S12-X12)>1,"; Profit Mismatch","")&IF(COUNTIF($A$2:$A$913,A12)>1,"; Duplicate Order ID Conflict",""),3,500),AC12&IF(B12="","; Missing Order Date","")&IF(C12="","; Missing Ship Date","")&IF(P12<0,"; Invalid Discount (Negative)","")&IF(P12>0.5,"; Invalid Discount (Too High)","")&IF(Z12<0,"; Invalid Shipping Record (Ship Before Order)","")&IF(ABS(Q12-W12)>1,"; Sales Mismatch","")&IF(ABS(S12-X12)>1,"; Profit Mismatch","")&IF(COUNTIF($A$2:$A$913,A12)>1,"; Duplicate Order ID Conflict","")) | AE12: =IF(OR(ISNUMBER(SEARCH("Invalid Discount",AD12)),ISNUMBER(SEARCH("Invalid Shipping Record",AD12)),ISNUMBER(SEARCH("Sales Mismatch",AD12)),ISNUMBER(SEARCH("Profit Mismatch",AD12)),ISNUMBER(SEARCH("Duplicate Order ID Conflict",AD12)),ISNUMBER(SEARCH("Missing Order Date",AD12)),ISNUMBER(SEARCH("Missing Ship Date",AD12))),"Invalid",IF(AD12<>"","Warning","Clean")) -> Clean
A13: ORD-2024-10012 | B13: 45495 | C13: 45496 | D13: CUST-6528 | E13: =PROPER(TRIM(SUBSTITUTE(Raw_Text_Fields!B14,CHAR(160)," "))) -> Vikram Iyer | F13: =PROPER(TRIM(SUBSTITUTE(Raw_Text_Fields!C14,CHAR(160)," "))) -> Small Business | G13: =PROPER(TRIM(SUBSTITUTE(Raw_Text_Fields!D14,CHAR(160)," "))) -> East | H13: =PROPER(TRIM(SUBSTITUTE(Raw_Text_Fields!E14,CHAR(160)," "))) -> Odisha | I13: =PROPER(TRIM(SUBSTITUTE(Raw_Text_Fields!F14,CHAR(160)," "))) -> Bhubaneswar | J13: =PROPER(TRIM(SUBSTITUTE(Raw_Text_Fields!G14,CHAR(160)," "))) -> Technology | K13: =PROPER(TRIM(SUBSTITUTE(Raw_Text_Fields!H14,CHAR(160)," "))) -> Accessories | L13: Smart Accessories 603 | M13: =PROPER(TRIM(SUBSTITUTE(Raw_Text_Fields!I14,CHAR(160)," "))) -> Same Day | N13: 6 | O13: 2005.95 | P13: 0.2 | Q13: 9628.56 | R13: 8038.59 | S13: 1589.97 | T13: =PROPER(TRIM(SUBSTITUTE(Raw_Text_Fields!J14,CHAR(160)," "))) -> Paid | U13: =PROPER(TRIM(SUBSTITUTE(Raw_Text_Fields!K14,CHAR(160)," "))) -> Completed | V13: =IF(OR(P13<0,P13>0.5),0,P13) -> 0.2 | W13: =N13*O13*(1-V13) -> 9628.56 | X13: =W13-R13 -> 1589.97 | Y13: =IFERROR(X13/W13,0) -> 0.16513061 | Z13: =C13-B13 -> 1 | AA13: =IF(B13="","",TEXT(B13,"mmm")) -> Jul | AB13: =IF(B13="","",YEAR(B13)) -> 2024 | AD13: =IF(LEFT(AC13&IF(B13="","; Missing Order Date","")&IF(C13="","; Missing Ship Date","")&IF(P13<0,"; Invalid Discount (Negative)","")&IF(P13>0.5,"; Invalid Discount (Too High)","")&IF(Z13<0,"; Invalid Shipping Record (Ship Before Order)","")&IF(ABS(Q13-W13)>1,"; Sales Mismatch","")&IF(ABS(S13-X13)>1,"; Profit Mismatch","")&IF(COUNTIF($A$2:$A$913,A13)>1,"; Duplicate Order ID Conflict",""),2)="; ",MID(AC13&IF(B13="","; Missing Order Date","")&IF(C13="","; Missing Ship Date","")&IF(P13<0,"; Invalid Discount (Negative)","")&IF(P13>0.5,"; Invalid Discount (Too High)","")&IF(Z13<0,"; Invalid Shipping Record (Ship Before Order)","")&IF(ABS(Q13-W13)>1,"; Sales Mismatch","")&IF(ABS(S13-X13)>1,"; Profit Mismatch","")&IF(COUNTIF($A$2:$A$913,A13)>1,"; Duplicate Order ID Conflict",""),3,500),AC13&IF(B13="","; Missing Order Date","")&IF(C13="","; Missing Ship Date","")&IF(P13<0,"; Invalid Discount (Negative)","")&IF(P13>0.5,"; Invalid Discount (Too High)","")&IF(Z13<0,"; Invalid Shipping Record (Ship Before Order)","")&IF(ABS(Q13-W13)>1,"; Sales Mismatch","")&IF(ABS(S13-X13)>1,"; Profit Mismatch","")&IF(COUNTIF($A$2:$A$913,A13)>1,"; Duplicate Order ID Conflict","")) | AE13: =IF(OR(ISNUMBER(SEARCH("Invalid Discount",AD13)),ISNUMBER(SEARCH("Invalid Shipping Record",AD13)),ISNUMBER(SEARCH("Sales Mismatch",AD13)),ISNUMBER(SEARCH("Profit Mismatch",AD13)),ISNUMBER(SEARCH("Duplicate Order ID Conflict",AD13)),ISNUMBER(SEARCH("Missing Order Date",AD13)),ISNUMBER(SEARCH("Missing Ship Date",AD13))),"Invalid",IF(AD13<>"","Warning","Clean")) -> Clean
... A33: ORD-2025-10032 | B33: 45823 | C33: 45827 | D33: CUST-7867 | E33: =PROPER(TRIM(SUBSTITUTE(Raw_Text_Fields!B34,CHAR(160)," "))) -> Karan Malhotra | F33: =PROPER(TRIM(SUBSTITUTE(Raw_Text_Fields!C34,CHAR(160)," "))) -> Small Business | G33: =PROPER(TRIM(SUBSTITUTE(Raw_Text_Fields!D34,CHAR(160)," "))) -> West | H33: =PROPER(TRIM(SUBSTITUTE(Raw_Text_Fields!E34,CHAR(160)," "))) -> Madhya Pradesh | I33: =PROPER(TRIM(SUBSTITUTE(Raw_Text_Fields!F34,CHAR(160)," "))) -> Indore | J33: =PROPER(TRIM(SUBSTITUTE(Raw_Text_Fields!G34,CHAR(160)," "))) -> Office Supplies | K33: =PROPER(TRIM(SUBSTITUTE(Raw_Text_Fields!H34,CHAR(160)," "))) -> Paper | L33: Pro Paper 959 | M33: =PROPER(TRIM(SUBSTITUTE(Raw_Text_Fields!I34,CHAR(160)," "))) -> Second Class | N33: 9 | O33: 3092.55 | P33: 0 | Q33: 27832.95 | R33: 17769.75 | S33: 10063.2 | T33: =PROPER(TRIM(SUBSTITUTE(Raw_Text_Fields!J34,CHAR(160)," "))) -> Failed | U33: =PROPER(TRIM(SUBSTITUTE(Raw_Text_Fields!K34,CHAR(160)," "))) -> Returned | V33: =IF(OR(P33<0,P33>0.5),0,P33) -> 0 | W33: =N33*O33*(1-V33) -> 27832.95 | X33: =W33-R33 -> 10063.2 | Y33: =IFERROR(X33/W33,0) -> 0.36155708 | Z33: =C33-B33 -> 4 | AA33: =IF(B33="","",TEXT(B33,"mmm")) -> Jun | AB33: =IF(B33="","",YEAR(B33)) -> 2025 | AD33: =IF(LEFT(AC33&IF(B33="","; Missing Order Date","")&IF(C33="","; Missing Ship Date","")&IF(P33<0,"; Invalid Discount (Negative)","")&IF(P33>0.5,"; Invalid Discount (Too High)","")&IF(Z33<0,"; Invalid Shipping Record (Ship Before Order)","")&IF(ABS(Q33-W33)>1,"; Sales Mismatch","")&IF(ABS(S33-X33)>1,"; Profit Mismatch","")&IF(COUNTIF($A$2:$A$913,A33)>1,"; Duplicate Order ID Conflict",""),2)="; ",MID(AC33&IF(B33="","; Missing Order Date","")&IF(C33="","; Missing Ship Date","")&IF(P33<0,"; Invalid Discount (Negative)","")&IF(P33>0.5,"; Invalid Discount (Too High)","")&IF(Z33<0,"; Invalid Shipping Record (Ship Before Order)","")&IF(ABS(Q33-W33)>1,"; Sales Mismatch","")&IF(ABS(S33-X33)>1,"; Profit Mismatch","")&IF(COUNTIF($A$2:$A$913,A33)>1,"; Duplicate Order ID Conflict",""),3,500),AC33&IF(B33="","; Missing Order Date","")&IF(C33="","; Missing Ship Date","")&IF(P33<0,"; Invalid Discount (Negative)","")&IF(P33>0.5,"; Invalid Discount (Too High)","")&IF(Z33<0,"; Invalid Shipping Record (Ship Before Order)","")&IF(ABS(Q33-W33)>1,"; Sales Mismatch","")&IF(ABS(S33-X33)>1,"; Profit Mismatch","")&IF(COUNTIF($A$2:$A$913,A33)>1,"; Duplicate Order ID Conflict","")) | AE33: =IF(OR(ISNUMBER(SEARCH("Invalid Discount",AD33)),ISNUMBER(SEARCH("Invalid Shipping Record",AD33)),ISNUMBER(SEARCH("Sales Mismatch",AD33)),ISNUMBER(SEARCH("Profit Mismatch",AD33)),ISNUMBER(SEARCH("Duplicate Order ID Conflict",AD33)),ISNUMBER(SEARCH("Missing Order Date",AD33)),ISNUMBER(SEARCH("Missing Ship Date",AD33))),"Invalid",IF(AD33<>"","Warning","Clean")) -> Clean
A34: ORD-2024-10033 | B34: 45618 | C34: 45622 | D34: CUST-6509 | E34: =PROPER(TRIM(SUBSTITUTE(Raw_Text_Fields!B35,CHAR(160)," "))) -> Aarav Sharma | F34: =PROPER(TRIM(SUBSTITUTE(Raw_Text_Fields!C35,CHAR(160)," "))) -> Corporate | G34: =PROPER(TRIM(SUBSTITUTE(Raw_Text_Fields!D35,CHAR(160)," "))) -> South | H34: =PROPER(TRIM(SUBSTITUTE(Raw_Text_Fields!E35,CHAR(160)," "))) -> Andhra Pradesh | I34: =PROPER(TRIM(SUBSTITUTE(Raw_Text_Fields!F35,CHAR(160)," "))) -> Vijayawada | J34: =PROPER(TRIM(SUBSTITUTE(Raw_Text_Fields!G35,CHAR(160)," "))) -> Technology | K34: =PROPER(TRIM(SUBSTITUTE(Raw_Text_Fields!H35,CHAR(160)," "))) -> Phones | L34: Basic Phones 242 | M34: =PROPER(TRIM(SUBSTITUTE(Raw_Text_Fields!I35,CHAR(160)," "))) -> Second Class | N34: 3 | O34: 4001.25 | P34: 0 | Q34: 9002.81 | R34: 7529.92 | S34: 1472.89 | T34: =PROPER(TRIM(SUBSTITUTE(Raw_Text_Fields!J35,CHAR(160)," "))) -> Paid | U34: =PROPER(TRIM(SUBSTITUTE(Raw_Text_Fields!K35,CHAR(160)," "))) -> Completed | V34: =IF(OR(P34<0,P34>0.5),0,P34) -> 0 | W34: =N34*O34*(1-V34) -> 12003.75 | X34: =W34-R34 -> 4473.83 | Y34: =IFERROR(X34/W34,0) -> 0.3727027 | Z34: =C34-B34 -> 4 | AA34: =IF(B34="","",TEXT(B34,"mmm")) -> Nov | AB34: =IF(B34="","",YEAR(B34)) -> 2024 | AC34: Missing Discount (defaulted 0) | AD34: =IF(LEFT(AC34&IF(B34="","; Missing Order Date","")&IF(C34="","; Missing Ship Date","")&IF(P34<0,"; Invalid Discount (Negative)","")&IF(P34>0.5,"; Invalid Discount (Too High)","")&IF(Z34<0,"; Invalid Shipping Record (Ship Before Order)","")&IF(ABS(Q34-W34)>1,"; Sales Mismatch","")&IF(ABS(S34-X34)>1,"; Profit Mismatch","")&IF(COUNTIF($A$2:$A$913,A34)>1,"; Duplicate Order ID Conflict",""),2)="; ",MID(AC34&IF(B34="","; Missing Order Date","")&IF(C34="","; Missing Ship Date","")&IF(P34<0,"; Invalid Discount (Negative)","")&IF(P34>0.5,"; Invalid Discount (Too High)","")&IF(Z34<0,"; Invalid Shipping Record (Ship Before Order)","")&IF(ABS(Q34-W34)>1,"; Sales Mismatch","")&IF(ABS(S34-X34)>1,"; Profit Mismatch","")&IF(COUNTIF($A$2:$A$913,A34)>1,"; Duplicate Order ID Conflict",""),3,500),AC34&IF(B34="","; Missing Order Date","")&IF(C34="","; Missing Ship Date","")&IF(P34<0,"; Invalid Discount (Negative)","")&IF(P34>0.5,"; Invalid Discount (Too High)","")&IF(Z34<0,"; Invalid Shipping Record (Ship Before Order)","")&IF(ABS(Q34-W34)>1,"; Sales Mismatch","")&IF(ABS(S34-X34)>1,"; Profit Mismatch","")&IF(COUNTIF($A$2:$A$913,A34)>1,"; Duplicate Order ID Conflict","")) -> Missing Discount (defaulted 0); Sales Mismatch; Profit Mismatch | AE34: =IF(OR(ISNUMBER(SEARCH("Invalid Discount",AD34)),ISNUMBER(SEARCH("Invalid Shipping Record",AD34)),ISNUMBER(SEARCH("Sales Mismatch",AD34)),ISNUMBER(SEARCH("Profit Mismatch",AD34)),ISNUMBER(SEARCH("Duplicate Order ID Conflict",AD34)),ISNUMBER(SEARCH("Missing Order Date",AD34)),ISNUMBER(SEARCH("Missing Ship Date",AD34))),"Invalid",IF(AD34<>"","Warning","Clean")) -> Invalid
A35: ORD-2024-10034 | B35: 45495 | C35: 45500 | D35: CUST-6660 | E35: =PROPER(TRIM(SUBSTITUTE(Raw_Text_Fields!B36,CHAR(160)," "))) -> Priya Menon | F35: =PROPER(TRIM(SUBSTITUTE(Raw_Text_Fields!C36,CHAR(160)," "))) -> Home Office | G35: =PROPER(TRIM(SUBSTITUTE(Raw_Text_Fields!D36,CHAR(160)," "))) -> West | H35: =PROPER(TRIM(SUBSTITUTE(Raw_Text_Fields!E36,CHAR(160)," "))) -> Goa | I35: =PROPER(TRIM(SUBSTITUTE(Raw_Text_Fields!F36,CHAR(160)," "))) -> Panaji | J35: =PROPER(TRIM(SUBSTITUTE(Raw_Text_Fields!G36,CHAR(160)," "))) -> Furniture | K35: =PROPER(TRIM(SUBSTITUTE(Raw_Text_Fields!H36,CHAR(160)," "))) -> Tables | L35: Max Tables 836 | M35: =PROPER(TRIM(SUBSTITUTE(Raw_Text_Fields!I36,CHAR(160)," "))) -> Same Day | N35: 7 | O35: 492.41 | P35: 0.25 | Q35: 2585.15 | R35: 2070.73 | S35: 514.42 | T35: =PROPER(TRIM(SUBSTITUTE(Raw_Text_Fields!J36,CHAR(160)," "))) -> Paid | U35: =PROPER(TRIM(SUBSTITUTE(Raw_Text_Fields!K36,CHAR(160)," "))) -> Completed | V35: =IF(OR(P35<0,P35>0.5),0,P35) -> 0.25 | W35: =N35*O35*(1-V35) -> 2585.1525 | X35: =W35-R35 -> 514.4225 | Y35: =IFERROR(X35/W35,0) -> 0.19899116 | Z35: =C35-B35 -> 5 | AA35: =IF(B35="","",TEXT(B35,"mmm")) -> Jul | AB35: =IF(B35="","",YEAR(B35)) -> 2024 | AD35: =IF(LEFT(AC35&IF(B35="","; Missing Order Date","")&IF(C35="","; Missing Ship Date","")&IF(P35<0,"; Invalid Discount (Negative)","")&IF(P35>0.5,"; Invalid Discount (Too High)","")&IF(Z35<0,"; Invalid Shipping Record (Ship Before Order)","")&IF(ABS(Q35-W35)>1,"; Sales Mismatch","")&IF(ABS(S35-X35)>1,"; Profit Mismatch","")&IF(COUNTIF($A$2:$A$913,A35)>1,"; Duplicate Order ID Conflict",""),2)="; ",MID(AC35&IF(B35="","; Missing Order Date","")&IF(C35="","; Missing Ship Date","")&IF(P35<0,"; Invalid Discount (Negative)","")&IF(P35>0.5,"; Invalid Discount (Too High)","")&IF(Z35<0,"; Invalid Shipping Record (Ship Before Order)","")&IF(ABS(Q35-W35)>1,"; Sales Mismatch","")&IF(ABS(S35-X35)>1,"; Profit Mismatch","")&IF(COUNTIF($A$2:$A$913,A35)>1,"; Duplicate Order ID Conflict",""),3,500),AC35&IF(B35="","; Missing Order Date","")&IF(C35="","; Missing Ship Date","")&IF(P35<0,"; Invalid Discount (Negative)","")&IF(P35>0.5,"; Invalid Discount (Too High)","")&IF(Z35<0,"; Invalid Shipping Record (Ship Before Order)","")&IF(ABS(Q35-W35)>1,"; Sales Mismatch","")&IF(ABS(S35-X35)>1,"; Profit Mismatch","")&IF(COUNTIF($A$2:$A$913,A35)>1,"; Duplicate Order ID Conflict","")) | AE35: =IF(OR(ISNUMBER(SEARCH("Invalid Discount",AD35)),ISNUMBER(SEARCH("Invalid Shipping Record",AD35)),ISNUMBER(SEARCH("Sales Mismatch",AD35)),ISNUMBER(SEARCH("Profit Mismatch",AD35)),ISNUMBER(SEARCH("Duplicate Order ID Conflict",AD35)),ISNUMBER(SEARCH("Missing Order Date",AD35)),ISNUMBER(SEARCH("Missing Ship Date",AD35))),"Invalid",IF(AD35<>"","Warning","Clean")) -> Clean
A36: ORD-2025-10035 | B36: 45688 | C36: 45693 | D36: CUST-2392 | E36: =PROPER(TRIM(SUBSTITUTE(Raw_Text_Fields!B37,CHAR(160)," "))) -> Priya Menon | F36: =PROPER(TRIM(SUBSTITUTE(Raw_Text_Fields!C37,CHAR(160)," "))) -> Home Office | G36: =PROPER(TRIM(SUBSTITUTE(Raw_Text_Fields!D37,CHAR(160)," "))) -> East | H36: =PROPER(TRIM(SUBSTITUTE(Raw_Text_Fields!E37,CHAR(160)," "))) -> West Bengal | I36: =PROPER(TRIM(SUBSTITUTE(Raw_Text_Fields!F37,CHAR(160)," "))) -> Kolkata | J36: =PROPER(TRIM(SUBSTITUTE(Raw_Text_Fields!G37,CHAR(160)," "))) -> Furniture | K36: =PROPER(TRIM(SUBSTITUTE(Raw_Text_Fields!H37,CHAR(160)," "))) -> Chairs | L36: Elite Chairs 862 | M36: =PROPER(TRIM(SUBSTITUTE(Raw_Text_Fields!I37,CHAR(160)," "))) -> Unknown | N36: 2 | O36: 4159.69 | P36: 0.2 | Q36: 6655.5 | R36: 4340.21 | S36: 2607.32 | T36: =PROPER(TRIM(SUBSTITUTE(Raw_Text_Fields!J37,CHAR(160)," "))) -> Paid | U36: =PROPER(TRIM(SUBSTITUTE(Raw_Text_Fields!K37,CHAR(160)," "))) -> Completed | V36: =IF(OR(P36<0,P36>0.5),0,P36) -> 0.2 | W36: =N36*O36*(1-V36) -> 6655.504 | X36: =W36-R36 -> 2315.294 | Y36: =IFERROR(X36/W36,0) -> 0.34787658 | Z36: =C36-B36 -> 5 | AA36: =IF(B36="","",TEXT(B36,"mmm")) -> Jan | AB36: =IF(B36="","",YEAR(B36)) -> 2025 | AC36: Missing Ship Mode (filled Unknown) | AD36: =IF(LEFT(AC36&IF(B36="","; Missing Order Date","")&IF(C36="","; Missing Ship Date","")&IF(P36<0,"; Invalid Discount (Negative)","")&IF(P36>0.5,"; Invalid Discount (Too High)","")&IF(Z36<0,"; Invalid Shipping Record (Ship Before Order)","")&IF(ABS(Q36-W36)>1,"; Sales Mismatch","")&IF(ABS(S36-X36)>1,"; Profit Mismatch","")&IF(COUNTIF($A$2:$A$913,A36)>1,"; Duplicate Order ID Conflict",""),2)="; ",MID(AC36&IF(B36="","; Missing Order Date","")&IF(C36="","; Missing Ship Date","")&IF(P36<0,"; Invalid Discount (Negative)","")&IF(P36>0.5,"; Invalid Discount (Too High)","")&IF(Z36<0,"; Invalid Shipping Record (Ship Before Order)","")&IF(ABS(Q36-W36)>1,"; Sales Mismatch","")&IF(ABS(S36-X36)>1,"; Profit Mismatch","")&IF(COUNTIF($A$2:$A$913,A36)>1,"; Duplicate Order ID Conflict",""),3,500),AC36&IF(B36="","; Missing Order Date","")&IF(C36="","; Missing Ship Date","")&IF(P36<0,"; Invalid Discount (Negative)","")&IF(P36>0.5,"; Invalid Discount (Too High)","")&IF(Z36<0,"; Invalid Shipping Record (Ship Before Order)","")&IF(ABS(Q36-W36)>1,"; Sales Mismatch","")&IF(ABS(S36-X36)>1,"; Profit Mismatch","")&IF(COUNTIF($A$2:$A$913,A36)>1,"; Duplicate Order ID Conflict","")) -> Missing Ship Mode (filled Unknown); Profit Mismatch | AE36: =IF(OR(ISNUMBER(SEARCH("Invalid Discount",AD36)),ISNUMBER(SEARCH("Invalid Shipping Record",AD36)),ISNUMBER(SEARCH("Sales Mismatch",AD36)),ISNUMBER(SEARCH("Profit Mismatch",AD36)),ISNUMBER(SEARCH("Duplicate Order ID Conflict",AD36)),ISNUMBER(SEARCH("Missing Order Date",AD36)),ISNUMBER(SEARCH("Missing Ship Date",AD36))),"Invalid",IF(AD36<>"","Warning","Clean")) -> Invalid
A37: ORD-2024-10036 | B37: 45441 | C37: 45441 | D37: CUST-1611 | E37: =PROPER(TRIM(SUBSTITUTE(Raw_Text_Fields!B38,CHAR(160)," "))) -> Sneha Kapoor | F37: =PROPER(TRIM(SUBSTITUTE(Raw_Text_Fields!C38,CHAR(160)," "))) -> Small Business | G37: =PROPER(TRIM(SUBSTITUTE(Raw_Text_Fields!D38,CHAR(160)," "))) -> West | H37: =PROPER(TRIM(SUBSTITUTE(Raw_Text_Fields!E38,CHAR(160)," "))) -> Gujarat | I37: =PROPER(TRIM(SUBSTITUTE(Raw_Text_Fields!F38,CHAR(160)," "))) -> Ahmedabad | J37: =PROPER(TRIM(SUBSTITUTE(Raw_Text_Fields!G38,CHAR(160)," "))) -> Furniture | K37: =PROPER(TRIM(SUBSTITUTE(Raw_Text_Fields!H38,CHAR(160)," "))) -> Bookcases | L37: Prime Bookcases 414 | M37: =PROPER(TRIM(SUBSTITUTE(Raw_Text_Fields!I38,CHAR(160)," "))) -> Second Class | N37: 8 | O37: 2507.12 | P37: 0.05 | Q37: 19054.11 | R37: 15313.83 | S37: 3740.28 | T37: =PROPER(TRIM(SUBSTITUTE(Raw_Text_Fields!J38,CHAR(160)," "))) -> Pending | U37: =PROPER(TRIM(SUBSTITUTE(Raw_Text_Fields!K38,CHAR(160)," "))) -> Returned | V37: =IF(OR(P37<0,P37>0.5),0,P37) -> 0.05 | W37: =N37*O37*(1-V37) -> 19054.112 | X37: =W37-R37 -> 3740.282 | Y37: =IFERROR(X37/W37,0) -> 0.19629789 | Z37: =C37-B37 -> 0 | AA37: =IF(B37="","",TEXT(B37,"mmm")) -> May | AB37: =IF(B37="","",YEAR(B37)) -> 2024 | AD37: =IF(LEFT(AC37&IF(B37="","; Missing Order Date","")&IF(C37="","; Missing Ship Date","")&IF(P37<0,"; Invalid Discount (Negative)","")&IF(P37>0.5,"; Invalid Discount (Too High)","")&IF(Z37<0,"; Invalid Shipping Record (Ship Before Order)","")&IF(ABS(Q37-W37)>1,"; Sales Mismatch","")&IF(ABS(S37-X37)>1,"; Profit Mismatch","")&IF(COUNTIF($A$2:$A$913,A37)>1,"; Duplicate Order ID Conflict",""),2)="; ",MID(AC37&IF(B37="","; Missing Order Date","")&IF(C37="","; Missing Ship Date","")&IF(P37<0,"; Invalid Discount (Negative)","")&IF(P37>0.5,"; Invalid Discount (Too High)","")&IF(Z37<0,"; Invalid Shipping Record (Ship Before Order)","")&IF(ABS(Q37-W37)>1,"; Sales Mismatch","")&IF(ABS(S37-X37)>1,"; Profit Mismatch","")&IF(COUNTIF($A$2:$A$913,A37)>1,"; Duplicate Order ID Conflict",""),3,500),AC37&IF(B37="","; Missing Order Date","")&IF(C37="","; Missing Ship Date","")&IF(P37<0,"; Invalid Discount (Negative)","")&IF(P37>0.5,"; Invalid Discount (Too High)","")&IF(Z37<0,"; Invalid Shipping Record (Ship Before Order)","")&IF(ABS(Q37-W37)>1,"; Sales Mismatch","")&IF(ABS(S37-X37)>1,"; Profit Mismatch","")&IF(COUNTIF($A$2:$A$913,A37)>1,"; Duplicate Order ID Conflict","")) | AE37: =IF(OR(ISNUMBER(SEARCH("Invalid Discount",AD37)),ISNUMBER(SEARCH("Invalid Shipping Record",AD37)),ISNUMBER(SEARCH("Sales Mismatch",AD37)),ISNUMBER(SEARCH("Profit Mismatch",AD37)),ISNUMBER(SEARCH("Duplicate Order ID Conflict",AD37)),ISNUMBER(SEARCH("Missing Order Date",AD37)),ISNUMBER(SEARCH("Missing Ship Date",AD37))),"Invalid",IF(AD37<>"","Warning","Clean")) -> Clean
A38: ORD-2024-10037 | B38: 45590 | C38: 45593 | D38: CUST-8296 | E38: =PROPER(TRIM(SUBSTITUTE(Raw_Text_Fields!B39,CHAR(160)," "))) -> Rohan Mehta | F38: =PROPER(TRIM(SUBSTITUTE(Raw_Text_Fields!C39,CHAR(160)," "))) -> Corporate | G38: =PROPER(TRIM(SUBSTITUTE(Raw_Text_Fields!D39,CHAR(160)," "))) -> West | H38: =PROPER(TRIM(SUBSTITUTE(Raw_Text_Fields!E39,CHAR(160)," "))) -> Maharashtra | I38: =PROPER(TRIM(SUBSTITUTE(Raw_Text_Fields!F39,CHAR(160)," "))) -> Mumbai | J38: =PROPER(TRIM(SUBSTITUTE(Raw_Text_Fields!G39,CHAR(160)," "))) -> Furniture | K38: =PROPER(TRIM(SUBSTITUTE(Raw_Text_Fields!H39,CHAR(160)," "))) -> Bookcases | L38: Eco Bookcases 220 | M38: =PROPER(TRIM(SUBSTITUTE(Raw_Text_Fields!I39,CHAR(160)," "))) -> Second Class | N38: 3 | O38: 3126.47 | P38: 0 | Q38: 9379.41 | R38: 6670.85 | S38: 2708.56 | T38: =PROPER(TRIM(SUBSTITUTE(Raw_Text_Fields!J39,CHAR(160)," "))) -> Paid | U38: =PROPER(TRIM(SUBSTITUTE(Raw_Text_Fields!K39,CHAR(160)," "))) -> Returned | V38: =IF(OR(P38<0,P38>0.5),0,P38) -> 0 | W38: =N38*O38*(1-V38) -> 9379.41 | X38: =W38-R38 -> 2708.56 | Y38: =IFERROR(X38/W38,0) -> 0.28877723 | Z38: =C38-B38 -> 3 | AA38: =IF(B38="","",TEXT(B38,"mmm")) -> Oct | AB38: =IF(B38="","",YEAR(B38)) -> 2024 | AD38: =IF(LEFT(AC38&IF(B38="","; Missing Order Date","")&IF(C38="","; Missing Ship Date","")&IF(P38<0,"; Invalid Discount (Negative)","")&IF(P38>0.5,"; Invalid Discount (Too High)","")&IF(Z38<0,"; Invalid Shipping Record (Ship Before Order)","")&IF(ABS(Q38-W38)>1,"; Sales Mismatch","")&IF(ABS(S38-X38)>1,"; Profit Mismatch","")&IF(COUNTIF($A$2:$A$913,A38)>1,"; Duplicate Order ID Conflict",""),2)="; ",MID(AC38&IF(B38="","; Missing Order Date","")&IF(C38="","; Missing Ship Date","")&IF(P38<0,"; Invalid Discount (Negative)","")&IF(P38>0.5,"; Invalid Discount (Too High)","")&IF(Z38<0,"; Invalid Shipping Record (Ship Before Order)","")&IF(ABS(Q38-W38)>1,"; Sales Mismatch","")&IF(ABS(S38-X38)>1,"; Profit Mismatch","")&IF(COUNTIF($A$2:$A$913,A38)>1,"; Duplicate Order ID Conflict",""),3,500),AC38&IF(B38="","; Missing Order Date","")&IF(C38="","; Missing Ship Date","")&IF(P38<0,"; Invalid Discount (Negative)","")&IF(P38>0.5,"; Invalid Discount (Too High)","")&IF(Z38<0,"; Invalid Shipping Record (Ship Before Order)","")&IF(ABS(Q38-W38)>1,"; Sales Mismatch","")&IF(ABS(S38-X38)>1,"; Profit Mismatch","")&IF(COUNTIF($A$2:$A$913,A38)>1,"; Duplicate Order ID Conflict","")) | AE38: =IF(OR(ISNUMBER(SEARCH("Invalid Discount",AD38)),ISNUMBER(SEARCH("Invalid Shipping Record",AD38)),ISNUMBER(SEARCH("Sales Mismatch",AD38)),ISNUMBER(SEARCH("Profit Mismatch",AD38)),ISNUMBER(SEARCH("Duplicate Order ID Conflict",AD38)),ISNUMBER(SEARCH("Missing Order Date",AD38)),ISNUMBER(SEARCH("Missing Ship Date",AD38))),"Invalid",IF(AD38<>"","Warning","Clean")) -> Clean
A39: ORD-2025-10038 | B39: 45867 | C39: 45867 | D39: CUST-4646 | E39: =PROPER(TRIM(SUBSTITUTE(Raw_Text_Fields!B40,CHAR(160)," "))) -> Diya Patel | F39: =PROPER(TRIM(SUBSTITUTE(Raw_Text_Fields!C40,CHAR(160)," "))) -> Consumer | G39: =PROPER(TRIM(SUBSTITUTE(Raw_Text_Fields!D40,CHAR(160)," "))) -> West | H39: =PROPER(TRIM(SUBSTITUTE(Raw_Text_Fields!E40,CHAR(160)," "))) -> Maharashtra | I39: =PROPER(TRIM(SUBSTITUTE(Raw_Text_Fields!F40,CHAR(160)," "))) -> Mumbai | J39: =PROPER(TRIM(SUBSTITUTE(Raw_Text_Fields!G40,CHAR(160)," "))) -> Technology | K39: =PROPER(TRIM(SUBSTITUTE(Raw_Text_Fields!H40,CHAR(160)," "))) -> Copiers | L39: Pro Copiers 830 | M39: =PROPER(TRIM(SUBSTITUTE(Raw_Text_Fields!I40,CHAR(160)," "))) -> Standard Class | N39: 4 | O39: 1327.54 | P39: 0.2 | Q39: 4248.13 | R39: 3321.09 | S39: 927.04 | T39: =PROPER(TRIM(SUBSTITUTE(Raw_Text_Fields!J40,CHAR(160)," "))) -> Paid | U39: =PROPER(TRIM(SUBSTITUTE(Raw_Text_Fields!K40,CHAR(160)," "))) -> Completed | V39: =IF(OR(P39<0,P39>0.5),0,P39) -> 0.2 | W39: =N39*O39*(1-V39) -> 4248.128 | X39: =W39-R39 -> 927.038 | Y39: =IFERROR(X39/W39,0) -> 0.21822271 | Z39: =C39-B39 -> 0 | AA39: =IF(B39="","",TEXT(B39,"mmm")) -> Jul | AB39: =IF(B39="","",YEAR(B39)) -> 2025 | AD39: =IF(LEFT(AC39&IF(B39="","; Missing Order Date","")&IF(C39="","; Missing Ship Date","")&IF(P39<0,"; Invalid Discount (Negative)","")&IF(P39>0.5,"; Invalid Discount (Too High)","")&IF(Z39<0,"; Invalid Shipping Record (Ship Before Order)","")&IF(ABS(Q39-W39)>1,"; Sales Mismatch","")&IF(ABS(S39-X39)>1,"; Profit Mismatch","")&IF(COUNTIF($A$2:$A$913,A39)>1,"; Duplicate Order ID Conflict",""),2)="; ",MID(AC39&IF(B39="","; Missing Order Date","")&IF(C39="","; Missing Ship Date","")&IF(P39<0,"; Invalid Discount (Negative)","")&IF(P39>0.5,"; Invalid Discount (Too High)","")&IF(Z39<0,"; Invalid Shipping Record (Ship Before Order)","")&IF(ABS(Q39-W39)>1,"; Sales Mismatch","")&IF(ABS(S39-X39)>1,"; Profit Mismatch","")&IF(COUNTIF($A$2:$A$913,A39)>1,"; Duplicate Order ID Conflict",""),3,500),AC39&IF(B39="","; Missing Order Date","")&IF(C39="","; Missing Ship Date","")&IF(P39<0,"; Invalid Discount (Negative)","")&IF(P39>0.5,"; Invalid Discount (Too High)","")&IF(Z39<0,"; Invalid Shipping Record (Ship Before Order)","")&IF(ABS(Q39-W39)>1,"; Sales Mismatch","")&IF(ABS(S39-X39)>1,"; Profit Mismatch","")&IF(COUNTIF($A$2:$A$913,A39)>1,"; Duplicate Order ID Conflict","")) | AE39: =IF(OR(ISNUMBER(SEARCH("Invalid Discount",AD39)),ISNUMBER(SEARCH("Invalid Shipping Record",AD39)),ISNUMBER(SEARCH("Sales Mismatch",AD39)),ISNUMBER(SEARCH("Profit Mismatch",AD39)),ISNUMBER(SEARCH("Duplicate Order ID Conflict",AD39)),ISNUMBER(SEARCH("Missing Order Date",AD39)),ISNUMBER(SEARCH("Missing Ship Date",AD39))),"Invalid",IF(AD39<>"","Warning","Clean")) -> Clean
A40: ORD-2024-10039 | B40: 45460 | C40: 45465 | D40: CUST-8235 | E40: =PROPER(TRIM(SUBSTITUTE(Raw_Text_Fields!B41,CHAR(160)," "))) -> Aarav Sharma | F40: =PROPER(TRIM(SUBSTITUTE(Raw_Text_Fields!C41,CHAR(160)," "))) -> Corporate | G40: =PROPER(TRIM(SUBSTITUTE(Raw_Text_Fields!D41,CHAR(160)," "))) -> West | H40: =PROPER(TRIM(SUBSTITUTE(Raw_Text_Fields!E41,CHAR(160)," "))) -> Gujarat | I40: =PROPER(TRIM(SUBSTITUTE(Raw_Text_Fields!F41,CHAR(160)," "))) -> Ahmedabad | J40: =PROPER(TRIM(SUBSTITUTE(Raw_Text_Fields!G41,CHAR(160)," "))) -> Technology | K40: =PROPER(TRIM(SUBSTITUTE(Raw_Text_Fields!H41,CHAR(160)," "))) -> Phones | L40: Prime Phones 507 | M40: =PROPER(TRIM(SUBSTITUTE(Raw_Text_Fields!I41,CHAR(160)," "))) -> First Class | N40: 7 | O40: 2210.68 | P40: 0.1 | Q40: 13927.28 | R40: 10504.87 | S40: 3422.41 | T40: =PROPER(TRIM(SUBSTITUTE(Raw_Text_Fields!J41,CHAR(160)," "))) -> Paid | U40: =PROPER(TRIM(SUBSTITUTE(Raw_Text_Fields!K41,CHAR(160)," "))) -> Completed | V40: =IF(OR(P40<0,P40>0.5),0,P40) -> 0.1 | W40: =N40*O40*(1-V40) -> 13927.284 | X40: =W40-R40 -> 3422.414 | Y40: =IFERROR(X40/W40,0) -> 0.24573449 | Z40: =C40-B40 -> 5 | AA40: =IF(B40="","",TEXT(B40,"mmm")) -> Jun | AB40: =IF(B40="","",YEAR(B40)) -> 2024 | AD40: =IF(LEFT(AC40&IF(B40="","; Missing Order Date","")&IF(C40="","; Missing Ship Date","")&IF(P40<0,"; Invalid Discount (Negative)","")&IF(P40>0.5,"; Invalid Discount (Too High)","")&IF(Z40<0,"; Invalid Shipping Record (Ship Before Order)","")&IF(ABS(Q40-W40)>1,"; Sales Mismatch","")&IF(ABS(S40-X40)>1,"; Profit Mismatch","")&IF(COUNTIF($A$2:$A$913,A40)>1,"; Duplicate Order ID Conflict",""),2)="; ",MID(AC40&IF(B40="","; Missing Order Date","")&IF(C40="","; Missing Ship Date","")&IF(P40<0,"; Invalid Discount (Negative)","")&IF(P40>0.5,"; Invalid Discount (Too High)","")&IF(Z40<0,"; Invalid Shipping Record (Ship Before Order)","")&IF(ABS(Q40-W40)>1,"; Sales Mismatch","")&IF(ABS(S40-X40)>1,"; Profit Mismatch","")&IF(COUNTIF($A$2:$A$913,A40)>1,"; Duplicate Order ID Conflict",""),3,500),AC40&IF(B40="","; Missing Order Date","")&IF(C40="","; Missing Ship Date","")&IF(P40<0,"; Invalid Discount (Negative)","")&IF(P40>0.5,"; Invalid Discount (Too High)","")&IF(Z40<0,"; Invalid Shipping Record (Ship Before Order)","")&IF(ABS(Q40-W40)>1,"; Sales Mismatch","")&IF(ABS(S40-X40)>1,"; Profit Mismatch","")&IF(COUNTIF($A$2:$A$913,A40)>1,"; Duplicate Order ID Conflict","")) | AE40: =IF(OR(ISNUMBER(SEARCH("Invalid Discount",AD40)),ISNUMBER(SEARCH("Invalid Shipping Record",AD40)),ISNUMBER(SEARCH("Sales Mismatch",AD40)),ISNUMBER(SEARCH("Profit Mismatch",AD40)),ISNUMBER(SEARCH("Duplicate Order ID Conflict",AD40)),ISNUMBER(SEARCH("Missing Order Date",AD40)),ISNUMBER(SEARCH("Missing Ship Date",AD40))),"Invalid",IF(AD40<>"","Warning","Clean")) -> Clean
A41: ORD-2024-10040 | B41: 45637 | C41: 45637 | D41: CUST-5830 | E41: =PROPER(TRIM(SUBSTITUTE(Raw_Text_Fields!B42,CHAR(160)," "))) -> Mira Das | F41: =PROPER(TRIM(SUBSTITUTE(Raw_Text_Fields!C42,CHAR(160)," "))) -> Small Business | G41: =PROPER(TRIM(SUBSTITUTE(Raw_Text_Fields!D42,CHAR(160)," "))) -> West | H41: =PROPER(TRIM(SUBSTITUTE(Raw_Text_Fields!E42,CHAR(160)," "))) -> Madhya Pradesh | I41: =PROPER(TRIM(SUBSTITUTE(Raw_Text_Fields!F42,CHAR(160)," "))) -> Indore | J41: =PROPER(TRIM(SUBSTITUTE(Raw_Text_Fields!G42,CHAR(160)," "))) -> Technology | K41: =PROPER(TRIM(SUBSTITUTE(Raw_Text_Fields!H42,CHAR(160)," "))) -> Copiers | L41: Classic Copiers 590 | M41: =PROPER(TRIM(SUBSTITUTE(Raw_Text_Fields!I42,CHAR(160)," "))) -> First Class | N41: 4 | O41: 1370.92 | P41: 0.1 | Q41: 4935.31 | R41: 3374.77 | S41: 1560.54 | T41: =PROPER(TRIM(SUBSTITUTE(Raw_Text_Fields!J42,CHAR(160)," "))) -> Pending | U41: =PROPER(TRIM(SUBSTITUTE(Raw_Text_Fields!K42,CHAR(160)," "))) -> Returned | V41: =IF(OR(P41<0,P41>0.5),0,P41) -> 0.1 | W41: =N41*O41*(1-V41) -> 4935.312 | X41: =W41-R41 -> 1560.542 | Y41: =IFERROR(X41/W41,0) -> 0.31619926 | Z41: =C41-B41 -> 0 | AA41: =IF(B41="","",TEXT(B41,"mmm")) -> Dec | AB41: =IF(B41="","",YEAR(B41)) -> 2024 | AD41: =IF(LEFT(AC41&IF(B41="","; Missing Order Date","")&IF(C41="","; Missing Ship Date","")&IF(P41<0,"; Invalid Discount (Negative)","")&IF(P41>0.5,"; Invalid Discount (Too High)","")&IF(Z41<0,"; Invalid Shipping Record (Ship Before Order)","")&IF(ABS(Q41-W41)>1,"; Sales Mismatch","")&IF(ABS(S41-X41)>1,"; Profit Mismatch","")&IF(COUNTIF($A$2:$A$913,A41)>1,"; Duplicate Order ID Conflict",""),2)="; ",MID(AC41&IF(B41="","; Missing Order Date","")&IF(C41="","; Missing Ship Date","")&IF(P41<0,"; Invalid Discount (Negative)","")&IF(P41>0.5,"; Invalid Discount (Too High)","")&IF(Z41<0,"; Invalid Shipping Record (Ship Before Order)","")&IF(ABS(Q41-W41)>1,"; Sales Mismatch","")&IF(ABS(S41-X41)>1,"; Profit Mismatch","")&IF(COUNTIF($A$2:$A$913,A41)>1,"; Duplicate Order ID Conflict",""),3,500),AC41&IF(B41="","; Missing Order Date","")&IF(C41="","; Missing Ship Date","")&IF(P41<0,"; Invalid Discount (Negative)","")&IF(P41>0.5,"; Invalid Discount (Too High)","")&IF(Z41<0,"; Invalid Shipping Record (Ship Before Order)","")&IF(ABS(Q41-W41)>1,"; Sales Mismatch","")&IF(ABS(S41-X41)>1,"; Profit Mismatch","")&IF(COUNTIF($A$2:$A$913,A41)>1,"; Duplicate Order ID Conflict","")) | AE41: =IF(OR(ISNUMBER(SEARCH("Invalid Discount",AD41)),ISNUMBER(SEARCH("Invalid Shipping Record",AD41)),ISNUMBER(SEARCH("Sales Mismatch",AD41)),ISNUMBER(SEARCH("Profit Mismatch",AD41)),ISNUMBER(SEARCH("Duplicate Order ID Conflict",AD41)),ISNUMBER(SEARCH("Missing Order Date",AD41)),ISNUMBER(SEARCH("Missing Ship Date",AD41))),"Invalid",IF(AD41<>"","Warning","Clean")) -> Clean
A42: ORD-2024-10041 | B42: 45575 | C42: 45581 | D42: CUST-7178 | E42: =PROPER(TRIM(SUBSTITUTE(Raw_Text_Fields!B43,CHAR(160)," "))) -> Isha Nair | F42: =PROPER(TRIM(SUBSTITUTE(Raw_Text_Fields!C43,CHAR(160)," "))) -> Home Office | G42: =PROPER(TRIM(SUBSTITUTE(Raw_Text_Fields!D43,CHAR(160)," "))) -> West | H42: =PROPER(TRIM(SUBSTITUTE(Raw_Text_Fields!E43,CHAR(160)," "))) -> Rajasthan | I42: =PROPER(TRIM(SUBSTITUTE(Raw_Text_Fields!F43,CHAR(160)," "))) -> Udaipur | J42: =PROPER(TRIM(SUBSTITUTE(Raw_Text_Fields!G43,CHAR(160)," "))) -> Technology | K42: =PROPER(TRIM(SUBSTITUTE(Raw_Text_Fields!H43,CHAR(160)," "))) -> Copiers | L42: Eco Copiers 865 | M42: =PROPER(TRIM(SUBSTITUTE(Raw_Text_Fields!I43,CHAR(160)," "))) -> Standard Class | N42: 7 | O42: 2509.27 | P42: 0.2 | Q42: 14051.91 | R42: 11990.37 | S42: 2061.54 | T42: =PROPER(TRIM(SUBSTITUTE(Raw_Text_Fields!J43,CHAR(160)," "))) -> Paid | U42: =PROPER(TRIM(SUBSTITUTE(Raw_Text_Fields!K43,CHAR(160)," "))) -> Completed | V42: =IF(OR(P42<0,P42>0.5),0,P42) -> 0.2 | W42: =N42*O42*(1-V42) -> 14051.912 | X42: =W42-R42 -> 2061.542 | Y42: =IFERROR(X42/W42,0) -> 0.146709 | Z42: =C42-B42 -> 6 | AA42: =IF(B42="","",TEXT(B42,"mmm")) -> Oct | AB42: =IF(B42="","",YEAR(B42)) -> 2024 | AD42: =IF(LEFT(AC42&IF(B42="","; Missing Order Date","")&IF(C42="","; Missing Ship Date","")&IF(P42<0,"; Invalid Discount (Negative)","")&IF(P42>0.5,"; Invalid Discount (Too High)","")&IF(Z42<0,"; Invalid Shipping Record (Ship Before Order)","")&IF(ABS(Q42-W42)>1,"; Sales Mismatch","")&IF(ABS(S42-X42)>1,"; Profit Mismatch","")&IF(COUNTIF($A$2:$A$913,A42)>1,"; Duplicate Order ID Conflict",""),2)="; ",MID(AC42&IF(B42="","; Missing Order Date","")&IF(C42="","; Missing Ship Date","")&IF(P42<0,"; Invalid Discount (Negative)","")&IF(P42>0.5,"; Invalid Discount (Too High)","")&IF(Z42<0,"; Invalid Shipping Record (Ship Before Order)","")&IF(ABS(Q42-W42)>1,"; Sales Mismatch","")&IF(ABS(S42-X42)>1,"; Profit Mismatch","")&IF(COUNTIF($A$2:$A$913,A42)>1,"; Duplicate Order ID Conflict",""),3,500),AC42&IF(B42="","; Missing Order Date","")&IF(C42="","; Missing Ship Date","")&IF(P42<0,"; Invalid Discount (Negative)","")&IF(P42>0.5,"; Invalid Discount (Too High)","")&IF(Z42<0,"; Invalid Shipping Record (Ship Before Order)","")&IF(ABS(Q42-W42)>1,"; Sales Mismatch","")&IF(ABS(S42-X42)>1,"; Profit Mismatch","")&IF(COUNTIF($A$2:$A$913,A42)>1,"; Duplicate Order ID Conflict","")) | AE42: =IF(OR(ISNUMBER(SEARCH("Invalid Discount",AD42)),ISNUMBER(SEARCH("Invalid Shipping Record",AD42)),ISNUMBER(SEARCH("Sales Mismatch",AD42)),ISNUMBER(SEARCH("Profit Mismatch",AD42)),ISNUMBER(SEARCH("Duplicate Order ID Conflict",AD42)),ISNUMBER(SEARCH("Missing Order Date",AD42)),ISNUMBER(SEARCH("Missing Ship Date",AD42))),"Invalid",IF(AD42<>"","Warning","Clean")) -> Clean
A43: ORD-2024-10042 | B43: 45363 | C43: 45368 | D43: CUST-3829 | E43: =PROPER(TRIM(SUBSTITUTE(Raw_Text_Fields!B44,CHAR(160)," "))) -> Aarav Sharma | F43: =PROPER(TRIM(SUBSTITUTE(Raw_Text_Fields!C44,CHAR(160)," "))) -> Small Business | G43: =PROPER(TRIM(SUBSTITUTE(Raw_Text_Fields!D44,CHAR(160)," "))) -> East | H43: =PROPER(TRIM(SUBSTITUTE(Raw_Text_Fields!E44,CHAR(160)," "))) -> Odisha | I43: =PROPER(TRIM(SUBSTITUTE(Raw_Text_Fields!F44,CHAR(160)," "))) -> Bhubaneswar | J43: =PROPER(TRIM(SUBSTITUTE(Raw_Text_Fields!G44,CHAR(160)," "))) -> Furniture | K43: =PROPER(TRIM(SUBSTITUTE(Raw_Text_Fields!H44,CHAR(160)," "))) -> Bookcases | L43: Classic Bookcases 835 | M43: =PROPER(TRIM(SUBSTITUTE(Raw_Text_Fields!I44,CHAR(160)," "))) -> Same Day | N43: 8 | O43: 855.81 | P43: 0 | Q43: 6846.48 | R43: 4239.89 | S43: 2606.59 | T43: =PROPER(TRIM(SUBSTITUTE(Raw_Text_Fields!J44,CHAR(160)," "))) -> Pending | U43: =PROPER(TRIM(SUBSTITUTE(Raw_Text_Fields!K44,CHAR(160)," "))) -> Cancelled | V43: =IF(OR(P43<0,P43>0.5),0,P43) -> 0 | W43: =N43*O43*(1-V43) -> 6846.48 | X43: =W43-R43 -> 2606.59 | Y43: =IFERROR(X43/W43,0) -> 0.38071973 | Z43: =C43-B43 -> 5 | AA43: =IF(B43="","",TEXT(B43,"mmm")) -> Mar | AB43: =IF(B43="","",YEAR(B43)) -> 2024 | AD43: =IF(LEFT(AC43&IF(B43="","; Missing Order Date","")&IF(C43="","; Missing Ship Date","")&IF(P43<0,"; Invalid Discount (Negative)","")&IF(P43>0.5,"; Invalid Discount (Too High)","")&IF(Z43<0,"; Invalid Shipping Record (Ship Before Order)","")&IF(ABS(Q43-W43)>1,"; Sales Mismatch","")&IF(ABS(S43-X43)>1,"; Profit Mismatch","")&IF(COUNTIF($A$2:$A$913,A43)>1,"; Duplicate Order ID Conflict",""),2)="; ",MID(AC43&IF(B43="","; Missing Order Date","")&IF(C43="","; Missing Ship Date","")&IF(P43<0,"; Invalid Discount (Negative)","")&IF(P43>0.5,"; Invalid Discount (Too High)","")&IF(Z43<0,"; Invalid Shipping Record (Ship Before Order)","")&IF(ABS(Q43-W43)>1,"; Sales Mismatch","")&IF(ABS(S43-X43)>1,"; Profit Mismatch","")&IF(COUNTIF($A$2:$A$913,A43)>1,"; Duplicate Order ID Conflict",""),3,500),AC43&IF(B43="","; Missing Order Date","")&IF(C43="","; Missing Ship Date","")&IF(P43<0,"; Invalid Discount (Negative)","")&IF(P43>0.5,"; Invalid Discount (Too High)","")&IF(Z43<0,"; Invalid Shipping Record (Ship Before Order)","")&IF(ABS(Q43-W43)>1,"; Sales Mismatch","")&IF(ABS(S43-X43)>1,"; Profit Mismatch","")&IF(COUNTIF($A$2:$A$913,A43)>1,"; Duplicate Order ID Conflict","")) | AE43: =IF(OR(ISNUMBER(SEARCH("Invalid Discount",AD43)),ISNUMBER(SEARCH("Invalid Shipping Record",AD43)),ISNUMBER(SEARCH("Sales Mismatch",AD43)),ISNUMBER(SEARCH("Profit Mismatch",AD43)),ISNUMBER(SEARCH("Duplicate Order ID Conflict",AD43)),ISNUMBER(SEARCH("Missing Order Date",AD43)),ISNUMBER(SEARCH("Missing Ship Date",AD43))),"Invalid",IF(AD43<>"","Warning","Clean")) -> Clean
A44: ORD-2025-10043 | B44: 45940 | C44: 45945 | D44: CUST-6708 | E44: =PROPER(TRIM(SUBSTITUTE(Raw_Text_Fields!B45,CHAR(160)," "))) -> Arjun Bose | F44: =PROPER(TRIM(SUBSTITUTE(Raw_Text_Fields!C45,CHAR(160)," "))) -> Corporate | G44: =PROPER(TRIM(SUBSTITUTE(Raw_Text_Fields!D45,CHAR(160)," "))) -> East | H44: =PROPER(TRIM(SUBSTITUTE(Raw_Text_Fields!E45,CHAR(160)," "))) -> Jharkhand | I44: =PROPER(TRIM(SUBSTITUTE(Raw_Text_Fields!F45,CHAR(160)," "))) -> Ranchi | J44: =PROPER(TRIM(SUBSTITUTE(Raw_Text_Fields!G45,CHAR(160)," "))) -> Technology | K44: =PROPER(TRIM(SUBSTITUTE(Raw_Text_Fields!H45,CHAR(160)," "))) -> Phones | L44: Eco Phones 702 | M44: =PROPER(TRIM(SUBSTITUTE(Raw_Text_Fields!I45,CHAR(160)," "))) -> Standard Class | N44: 8 | O44: 979.87 | P44: 0.05 | Q44: 7447.01 | R44: 4496.22 | S44: 2950.79 | T44: =PROPER(TRIM(SUBSTITUTE(Raw_Text_Fields!J45,CHAR(160)," "))) -> Paid | U44: =PROPER(TRIM(SUBSTITUTE(Raw_Text_Fields!K45,CHAR(160)," "))) -> Completed | V44: =IF(OR(P44<0,P44>0.5),0,P44) -> 0.05 | W44: =N44*O44*(1-V44) -> 7447.012 | X44: =W44-R44 -> 2950.792 | Y44: =IFERROR(X44/W44,0) -> 0.39623838 | Z44: =C44-B44 -> 5 | AA44: =IF(B44="","",TEXT(B44,"mmm")) -> Oct | AB44: =IF(B44="","",YEAR(B44)) -> 2025 | AD44: =IF(LEFT(AC44&IF(B44="","; Missing Order Date","")&IF(C44="","; Missing Ship Date","")&IF(P44<0,"; Invalid Discount (Negative)","")&IF(P44>0.5,"; Invalid Discount (Too High)","")&IF(Z44<0,"; Invalid Shipping Record (Ship Before Order)","")&IF(ABS(Q44-W44)>1,"; Sales Mismatch","")&IF(ABS(S44-X44)>1,"; Profit Mismatch","")&IF(COUNTIF($A$2:$A$913,A44)>1,"; Duplicate Order ID Conflict",""),2)="; ",MID(AC44&IF(B44="","; Missing Order Date","")&IF(C44="","; Missing Ship Date","")&IF(P44<0,"; Invalid Discount (Negative)","")&IF(P44>0.5,"; Invalid Discount (Too High)","")&IF(Z44<0,"; Invalid Shipping Record (Ship Before Order)","")&IF(ABS(Q44-W44)>1,"; Sales Mismatch","")&IF(ABS(S44-X44)>1,"; Profit Mismatch","")&IF(COUNTIF($A$2:$A$913,A44)>1,"; Duplicate Order ID Conflict",""),3,500),AC44&IF(B44="","; Missing Order Date","")&IF(C44="","; Missing Ship Date","")&IF(P44<0,"; Invalid Discount (Negative)","")&IF(P44>0.5,"; Invalid Discount (Too High)","")&IF(Z44<0,"; Invalid Shipping Record (Ship Before Order)","")&IF(ABS(Q44-W44)>1,"; Sales Mismatch","")&IF(ABS(S44-X44)>1,"; Profit Mismatch","")&IF(COUNTIF($A$2:$A$913,A44)>1,"; Duplicate Order ID Conflict","")) | AE44: =IF(OR(ISNUMBER(SEARCH("Invalid Discount",AD44)),ISNUMBER(SEARCH("Invalid Shipping Record",AD44)),ISNUMBER(SEARCH("Sales Mismatch",AD44)),ISNUMBER(SEARCH("Profit Mismatch",AD44)),ISNUMBER(SEARCH("Duplicate Order ID Conflict",AD44)),ISNUMBER(SEARCH("Missing Order Date",AD44)),ISNUMBER(SEARCH("Missing Ship Date",AD44))),"Invalid",IF(AD44<>"","Warning","Clean")) -> Clean
A45: ORD-2024-10044 | B45: 45481 | C45: 45487 | D45: CUST-7119 | E45: =PROPER(TRIM(SUBSTITUTE(Raw_Text_Fields!B46,CHAR(160)," "))) -> Priya Menon | F45: =PROPER(TRIM(SUBSTITUTE(Raw_Text_Fields!C46,CHAR(160)," "))) -> Small Business | G45: =PROPER(TRIM(SUBSTITUTE(Raw_Text_Fields!D46,CHAR(160)," "))) -> East | H45: =PROPER(TRIM(SUBSTITUTE(Raw_Text_Fields!E46,CHAR(160)," "))) -> Odisha | I45: =PROPER(TRIM(SUBSTITUTE(Raw_Text_Fields!F46,CHAR(160)," "))) -> Bhubaneswar | J45: =PROPER(TRIM(SUBSTITUTE(Raw_Text_Fields!G46,CHAR(160)," "))) -> Furniture | K45: =PROPER(TRIM(SUBSTITUTE(Raw_Text_Fields!H46,CHAR(160)," "))) -> Furnishings | L45: Smart Furnishings 956 | M45: =PROPER(TRIM(SUBSTITUTE(Raw_Text_Fields!I46,CHAR(160)," "))) -> Same Day | N45: 3 | O45: 1010.23 | P45: 0 | Q45: 3030.69 | R45: 1721.08 | S45: 1309.61 | T45: =PROPER(TRIM(SUBSTITUTE(Raw_Text_Fields!J46,CHAR(160)," "))) -> Paid | U45: =PROPER(TRIM(SUBSTITUTE(Raw_Text_Fields!K46,CHAR(160)," "))) -> Completed | V45: =IF(OR(P45<0,P45>0.5),0,P45) -> 0 | W45: =N45*O45*(1-V45) -> 3030.69 | X45: =W45-R45 -> 1309.61 | Y45: =IFERROR(X45/W45,0) -> 0.43211612 | Z45: =C45-B45 -> 6 | AA45: =IF(B45="","",TEXT(B45,"mmm")) -> Jul | AB45: =IF(B45="","",YEAR(B45)) -> 2024 | AD45: =IF(LEFT(AC45&IF(B45="","; Missing Order Date","")&IF(C45="","; Missing Ship Date","")&IF(P45<0,"; Invalid Discount (Negative)","")&IF(P45>0.5,"; Invalid Discount (Too High)","")&IF(Z45<0,"; Invalid Shipping Record (Ship Before Order)","")&IF(ABS(Q45-W45)>1,"; Sales Mismatch","")&IF(ABS(S45-X45)>1,"; Profit Mismatch","")&IF(COUNTIF($A$2:$A$913,A45)>1,"; Duplicate Order ID Conflict",""),2)="; ",MID(AC45&IF(B45="","; Missing Order Date","")&IF(C45="","; Missing Ship Date","")&IF(P45<0,"; Invalid Discount (Negative)","")&IF(P45>0.5,"; Invalid Discount (Too High)","")&IF(Z45<0,"; Invalid Shipping Record (Ship Before Order)","")&IF(ABS(Q45-W45)>1,"; Sales Mismatch","")&IF(ABS(S45-X45)>1,"; Profit Mismatch","")&IF(COUNTIF($A$2:$A$913,A45)>1,"; Duplicate Order ID Conflict",""),3,500),AC45&IF(B45="","; Missing Order Date","")&IF(C45="","; Missing Ship Date","")&IF(P45<0,"; Invalid Discount (Negative)","")&IF(P45>0.5,"; Invalid Discount (Too High)","")&IF(Z45<0,"; Invalid Shipping Record (Ship Before Order)","")&IF(ABS(Q45-W45)>1,"; Sales Mismatch","")&IF(ABS(S45-X45)>1,"; Profit Mismatch","")&IF(COUNTIF($A$2:$A$913,A45)>1,"; Duplicate Order ID Conflict","")) | AE45: =IF(OR(ISNUMBER(SEARCH("Invalid Discount",AD45)),ISNUMBER(SEARCH("Invalid Shipping Record",AD45)),ISNUMBER(SEARCH("Sales Mismatch",AD45)),ISNUMBER(SEARCH("Profit Mismatch",AD45)),ISNUMBER(SEARCH("Duplicate Order ID Conflict",AD45)),ISNUMBER(SEARCH("Missing Order Date",AD45)),ISNUMBER(SEARCH("Missing Ship Date",AD45))),"Invalid",IF(AD45<>"","Warning","Clean")) -> Clean
A46: ORD-2024-10045 | B46: 45465 | C46: 45468 | D46: CUST-3373 | E46: =PROPER(TRIM(SUBSTITUTE(Raw_Text_Fields!B47,CHAR(160)," "))) -> Rohan Mehta | F46: =PROPER(TRIM(SUBSTITUTE(Raw_Text_Fields!C47,CHAR(160)," "))) -> Small Business | G46: =PROPER(TRIM(SUBSTITUTE(Raw_Text_Fields!D47,CHAR(160)," "))) -> North | H46: =PROPER(TRIM(SUBSTITUTE(Raw_Text_Fields!E47,CHAR(160)," "))) -> Haryana | I46: =PROPER(TRIM(SUBSTITUTE(Raw_Text_Fields!F47,CHAR(160)," "))) -> Gurugram | J46: =PROPER(TRIM(SUBSTITUTE(Raw_Text_Fields!G47,CHAR(160)," "))) -> Furniture | K46: =PROPER(TRIM(SUBSTITUTE(Raw_Text_Fields!H47,CHAR(160)," "))) -> Chairs | L46: Max Chairs 393 | M46: =PROPER(TRIM(SUBSTITUTE(Raw_Text_Fields!I47,CHAR(160)," "))) -> Standard Class | N46: 9 | O46: 3329.77 | P46: 0.1 | Q46: 26971.14 | R46: 17376.2 | S46: 9594.94 | T46: =PROPER(TRIM(SUBSTITUTE(Raw_Text_Fields!J47,CHAR(160)," "))) -> Paid | U46: =PROPER(TRIM(SUBSTITUTE(Raw_Text_Fields!K47,CHAR(160)," "))) -> Completed | V46: =IF(OR(P46<0,P46>0.5),0,P46) -> 0.1 | W46: =N46*O46*(1-V46) -> 26971.137 | X46: =W46-R46 -> 9594.937 | Y46: =IFERROR(X46/W46,0) -> 0.35574833 | Z46: =C46-B46 -> 3 | AA46: =IF(B46="","",TEXT(B46,"mmm")) -> Jun | AB46: =IF(B46="","",YEAR(B46)) -> 2024 | AD46: =IF(LEFT(AC46&IF(B46="","; Missing Order Date","")&IF(C46="","; Missing Ship Date","")&IF(P46<0,"; Invalid Discount (Negative)","")&IF(P46>0.5,"; Invalid Discount (Too High)","")&IF(Z46<0,"; Invalid Shipping Record (Ship Before Order)","")&IF(ABS(Q46-W46)>1,"; Sales Mismatch","")&IF(ABS(S46-X46)>1,"; Profit Mismatch","")&IF(COUNTIF($A$2:$A$913,A46)>1,"; Duplicate Order ID Conflict",""),2)="; ",MID(AC46&IF(B46="","; Missing Order Date","")&IF(C46="","; Missing Ship Date","")&IF(P46<0,"; Invalid Discount (Negative)","")&IF(P46>0.5,"; Invalid Discount (Too High)","")&IF(Z46<0,"; Invalid Shipping Record (Ship Before Order)","")&IF(ABS(Q46-W46)>1,"; Sales Mismatch","")&IF(ABS(S46-X46)>1,"; Profit Mismatch","")&IF(COUNTIF($A$2:$A$913,A46)>1,"; Duplicate Order ID Conflict",""),3,500),AC46&IF(B46="","; Missing Order Date","")&IF(C46="","; Missing Ship Date","")&IF(P46<0,"; Invalid Discount (Negative)","")&IF(P46>0.5,"; Invalid Discount (Too High)","")&IF(Z46<0,"; Invalid Shipping Record (Ship Before Order)","")&IF(ABS(Q46-W46)>1,"; Sales Mismatch","")&IF(ABS(S46-X46)>1,"; Profit Mismatch","")&IF(COUNTIF($A$2:$A$913,A46)>1,"; Duplicate Order ID Conflict","")) | AE46: =IF(OR(ISNUMBER(SEARCH("Invalid Discount",AD46)),ISNUMBER(SEARCH("Invalid Shipping Record",AD46)),ISNUMBER(SEARCH("Sales Mismatch",AD46)),ISNUMBER(SEARCH("Profit Mismatch",AD46)),ISNUMBER(SEARCH("Duplicate Order ID Conflict",AD46)),ISNUMBER(SEARCH("Missing Order Date",AD46)),ISNUMBER(SEARCH("Missing Ship Date",AD46))),"Invalid",IF(AD46<>"","Warning","Clean")) -> Clean
A47: ORD-2024-10046 | B47: 45309 | C47: 45315 | D47: CUST-8896 | E47: =PROPER(TRIM(SUBSTITUTE(Raw_Text_Fields!B48,CHAR(160)," "))) -> Isha Nair | F47: =PROPER(TRIM(SUBSTITUTE(Raw_Text_Fields!C48,CHAR(160)," "))) -> Home Office | G47: =PROPER(TRIM(SUBSTITUTE(Raw_Text_Fields!D48,CHAR(160)," "))) -> East | H47: =PROPER(TRIM(SUBSTITUTE(Raw_Text_Fields!E48,CHAR(160)," "))) -> Bihar | I47: =PROPER(TRIM(SUBSTITUTE(Raw_Text_Fields!F48,CHAR(160)," "))) -> Patna | J47: =PROPER(TRIM(SUBSTITUTE(Raw_Text_Fields!G48,CHAR(160)," "))) -> Office Supplies | K47: =PROPER(TRIM(SUBSTITUTE(Raw_Text_Fields!H48,CHAR(160)," "))) -> Art | L47: Prime Art 221 | M47: =PROPER(TRIM(SUBSTITUTE(Raw_Text_Fields!I48,CHAR(160)," "))) -> Second Class | N47: 8 | O47: 3927.82 | P47: 0.05 | Q47: 29851.43 | R47: 17487.48 | S47: 12363.95 | T47: =PROPER(TRIM(SUBSTITUTE(Raw_Text_Fields!J48,CHAR(160)," "))) -> Pending | U47: =PROPER(TRIM(SUBSTITUTE(Raw_Text_Fields!K48,CHAR(160)," "))) -> Returned | V47: =IF(OR(P47<0,P47>0.5),0,P47) -> 0.05 | W47: =N47*O47*(1-V47) -> 29851.432 | X47: =W47-R47 -> 12363.952 | Y47: =IFERROR(X47/W47,0) -> 0.41418288 | Z47: =C47-B47 -> 6 | AA47: =IF(B47="","",TEXT(B47,"mmm")) -> Jan | AB47: =IF(B47="","",YEAR(B47)) -> 2024 | AD47: =IF(LEFT(AC47&IF(B47="","; Missing Order Date","")&IF(C47="","; Missing Ship Date","")&IF(P47<0,"; Invalid Discount (Negative)","")&IF(P47>0.5,"; Invalid Discount (Too High)","")&IF(Z47<0,"; Invalid Shipping Record (Ship Before Order)","")&IF(ABS(Q47-W47)>1,"; Sales Mismatch","")&IF(ABS(S47-X47)>1,"; Profit Mismatch","")&IF(COUNTIF($A$2:$A$913,A47)>1,"; Duplicate Order ID Conflict",""),2)="; ",MID(AC47&IF(B47="","; Missing Order Date","")&IF(C47="","; Missing Ship Date","")&IF(P47<0,"; Invalid Discount (Negative)","")&IF(P47>0.5,"; Invalid Discount (Too High)","")&IF(Z47<0,"; Invalid Shipping Record (Ship Before Order)","")&IF(ABS(Q47-W47)>1,"; Sales Mismatch","")&IF(ABS(S47-X47)>1,"; Profit Mismatch","")&IF(COUNTIF($A$2:$A$913,A47)>1,"; Duplicate Order ID Conflict",""),3,500),AC47&IF(B47="","; Missing Order Date","")&IF(C47="","; Missing Ship Date","")&IF(P47<0,"; Invalid Discount (Negative)","")&IF(P47>0.5,"; Invalid Discount (Too High)","")&IF(Z47<0,"; Invalid Shipping Record (Ship Before Order)","")&IF(ABS(Q47-W47)>1,"; Sales Mismatch","")&IF(ABS(S47-X47)>1,"; Profit Mismatch","")&IF(COUNTIF($A$2:$A$913,A47)>1,"; Duplicate Order ID Conflict","")) | AE47: =IF(OR(ISNUMBER(SEARCH("Invalid Discount",AD47)),ISNUMBER(SEARCH("Invalid Shipping Record",AD47)),ISNUMBER(SEARCH("Sales Mismatch",AD47)),ISNUMBER(SEARCH("Profit Mismatch",AD47)),ISNUMBER(SEARCH("Duplicate Order ID Conflict",AD47)),ISNUMBER(SEARCH("Missing Order Date",AD47)),ISNUMBER(SEARCH("Missing Ship Date",AD47))),"Invalid",IF(AD47<>"","Warning","Clean")) -> Clean
A48: ORD-2024-10047 | B48: 45492 | C48: 45492 | D48: CUST-8517 | E48: =PROPER(TRIM(SUBSTITUTE(Raw_Text_Fields!B49,CHAR(160)," "))) -> Ananya Rao | F48: =PROPER(TRIM(SUBSTITUTE(Raw_Text_Fields!C49,CHAR(160)," "))) -> Small Business | G48: =PROPER(TRIM(SUBSTITUTE(Raw_Text_Fields!D49,CHAR(160)," "))) -> South | H48: =PROPER(TRIM(SUBSTITUTE(Raw_Text_Fields!E49,CHAR(160)," "))) -> Kerala | I48: =PROPER(TRIM(SUBSTITUTE(Raw_Text_Fields!F49,CHAR(160)," "))) -> Kochi | J48: =PROPER(TRIM(SUBSTITUTE(Raw_Text_Fields!G49,CHAR(160)," "))) -> Furniture | K48: =PROPER(TRIM(SUBSTITUTE(Raw_Text_Fields!H49,CHAR(160)," "))) -> Bookcases | L48: Elite Bookcases 671 | M48: =PROPER(TRIM(SUBSTITUTE(Raw_Text_Fields!I49,CHAR(160)," "))) -> Standard Class | N48: 9 | O48: 2386.79 | P48: 0.25 | Q48: 16110.83 | R48: 10680.03 | S48: 5430.8 | T48: =PROPER(TRIM(SUBSTITUTE(Raw_Text_Fields!J49,CHAR(160)," "))) -> Refunded | U48: =PROPER(TRIM(SUBSTITUTE(Raw_Text_Fields!K49,CHAR(160)," "))) -> Returned | V48: =IF(OR(P48<0,P48>0.5),0,P48) -> 0.25 | W48: =N48*O48*(1-V48) -> 16110.833 | X48: =W48-R48 -> 5430.8025 | Y48: =IFERROR(X48/W48,0) -> 0.33709012 | Z48: =C48-B48 -> 0 | AA48: =IF(B48="","",TEXT(B48,"mmm")) -> Jul | AB48: =IF(B48="","",YEAR(B48)) -> 2024 | AD48: =IF(LEFT(AC48&IF(B48="","; Missing Order Date","")&IF(C48="","; Missing Ship Date","")&IF(P48<0,"; Invalid Discount (Negative)","")&IF(P48>0.5,"; Invalid Discount (Too High)","")&IF(Z48<0,"; Invalid Shipping Record (Ship Before Order)","")&IF(ABS(Q48-W48)>1,"; Sales Mismatch","")&IF(ABS(S48-X48)>1,"; Profit Mismatch","")&IF(COUNTIF($A$2:$A$913,A48)>1,"; Duplicate Order ID Conflict",""),2)="; ",MID(AC48&IF(B48="","; Missing Order Date","")&IF(C48="","; Missing Ship Date","")&IF(P48<0,"; Invalid Discount (Negative)","")&IF(P48>0.5,"; Invalid Discount (Too High)","")&IF(Z48<0,"; Invalid Shipping Record (Ship Before Order)","")&IF(ABS(Q48-W48)>1,"; Sales Mismatch","")&IF(ABS(S48-X48)>1,"; Profit Mismatch","")&IF(COUNTIF($A$2:$A$913,A48)>1,"; Duplicate Order ID Conflict",""),3,500),AC48&IF(B48="","; Missing Order Date","")&IF(C48="","; Missing Ship Date","")&IF(P48<0,"; Invalid Discount (Negative)","")&IF(P48>0.5,"; Invalid Discount (Too High)","")&IF(Z48<0,"; Invalid Shipping Record (Ship Before Order)","")&IF(ABS(Q48-W48)>1,"; Sales Mismatch","")&IF(ABS(S48-X48)>1,"; Profit Mismatch","")&IF(COUNTIF($A$2:$A$913,A48)>1,"; Duplicate Order ID Conflict","")) | AE48: =IF(OR(ISNUMBER(SEARCH("Invalid Discount",AD48)),ISNUMBER(SEARCH("Invalid Shipping Record",AD48)),ISNUMBER(SEARCH("Sales Mismatch",AD48)),ISNUMBER(SEARCH("Profit Mismatch",AD48)),ISNUMBER(SEARCH("Duplicate Order ID Conflict",AD48)),ISNUMBER(SEARCH("Missing Order Date",AD48)),ISNUMBER(SEARCH("Missing Ship Date",AD48))),"Invalid",IF(AD48<>"","Warning","Clean")) -> Clean
... A59: ORD-2024-10058 | B59: 45329 | C59: 45337 | D59: CUST-9941 | E59: =PROPER(TRIM(SUBSTITUTE(Raw_Text_Fields!B60,CHAR(160)," "))) -> Priya Menon | F59: =PROPER(TRIM(SUBSTITUTE(Raw_Text_Fields!C60,CHAR(160)," "))) -> Consumer | G59: =PROPER(TRIM(SUBSTITUTE(Raw_Text_Fields!D60,CHAR(160)," "))) -> West | H59: =PROPER(TRIM(SUBSTITUTE(Raw_Text_Fields!E60,CHAR(160)," "))) -> Goa | I59: =PROPER(TRIM(SUBSTITUTE(Raw_Text_Fields!F60,CHAR(160)," "))) -> Panaji | J59: =PROPER(TRIM(SUBSTITUTE(Raw_Text_Fields!G60,CHAR(160)," "))) -> Furniture | K59: =PROPER(TRIM(SUBSTITUTE(Raw_Text_Fields!H60,CHAR(160)," "))) -> Chairs | L59: Max Chairs 813 | M59: =PROPER(TRIM(SUBSTITUTE(Raw_Text_Fields!I60,CHAR(160)," "))) -> Same Day | N59: 5 | O59: 255.87 | P59: 0 | Q59: 1279.35 | R59: 1091.54 | S59: 187.81 | T59: =PROPER(TRIM(SUBSTITUTE(Raw_Text_Fields!J60,CHAR(160)," "))) -> Paid | U59: =PROPER(TRIM(SUBSTITUTE(Raw_Text_Fields!K60,CHAR(160)," "))) -> Completed | V59: =IF(OR(P59<0,P59>0.5),0,P59) -> 0 | W59: =N59*O59*(1-V59) -> 1279.35 | X59: =W59-R59 -> 187.81 | Y59: =IFERROR(X59/W59,0) -> 0.14680111 | Z59: =C59-B59 -> 8 | AA59: =IF(B59="","",TEXT(B59,"mmm")) -> Feb | AB59: =IF(B59="","",YEAR(B59)) -> 2024 | AD59: =IF(LEFT(AC59&IF(B59="","; Missing Order Date","")&IF(C59="","; Missing Ship Date","")&IF(P59<0,"; Invalid Discount (Negative)","")&IF(P59>0.5,"; Invalid Discount (Too High)","")&IF(Z59<0,"; Invalid Shipping Record (Ship Before Order)","")&IF(ABS(Q59-W59)>1,"; Sales Mismatch","")&IF(ABS(S59-X59)>1,"; Profit Mismatch","")&IF(COUNTIF($A$2:$A$913,A59)>1,"; Duplicate Order ID Conflict",""),2)="; ",MID(AC59&IF(B59="","; Missing Order Date","")&IF(C59="","; Missing Ship Date","")&IF(P59<0,"; Invalid Discount (Negative)","")&IF(P59>0.5,"; Invalid Discount (Too High)","")&IF(Z59<0,"; Invalid Shipping Record (Ship Before Order)","")&IF(ABS(Q59-W59)>1,"; Sales Mismatch","")&IF(ABS(S59-X59)>1,"; Profit Mismatch","")&IF(COUNTIF($A$2:$A$913,A59)>1,"; Duplicate Order ID Conflict",""),3,500),AC59&IF(B59="","; Missing Order Date","")&IF(C59="","; Missing Ship Date","")&IF(P59<0,"; Invalid Discount (Negative)","")&IF(P59>0.5,"; Invalid Discount (Too High)","")&IF(Z59<0,"; Invalid Shipping Record (Ship Before Order)","")&IF(ABS(Q59-W59)>1,"; Sales Mismatch","")&IF(ABS(S59-X59)>1,"; Profit Mismatch","")&IF(COUNTIF($A$2:$A$913,A59)>1,"; Duplicate Order ID Conflict","")) | AE59: =IF(OR(ISNUMBER(SEARCH("Invalid Discount",AD59)),ISNUMBER(SEARCH("Invalid Shipping Record",AD59)),ISNUMBER(SEARCH("Sales Mismatch",AD59)),ISNUMBER(SEARCH("Profit Mismatch",AD59)),ISNUMBER(SEARCH("Duplicate Order ID Conflict",AD59)),ISNUMBER(SEARCH("Missing Order Date",AD59)),ISNUMBER(SEARCH("Missing Ship Date",AD59))),"Invalid",IF(AD59<>"","Warning","Clean")) -> Clean
A60: ORD-2024-10059 | B60: 45536 | C60: 45542 | D60: CUST-3983 | E60: =PROPER(TRIM(SUBSTITUTE(Raw_Text_Fields!B61,CHAR(160)," "))) -> Isha Nair | F60: =PROPER(TRIM(SUBSTITUTE(Raw_Text_Fields!C61,CHAR(160)," "))) -> Home Office | G60: =PROPER(TRIM(SUBSTITUTE(Raw_Text_Fields!D61,CHAR(160)," "))) -> North | H60: =PROPER(TRIM(SUBSTITUTE(Raw_Text_Fields!E61,CHAR(160)," "))) -> Rajasthan | I60: =PROPER(TRIM(SUBSTITUTE(Raw_Text_Fields!F61,CHAR(160)," "))) -> Jaipur | J60: =PROPER(TRIM(SUBSTITUTE(Raw_Text_Fields!G61,CHAR(160)," "))) -> Office Supplies | K60: =PROPER(TRIM(SUBSTITUTE(Raw_Text_Fields!H61,CHAR(160)," "))) -> Storage | L60: Basic Storage 872 | M60: =PROPER(TRIM(SUBSTITUTE(Raw_Text_Fields!I61,CHAR(160)," "))) -> Unknown | N60: 9 | O60: 1389.48 | P60: 0.1 | Q60: 11254.79 | R60: 6578.06 | S60: 4676.73 | T60: =PROPER(TRIM(SUBSTITUTE(Raw_Text_Fields!J61,CHAR(160)," "))) -> Pending | U60: =PROPER(TRIM(SUBSTITUTE(Raw_Text_Fields!K61,CHAR(160)," "))) -> Returned | V60: =IF(OR(P60<0,P60>0.5),0,P60) -> 0.1 | W60: =N60*O60*(1-V60) -> 11254.788 | X60: =W60-R60 -> 4676.728 | Y60: =IFERROR(X60/W60,0) -> 0.41553231 | Z60: =C60-B60 -> 6 | AA60: =IF(B60="","",TEXT(B60,"mmm")) -> Sep | AB60: =IF(B60="","",YEAR(B60)) -> 2024 | AC60: Missing Ship Mode (filled Unknown) | AD60: =IF(LEFT(AC60&IF(B60="","; Missing Order Date","")&IF(C60="","; Missing Ship Date","")&IF(P60<0,"; Invalid Discount (Negative)","")&IF(P60>0.5,"; Invalid Discount (Too High)","")&IF(Z60<0,"; Invalid Shipping Record (Ship Before Order)","")&IF(ABS(Q60-W60)>1,"; Sales Mismatch","")&IF(ABS(S60-X60)>1,"; Profit Mismatch","")&IF(COUNTIF($A$2:$A$913,A60)>1,"; Duplicate Order ID Conflict",""),2)="; ",MID(AC60&IF(B60="","; Missing Order Date","")&IF(C60="","; Missing Ship Date","")&IF(P60<0,"; Invalid Discount (Negative)","")&IF(P60>0.5,"; Invalid Discount (Too High)","")&IF(Z60<0,"; Invalid Shipping Record (Ship Before Order)","")&IF(ABS(Q60-W60)>1,"; Sales Mismatch","")&IF(ABS(S60-X60)>1,"; Profit Mismatch","")&IF(COUNTIF($A$2:$A$913,A60)>1,"; Duplicate Order ID Conflict",""),3,500),AC60&IF(B60="","; Missing Order Date","")&IF(C60="","; Missing Ship Date","")&IF(P60<0,"; Invalid Discount (Negative)","")&IF(P60>0.5,"; Invalid Discount (Too High)","")&IF(Z60<0,"; Invalid Shipping Record (Ship Before Order)","")&IF(ABS(Q60-W60)>1,"; Sales Mismatch","")&IF(ABS(S60-X60)>1,"; Profit Mismatch","")&IF(COUNTIF($A$2:$A$913,A60)>1,"; Duplicate Order ID Conflict","")) -> Missing Ship Mode (filled Unknown) | AE60: =IF(OR(ISNUMBER(SEARCH("Invalid Discount",AD60)),ISNUMBER(SEARCH("Invalid Shipping Record",AD60)),ISNUMBER(SEARCH("Sales Mismatch",AD60)),ISNUMBER(SEARCH("Profit Mismatch",AD60)),ISNUMBER(SEARCH("Duplicate Order ID Conflict",AD60)),ISNUMBER(SEARCH("Missing Order Date",AD60)),ISNUMBER(SEARCH("Missing Ship Date",AD60))),"Invalid",IF(AD60<>"","Warning","Clean")) -> Warning
A61: ORD-2024-10060 | B61: 45493 | C61: 45498 | D61: CUST-2418 | E61: =PROPER(TRIM(SUBSTITUTE(Raw_Text_Fields!B62,CHAR(160)," "))) -> Priya Menon | F61: =PROPER(TRIM(SUBSTITUTE(Raw_Text_Fields!C62,CHAR(160)," "))) -> Corporate | G61: =PROPER(TRIM(SUBSTITUTE(Raw_Text_Fields!D62,CHAR(160)," "))) -> East | H61: =PROPER(TRIM(SUBSTITUTE(Raw_Text_Fields!E62,CHAR(160)," "))) -> Assam | I61: =PROPER(TRIM(SUBSTITUTE(Raw_Text_Fields!F62,CHAR(160)," "))) -> Guwahati | J61: =PROPER(TRIM(SUBSTITUTE(Raw_Text_Fields!G62,CHAR(160)," "))) -> Office Supplies | K61: =PROPER(TRIM(SUBSTITUTE(Raw_Text_Fields!H62,CHAR(160)," "))) -> Labels | L61: Smart Labels 655 | M61: =PROPER(TRIM(SUBSTITUTE(Raw_Text_Fields!I62,CHAR(160)," "))) -> Same Day | N61: 5 | O61: 4133.85 | P61: 0.2 | Q61: 16535.4 | R61: 12990.21 | S61: 3545.19 | T61: =PROPER(TRIM(SUBSTITUTE(Raw_Text_Fields!J62,CHAR(160)," "))) -> Paid | U61: =PROPER(TRIM(SUBSTITUTE(Raw_Text_Fields!K62,CHAR(160)," "))) -> Cancelled | V61: =IF(OR(P61<0,P61>0.5),0,P61) -> 0.2 | W61: =N61*O61*(1-V61) -> 16535.4 | X61: =W61-R61 -> 3545.19 | Y61: =IFERROR(X61/W61,0) -> 0.21440001 | Z61: =C61-B61 -> 5 | AA61: =IF(B61="","",TEXT(B61,"mmm")) -> Jul | AB61: =IF(B61="","",YEAR(B61)) -> 2024 | AD61: =IF(LEFT(AC61&IF(B61="","; Missing Order Date","")&IF(C61="","; Missing Ship Date","")&IF(P61<0,"; Invalid Discount (Negative)","")&IF(P61>0.5,"; Invalid Discount (Too High)","")&IF(Z61<0,"; Invalid Shipping Record (Ship Before Order)","")&IF(ABS(Q61-W61)>1,"; Sales Mismatch","")&IF(ABS(S61-X61)>1,"; Profit Mismatch","")&IF(COUNTIF($A$2:$A$913,A61)>1,"; Duplicate Order ID Conflict",""),2)="; ",MID(AC61&IF(B61="","; Missing Order Date","")&IF(C61="","; Missing Ship Date","")&IF(P61<0,"; Invalid Discount (Negative)","")&IF(P61>0.5,"; Invalid Discount (Too High)","")&IF(Z61<0,"; Invalid Shipping Record (Ship Before Order)","")&IF(ABS(Q61-W61)>1,"; Sales Mismatch","")&IF(ABS(S61-X61)>1,"; Profit Mismatch","")&IF(COUNTIF($A$2:$A$913,A61)>1,"; Duplicate Order ID Conflict",""),3,500),AC61&IF(B61="","; Missing Order Date","")&IF(C61="","; Missing Ship Date","")&IF(P61<0,"; Invalid Discount (Negative)","")&IF(P61>0.5,"; Invalid Discount (Too High)","")&IF(Z61<0,"; Invalid Shipping Record (Ship Before Order)","")&IF(ABS(Q61-W61)>1,"; Sales Mismatch","")&IF(ABS(S61-X61)>1,"; Profit Mismatch","")&IF(COUNTIF($A$2:$A$913,A61)>1,"; Duplicate Order ID Conflict","")) | AE61: =IF(OR(ISNUMBER(SEARCH("Invalid Discount",AD61)),ISNUMBER(SEARCH("Invalid Shipping Record",AD61)),ISNUMBER(SEARCH("Sales Mismatch",AD61)),ISNUMBER(SEARCH("Profit Mismatch",AD61)),ISNUMBER(SEARCH("Duplicate Order ID Conflict",AD61)),ISNUMBER(SEARCH("Missing Order Date",AD61)),ISNUMBER(SEARCH("Missing Ship Date",AD61))),"Invalid",IF(AD61<>"","Warning","Clean")) -> Clean
A62: ORD-2024-10061 | B62: 45486 | C62: 45492 | D62: CUST-2892 | E62: =PROPER(TRIM(SUBSTITUTE(Raw_Text_Fields!B63,CHAR(160)," "))) -> Ananya Rao | F62: =PROPER(TRIM(SUBSTITUTE(Raw_Text_Fields!C63,CHAR(160)," "))) -> Corporate | G62: =PROPER(TRIM(SUBSTITUTE(Raw_Text_Fields!D63,CHAR(160)," "))) -> East | H62: =PROPER(TRIM(SUBSTITUTE(Raw_Text_Fields!E63,CHAR(160)," "))) -> Assam | I62: =PROPER(TRIM(SUBSTITUTE(Raw_Text_Fields!F63,CHAR(160)," "))) -> Guwahati | J62: =PROPER(TRIM(SUBSTITUTE(Raw_Text_Fields!G63,CHAR(160)," "))) -> Office Supplies | K62: =PROPER(TRIM(SUBSTITUTE(Raw_Text_Fields!H63,CHAR(160)," "))) -> Labels | L62: Eco Labels 210 | M62: =PROPER(TRIM(SUBSTITUTE(Raw_Text_Fields!I63,CHAR(160)," "))) -> Same Day | N62: 3 | O62: 275.76 | P62: 0.2 | Q62: 661.82 | R62: 481.47 | S62: 180.35 | T62: =PROPER(TRIM(SUBSTITUTE(Raw_Text_Fields!J63,CHAR(160)," "))) -> Refunded | U62: =PROPER(TRIM(SUBSTITUTE(Raw_Text_Fields!K63,CHAR(160)," "))) -> Cancelled | V62: =IF(OR(P62<0,P62>0.5),0,P62) -> 0.2 | W62: =N62*O62*(1-V62) -> 661.824 | X62: =W62-R62 -> 180.354 | Y62: =IFERROR(X62/W62,0) -> 0.27251052 | Z62: =C62-B62 -> 6 | AA62: =IF(B62="","",TEXT(B62,"mmm")) -> Jul | AB62: =IF(B62="","",YEAR(B62)) -> 2024 | AD62: =IF(LEFT(AC62&IF(B62="","; Missing Order Date","")&IF(C62="","; Missing Ship Date","")&IF(P62<0,"; Invalid Discount (Negative)","")&IF(P62>0.5,"; Invalid Discount (Too High)","")&IF(Z62<0,"; Invalid Shipping Record (Ship Before Order)","")&IF(ABS(Q62-W62)>1,"; Sales Mismatch","")&IF(ABS(S62-X62)>1,"; Profit Mismatch","")&IF(COUNTIF($A$2:$A$913,A62)>1,"; Duplicate Order ID Conflict",""),2)="; ",MID(AC62&IF(B62="","; Missing Order Date","")&IF(C62="","; Missing Ship Date","")&IF(P62<0,"; Invalid Discount (Negative)","")&IF(P62>0.5,"; Invalid Discount (Too High)","")&IF(Z62<0,"; Invalid Shipping Record (Ship Before Order)","")&IF(ABS(Q62-W62)>1,"; Sales Mismatch","")&IF(ABS(S62-X62)>1,"; Profit Mismatch","")&IF(COUNTIF($A$2:$A$913,A62)>1,"; Duplicate Order ID Conflict",""),3,500),AC62&IF(B62="","; Missing Order Date","")&IF(C62="","; Missing Ship Date","")&IF(P62<0,"; Invalid Discount (Negative)","")&IF(P62>0.5,"; Invalid Discount (Too High)","")&IF(Z62<0,"; Invalid Shipping Record (Ship Before Order)","")&IF(ABS(Q62-W62)>1,"; Sales Mismatch","")&IF(ABS(S62-X62)>1,"; Profit Mismatch","")&IF(COUNTIF($A$2:$A$913,A62)>1,"; Duplicate Order ID Conflict","")) | AE62: =IF(OR(ISNUMBER(SEARCH("Invalid Discount",AD62)),ISNUMBER(SEARCH("Invalid Shipping Record",AD62)),ISNUMBER(SEARCH("Sales Mismatch",AD62)),ISNUMBER(SEARCH("Profit Mismatch",AD62)),ISNUMBER(SEARCH("Duplicate Order ID Conflict",AD62)),ISNUMBER(SEARCH("Missing Order Date",AD62)),ISNUMBER(SEARCH("Missing Ship Date",AD62))),"Invalid",IF(AD62<>"","Warning","Clean")) -> Clean
A63: ORD-2024-10062 | B63: 45398 | C63: 45398 | D63: CUST-7008 | E63: =PROPER(TRIM(SUBSTITUTE(Raw_Text_Fields!B64,CHAR(160)," "))) -> Vikram Iyer | F63: =PROPER(TRIM(SUBSTITUTE(Raw_Text_Fields!C64,CHAR(160)," "))) -> Home Office | G63: =PROPER(TRIM(SUBSTITUTE(Raw_Text_Fields!D64,CHAR(160)," "))) -> East | H63: =PROPER(TRIM(SUBSTITUTE(Raw_Text_Fields!E64,CHAR(160)," "))) -> Bihar | I63: =PROPER(TRIM(SUBSTITUTE(Raw_Text_Fields!F64,CHAR(160)," "))) -> Patna | J63: =PROPER(TRIM(SUBSTITUTE(Raw_Text_Fields!G64,CHAR(160)," "))) -> Furniture | K63: =PROPER(TRIM(SUBSTITUTE(Raw_Text_Fields!H64,CHAR(160)," "))) -> Bookcases | L63: Classic Bookcases 296 | M63: =PROPER(TRIM(SUBSTITUTE(Raw_Text_Fields!I64,CHAR(160)," "))) -> Standard Class | N63: 1 | O63: 949.59 | P63: 0 | Q63: 949.59 | R63: 751.25 | S63: 198.34 | T63: =PROPER(TRIM(SUBSTITUTE(Raw_Text_Fields!J64,CHAR(160)," "))) -> Paid | U63: =PROPER(TRIM(SUBSTITUTE(Raw_Text_Fields!K64,CHAR(160)," "))) -> Completed | V63: =IF(OR(P63<0,P63>0.5),0,P63) -> 0 | W63: =N63*O63*(1-V63) -> 949.59 | X63: =W63-R63 -> 198.34 | Y63: =IFERROR(X63/W63,0) -> 0.20886909 | Z63: =C63-B63 -> 0 | AA63: =IF(B63="","",TEXT(B63,"mmm")) -> Apr | AB63: =IF(B63="","",YEAR(B63)) -> 2024 | AD63: =IF(LEFT(AC63&IF(B63="","; Missing Order Date","")&IF(C63="","; Missing Ship Date","")&IF(P63<0,"; Invalid Discount (Negative)","")&IF(P63>0.5,"; Invalid Discount (Too High)","")&IF(Z63<0,"; Invalid Shipping Record (Ship Before Order)","")&IF(ABS(Q63-W63)>1,"; Sales Mismatch","")&IF(ABS(S63-X63)>1,"; Profit Mismatch","")&IF(COUNTIF($A$2:$A$913,A63)>1,"; Duplicate Order ID Conflict",""),2)="; ",MID(AC63&IF(B63="","; Missing Order Date","")&IF(C63="","; Missing Ship Date","")&IF(P63<0,"; Invalid Discount (Negative)","")&IF(P63>0.5,"; Invalid Discount (Too High)","")&IF(Z63<0,"; Invalid Shipping Record (Ship Before Order)","")&IF(ABS(Q63-W63)>1,"; Sales Mismatch","")&IF(ABS(S63-X63)>1,"; Profit Mismatch","")&IF(COUNTIF($A$2:$A$913,A63)>1,"; Duplicate Order ID Conflict",""),3,500),AC63&IF(B63="","; Missing Order Date","")&IF(C63="","; Missing Ship Date","")&IF(P63<0,"; Invalid Discount (Negative)","")&IF(P63>0.5,"; Invalid Discount (Too High)","")&IF(Z63<0,"; Invalid Shipping Record (Ship Before Order)","")&IF(ABS(Q63-W63)>1,"; Sales Mismatch","")&IF(ABS(S63-X63)>1,"; Profit Mismatch","")&IF(COUNTIF($A$2:$A$913,A63)>1,"; Duplicate Order ID Conflict","")) | AE63: =IF(OR(ISNUMBER(SEARCH("Invalid Discount",AD63)),ISNUMBER(SEARCH("Invalid Shipping Record",AD63)),ISNUMBER(SEARCH("Sales Mismatch",AD63)),ISNUMBER(SEARCH("Profit Mismatch",AD63)),ISNUMBER(SEARCH("Duplicate Order ID Conflict",AD63)),ISNUMBER(SEARCH("Missing Order Date",AD63)),ISNUMBER(SEARCH("Missing Ship Date",AD63))),"Invalid",IF(AD63<>"","Warning","Clean")) -> Clean
A64: ORD-2024-10063 | B64: 45595 | C64: 45598 | D64: CUST-4900 | E64: =PROPER(TRIM(SUBSTITUTE(Raw_Text_Fields!B65,CHAR(160)," "))) -> Sneha Kapoor | F64: =PROPER(TRIM(SUBSTITUTE(Raw_Text_Fields!C65,CHAR(160)," "))) -> Home Office | G64: =PROPER(TRIM(SUBSTITUTE(Raw_Text_Fields!D65,CHAR(160)," "))) -> North | H64: =PROPER(TRIM(SUBSTITUTE(Raw_Text_Fields!E65,CHAR(160)," "))) -> Rajasthan | I64: =PROPER(TRIM(SUBSTITUTE(Raw_Text_Fields!F65,CHAR(160)," "))) -> Jaipur | J64: =PROPER(TRIM(SUBSTITUTE(Raw_Text_Fields!G65,CHAR(160)," "))) -> Technology | K64: =PROPER(TRIM(SUBSTITUTE(Raw_Text_Fields!H65,CHAR(160)," "))) -> Phones | L64: Basic Phones 230 | M64: =PROPER(TRIM(SUBSTITUTE(Raw_Text_Fields!I65,CHAR(160)," "))) -> Standard Class | N64: 9 | O64: 3042.29 | P64: 0.2 | Q64: 21904.49 | R64: 13570.55 | S64: 8333.94 | T64: =PROPER(TRIM(SUBSTITUTE(Raw_Text_Fields!J65,CHAR(160)," "))) -> Paid | U64: =PROPER(TRIM(SUBSTITUTE(Raw_Text_Fields!K65,CHAR(160)," "))) -> Completed | V64: =IF(OR(P64<0,P64>0.5),0,P64) -> 0.2 | W64: =N64*O64*(1-V64) -> 21904.488 | X64: =W64-R64 -> 8333.938 | Y64: =IFERROR(X64/W64,0) -> 0.38046714 | Z64: =C64-B64 -> 3 | AA64: =IF(B64="","",TEXT(B64,"mmm")) -> Oct | AB64: =IF(B64="","",YEAR(B64)) -> 2024 | AD64: =IF(LEFT(AC64&IF(B64="","; Missing Order Date","")&IF(C64="","; Missing Ship Date","")&IF(P64<0,"; Invalid Discount (Negative)","")&IF(P64>0.5,"; Invalid Discount (Too High)","")&IF(Z64<0,"; Invalid Shipping Record (Ship Before Order)","")&IF(ABS(Q64-W64)>1,"; Sales Mismatch","")&IF(ABS(S64-X64)>1,"; Profit Mismatch","")&IF(COUNTIF($A$2:$A$913,A64)>1,"; Duplicate Order ID Conflict",""),2)="; ",MID(AC64&IF(B64="","; Missing Order Date","")&IF(C64="","; Missing Ship Date","")&IF(P64<0,"; Invalid Discount (Negative)","")&IF(P64>0.5,"; Invalid Discount (Too High)","")&IF(Z64<0,"; Invalid Shipping Record (Ship Before Order)","")&IF(ABS(Q64-W64)>1,"; Sales Mismatch","")&IF(ABS(S64-X64)>1,"; Profit Mismatch","")&IF(COUNTIF($A$2:$A$913,A64)>1,"; Duplicate Order ID Conflict",""),3,500),AC64&IF(B64="","; Missing Order Date","")&IF(C64="","; Missing Ship Date","")&IF(P64<0,"; Invalid Discount (Negative)","")&IF(P64>0.5,"; Invalid Discount (Too High)","")&IF(Z64<0,"; Invalid Shipping Record (Ship Before Order)","")&IF(ABS(Q64-W64)>1,"; Sales Mismatch","")&IF(ABS(S64-X64)>1,"; Profit Mismatch","")&IF(COUNTIF($A$2:$A$913,A64)>1,"; Duplicate Order ID Conflict","")) | AE64: =IF(OR(ISNUMBER(SEARCH("Invalid Discount",AD64)),ISNUMBER(SEARCH("Invalid Shipping Record",AD64)),ISNUMBER(SEARCH("Sales Mismatch",AD64)),ISNUMBER(SEARCH("Profit Mismatch",AD64)),ISNUMBER(SEARCH("Duplicate Order ID Conflict",AD64)),ISNUMBER(SEARCH("Missing Order Date",AD64)),ISNUMBER(SEARCH("Missing Ship Date",AD64))),"Invalid",IF(AD64<>"","Warning","Clean")) -> Clean
A65: ORD-2024-10064 | B65: 45316 | C65: 45323 | D65: CUST-5382 | E65: =PROPER(TRIM(SUBSTITUTE(Raw_Text_Fields!B66,CHAR(160)," "))) -> Sneha Kapoor | F65: =PROPER(TRIM(SUBSTITUTE(Raw_Text_Fields!C66,CHAR(160)," "))) -> Home Office | G65: =PROPER(TRIM(SUBSTITUTE(Raw_Text_Fields!D66,CHAR(160)," "))) -> North | H65: =PROPER(TRIM(SUBSTITUTE(Raw_Text_Fields!E66,CHAR(160)," "))) -> Haryana | I65: =PROPER(TRIM(SUBSTITUTE(Raw_Text_Fields!F66,CHAR(160)," "))) -> Gurugram | J65: =PROPER(TRIM(SUBSTITUTE(Raw_Text_Fields!G66,CHAR(160)," "))) -> Office Supplies | K65: =PROPER(TRIM(SUBSTITUTE(Raw_Text_Fields!H66,CHAR(160)," "))) -> Binders | L65: Pro Binders 690 | M65: =PROPER(TRIM(SUBSTITUTE(Raw_Text_Fields!I66,CHAR(160)," "))) -> Same Day | N65: 2 | O65: 2832.77 | P65: 0.15 | Q65: 4815.71 | R65: 3027.75 | S65: 1917.47 | T65: =PROPER(TRIM(SUBSTITUTE(Raw_Text_Fields!J66,CHAR(160)," "))) -> Paid | U65: =PROPER(TRIM(SUBSTITUTE(Raw_Text_Fields!K66,CHAR(160)," "))) -> Completed | V65: =IF(OR(P65<0,P65>0.5),0,P65) -> 0.15 | W65: =N65*O65*(1-V65) -> 4815.709 | X65: =W65-R65 -> 1787.959 | Y65: =IFERROR(X65/W65,0) -> 0.37127638 | Z65: =C65-B65 -> 7 | AA65: =IF(B65="","",TEXT(B65,"mmm")) -> Jan | AB65: =IF(B65="","",YEAR(B65)) -> 2024 | AD65: =IF(LEFT(AC65&IF(B65="","; Missing Order Date","")&IF(C65="","; Missing Ship Date","")&IF(P65<0,"; Invalid Discount (Negative)","")&IF(P65>0.5,"; Invalid Discount (Too High)","")&IF(Z65<0,"; Invalid Shipping Record (Ship Before Order)","")&IF(ABS(Q65-W65)>1,"; Sales Mismatch","")&IF(ABS(S65-X65)>1,"; Profit Mismatch","")&IF(COUNTIF($A$2:$A$913,A65)>1,"; Duplicate Order ID Conflict",""),2)="; ",MID(AC65&IF(B65="","; Missing Order Date","")&IF(C65="","; Missing Ship Date","")&IF(P65<0,"; Invalid Discount (Negative)","")&IF(P65>0.5,"; Invalid Discount (Too High)","")&IF(Z65<0,"; Invalid Shipping Record (Ship Before Order)","")&IF(ABS(Q65-W65)>1,"; Sales Mismatch","")&IF(ABS(S65-X65)>1,"; Profit Mismatch","")&IF(COUNTIF($A$2:$A$913,A65)>1,"; Duplicate Order ID Conflict",""),3,500),AC65&IF(B65="","; Missing Order Date","")&IF(C65="","; Missing Ship Date","")&IF(P65<0,"; Invalid Discount (Negative)","")&IF(P65>0.5,"; Invalid Discount (Too High)","")&IF(Z65<0,"; Invalid Shipping Record (Ship Before Order)","")&IF(ABS(Q65-W65)>1,"; Sales Mismatch","")&IF(ABS(S65-X65)>1,"; Profit Mismatch","")&IF(COUNTIF($A$2:$A$913,A65)>1,"; Duplicate Order ID Conflict","")) -> Profit Mismatch | AE65: =IF(OR(ISNUMBER(SEARCH("Invalid Discount",AD65)),ISNUMBER(SEARCH("Invalid Shipping Record",AD65)),ISNUMBER(SEARCH("Sales Mismatch",AD65)),ISNUMBER(SEARCH("Profit Mismatch",AD65)),ISNUMBER(SEARCH("Duplicate Order ID Conflict",AD65)),ISNUMBER(SEARCH("Missing Order Date",AD65)),ISNUMBER(SEARCH("Missing Ship Date",AD65))),"Invalid",IF(AD65<>"","Warning","Clean")) -> Invalid
A66: ORD-2024-10065 | B66: 45649 | C66: 45655 | D66: CUST-2749 | E66: =PROPER(TRIM(SUBSTITUTE(Raw_Text_Fields!B67,CHAR(160)," "))) -> Aarav Sharma | F66: =PROPER(TRIM(SUBSTITUTE(Raw_Text_Fields!C67,CHAR(160)," "))) -> Corporate | G66: =PROPER(TRIM(SUBSTITUTE(Raw_Text_Fields!D67,CHAR(160)," "))) -> East | H66: =PROPER(TRIM(SUBSTITUTE(Raw_Text_Fields!E67,CHAR(160)," "))) -> Jharkhand | I66: =PROPER(TRIM(SUBSTITUTE(Raw_Text_Fields!F67,CHAR(160)," "))) -> Ranchi | J66: =PROPER(TRIM(SUBSTITUTE(Raw_Text_Fields!G67,CHAR(160)," "))) -> Office Supplies | K66: =PROPER(TRIM(SUBSTITUTE(Raw_Text_Fields!H67,CHAR(160)," "))) -> Paper | L66: Classic Paper 458 | M66: =PROPER(TRIM(SUBSTITUTE(Raw_Text_Fields!I67,CHAR(160)," "))) -> First Class | N66: 7 | O66: 447.84 | P66: 0 | Q66: 3134.88 | R66: 2367.63 | S66: 767.25 | T66: =PROPER(TRIM(SUBSTITUTE(Raw_Text_Fields!J67,CHAR(160)," "))) -> Refunded | U66: =PROPER(TRIM(SUBSTITUTE(Raw_Text_Fields!K67,CHAR(160)," "))) -> Returned | V66: =IF(OR(P66<0,P66>0.5),0,P66) -> 0 | W66: =N66*O66*(1-V66) -> 3134.88 | X66: =W66-R66 -> 767.25 | Y66: =IFERROR(X66/W66,0) -> 0.24474621 | Z66: =C66-B66 -> 6 | AA66: =IF(B66="","",TEXT(B66,"mmm")) -> Dec | AB66: =IF(B66="","",YEAR(B66)) -> 2024 | AD66: =IF(LEFT(AC66&IF(B66="","; Missing Order Date","")&IF(C66="","; Missing Ship Date","")&IF(P66<0,"; Invalid Discount (Negative)","")&IF(P66>0.5,"; Invalid Discount (Too High)","")&IF(Z66<0,"; Invalid Shipping Record (Ship Before Order)","")&IF(ABS(Q66-W66)>1,"; Sales Mismatch","")&IF(ABS(S66-X66)>1,"; Profit Mismatch","")&IF(COUNTIF($A$2:$A$913,A66)>1,"; Duplicate Order ID Conflict",""),2)="; ",MID(AC66&IF(B66="","; Missing Order Date","")&IF(C66="","; Missing Ship Date","")&IF(P66<0,"; Invalid Discount (Negative)","")&IF(P66>0.5,"; Invalid Discount (Too High)","")&IF(Z66<0,"; Invalid Shipping Record (Ship Before Order)","")&IF(ABS(Q66-W66)>1,"; Sales Mismatch","")&IF(ABS(S66-X66)>1,"; Profit Mismatch","")&IF(COUNTIF($A$2:$A$913,A66)>1,"; Duplicate Order ID Conflict",""),3,500),AC66&IF(B66="","; Missing Order Date","")&IF(C66="","; Missing Ship Date","")&IF(P66<0,"; Invalid Discount (Negative)","")&IF(P66>0.5,"; Invalid Discount (Too High)","")&IF(Z66<0,"; Invalid Shipping Record (Ship Before Order)","")&IF(ABS(Q66-W66)>1,"; Sales Mismatch","")&IF(ABS(S66-X66)>1,"; Profit Mismatch","")&IF(COUNTIF($A$2:$A$913,A66)>1,"; Duplicate Order ID Conflict","")) | AE66: =IF(OR(ISNUMBER(SEARCH("Invalid Discount",AD66)),ISNUMBER(SEARCH("Invalid Shipping Record",AD66)),ISNUMBER(SEARCH("Sales Mismatch",AD66)),ISNUMBER(SEARCH("Profit Mismatch",AD66)),ISNUMBER(SEARCH("Duplicate Order ID Conflict",AD66)),ISNUMBER(SEARCH("Missing Order Date",AD66)),ISNUMBER(SEARCH("Missing Ship Date",AD66))),"Invalid",IF(AD66<>"","Warning","Clean")) -> Clean
A67: ORD-2024-10066 | B67: 45404 | C67: 45409 | D67: CUST-2463 | E67: =PROPER(TRIM(SUBSTITUTE(Raw_Text_Fields!B68,CHAR(160)," "))) -> Mira Das | F67: =PROPER(TRIM(SUBSTITUTE(Raw_Text_Fields!C68,CHAR(160)," "))) -> Home Office | G67: =PROPER(TRIM(SUBSTITUTE(Raw_Text_Fields!D68,CHAR(160)," "))) -> West | H67: =PROPER(TRIM(SUBSTITUTE(Raw_Text_Fields!E68,CHAR(160)," "))) -> Maharashtra | I67: =PROPER(TRIM(SUBSTITUTE(Raw_Text_Fields!F68,CHAR(160)," "))) -> Mumbai | J67: =PROPER(TRIM(SUBSTITUTE(Raw_Text_Fields!G68,CHAR(160)," "))) -> Office Supplies | K67: =PROPER(TRIM(SUBSTITUTE(Raw_Text_Fields!H68,CHAR(160)," "))) -> Paper | L67: Pro Paper 552 | M67: =PROPER(TRIM(SUBSTITUTE(Raw_Text_Fields!I68,CHAR(160)," "))) -> Second Class | N67: 1 | O67: 4280.19 | P67: 0.05 | Q67: 4066.18 | R67: 2628.92 | S67: 1437.26 | T67: =PROPER(TRIM(SUBSTITUTE(Raw_Text_Fields!J68,CHAR(160)," "))) -> Paid | U67: =PROPER(TRIM(SUBSTITUTE(Raw_Text_Fields!K68,CHAR(160)," "))) -> Completed | V67: =IF(OR(P67<0,P67>0.5),0,P67) -> 0.05 | W67: =N67*O67*(1-V67) -> 4066.1805 | X67: =W67-R67 -> 1437.2605 | Y67: =IFERROR(X67/W67,0) -> 0.35346697 | Z67: =C67-B67 -> 5 | AA67: =IF(B67="","",TEXT(B67,"mmm")) -> Apr | AB67: =IF(B67="","",YEAR(B67)) -> 2024 | AD67: =IF(LEFT(AC67&IF(B67="","; Missing Order Date","")&IF(C67="","; Missing Ship Date","")&IF(P67<0,"; Invalid Discount (Negative)","")&IF(P67>0.5,"; Invalid Discount (Too High)","")&IF(Z67<0,"; Invalid Shipping Record (Ship Before Order)","")&IF(ABS(Q67-W67)>1,"; Sales Mismatch","")&IF(ABS(S67-X67)>1,"; Profit Mismatch","")&IF(COUNTIF($A$2:$A$913,A67)>1,"; Duplicate Order ID Conflict",""),2)="; ",MID(AC67&IF(B67="","; Missing Order Date","")&IF(C67="","; Missing Ship Date","")&IF(P67<0,"; Invalid Discount (Negative)","")&IF(P67>0.5,"; Invalid Discount (Too High)","")&IF(Z67<0,"; Invalid Shipping Record (Ship Before Order)","")&IF(ABS(Q67-W67)>1,"; Sales Mismatch","")&IF(ABS(S67-X67)>1,"; Profit Mismatch","")&IF(COUNTIF($A$2:$A$913,A67)>1,"; Duplicate Order ID Conflict",""),3,500),AC67&IF(B67="","; Missing Order Date","")&IF(C67="","; Missing Ship Date","")&IF(P67<0,"; Invalid Discount (Negative)","")&IF(P67>0.5,"; Invalid Discount (Too High)","")&IF(Z67<0,"; Invalid Shipping Record (Ship Before Order)","")&IF(ABS(Q67-W67)>1,"; Sales Mismatch","")&IF(ABS(S67-X67)>1,"; Profit Mismatch","")&IF(COUNTIF($A$2:$A$913,A67)>1,"; Duplicate Order ID Conflict","")) | AE67: =IF(OR(ISNUMBER(SEARCH("Invalid Discount",AD67)),ISNUMBER(SEARCH("Invalid Shipping Record",AD67)),ISNUMBER(SEARCH("Sales Mismatch",AD67)),ISNUMBER(SEARCH("Profit Mismatch",AD67)),ISNUMBER(SEARCH("Duplicate Order ID Conflict",AD67)),ISNUMBER(SEARCH("Missing Order Date",AD67)),ISNUMBER(SEARCH("Missing Ship Date",AD67))),"Invalid",IF(AD67<>"","Warning","Clean")) -> Clean
A68: ORD-2025-10067 | B68: 45897 | C68: 45901 | D68: CUST-1504 | E68: =PROPER(TRIM(SUBSTITUTE(Raw_Text_Fields!B69,CHAR(160)," "))) -> Karan Malhotra | F68: =PROPER(TRIM(SUBSTITUTE(Raw_Text_Fields!C69,CHAR(160)," "))) -> Small Business | G68: =PROPER(TRIM(SUBSTITUTE(Raw_Text_Fields!D69,CHAR(160)," "))) -> South | H68: =PROPER(TRIM(SUBSTITUTE(Raw_Text_Fields!E69,CHAR(160)," "))) -> Tamil Nadu | I68: =PROPER(TRIM(SUBSTITUTE(Raw_Text_Fields!F69,CHAR(160)," "))) -> Chennai | J68: =PROPER(TRIM(SUBSTITUTE(Raw_Text_Fields!G69,CHAR(160)," "))) -> Technology | K68: =PROPER(TRIM(SUBSTITUTE(Raw_Text_Fields!H69,CHAR(160)," "))) -> Accessories | L68: Elite Accessories 187 | M68: =PROPER(TRIM(SUBSTITUTE(Raw_Text_Fields!I69,CHAR(160)," "))) -> Same Day | N68: 7 | O68: 1057.46 | P68: 0.05 | Q68: 7032.11 | R68: 4610.34 | S68: 2421.77 | T68: =PROPER(TRIM(SUBSTITUTE(Raw_Text_Fields!J69,CHAR(160)," "))) -> Paid | U68: =PROPER(TRIM(SUBSTITUTE(Raw_Text_Fields!K69,CHAR(160)," "))) -> Completed | V68: =IF(OR(P68<0,P68>0.5),0,P68) -> 0.05 | W68: =N68*O68*(1-V68) -> 7032.109 | X68: =W68-R68 -> 2421.769 | Y68: =IFERROR(X68/W68,0) -> 0.3443873 | Z68: =C68-B68 -> 4 | AA68: =IF(B68="","",TEXT(B68,"mmm")) -> Aug | AB68: =IF(B68="","",YEAR(B68)) -> 2025 | AD68: =IF(LEFT(AC68&IF(B68="","; Missing Order Date","")&IF(C68="","; Missing Ship Date","")&IF(P68<0,"; Invalid Discount (Negative)","")&IF(P68>0.5,"; Invalid Discount (Too High)","")&IF(Z68<0,"; Invalid Shipping Record (Ship Before Order)","")&IF(ABS(Q68-W68)>1,"; Sales Mismatch","")&IF(ABS(S68-X68)>1,"; Profit Mismatch","")&IF(COUNTIF($A$2:$A$913,A68)>1,"; Duplicate Order ID Conflict",""),2)="; ",MID(AC68&IF(B68="","; Missing Order Date","")&IF(C68="","; Missing Ship Date","")&IF(P68<0,"; Invalid Discount (Negative)","")&IF(P68>0.5,"; Invalid Discount (Too High)","")&IF(Z68<0,"; Invalid Shipping Record (Ship Before Order)","")&IF(ABS(Q68-W68)>1,"; Sales Mismatch","")&IF(ABS(S68-X68)>1,"; Profit Mismatch","")&IF(COUNTIF($A$2:$A$913,A68)>1,"; Duplicate Order ID Conflict",""),3,500),AC68&IF(B68="","; Missing Order Date","")&IF(C68="","; Missing Ship Date","")&IF(P68<0,"; Invalid Discount (Negative)","")&IF(P68>0.5,"; Invalid Discount (Too High)","")&IF(Z68<0,"; Invalid Shipping Record (Ship Before Order)","")&IF(ABS(Q68-W68)>1,"; Sales Mismatch","")&IF(ABS(S68-X68)>1,"; Profit Mismatch","")&IF(COUNTIF($A$2:$A$913,A68)>1,"; Duplicate Order ID Conflict","")) | AE68: =IF(OR(ISNUMBER(SEARCH("Invalid Discount",AD68)),ISNUMBER(SEARCH("Invalid Shipping Record",AD68)),ISNUMBER(SEARCH("Sales Mismatch",AD68)),ISNUMBER(SEARCH("Profit Mismatch",AD68)),ISNUMBER(SEARCH("Duplicate Order ID Conflict",AD68)),ISNUMBER(SEARCH("Missing Order Date",AD68)),ISNUMBER(SEARCH("Missing Ship Date",AD68))),"Invalid",IF(AD68<>"","Warning","Clean")) -> Clean
A69: ORD-2025-10068 | B69: 45691 | C69: 45695 | D69: CUST-8282 | E69: =PROPER(TRIM(SUBSTITUTE(Raw_Text_Fields!B70,CHAR(160)," "))) -> Kabir Singh | F69: =PROPER(TRIM(SUBSTITUTE(Raw_Text_Fields!C70,CHAR(160)," "))) -> Consumer | G69: =PROPER(TRIM(SUBSTITUTE(Raw_Text_Fields!D70,CHAR(160)," "))) -> North | H69: =PROPER(TRIM(SUBSTITUTE(Raw_Text_Fields!E70,CHAR(160)," "))) -> Haryana | I69: =PROPER(TRIM(SUBSTITUTE(Raw_Text_Fields!F70,CHAR(160)," "))) -> Gurugram | J69: =PROPER(TRIM(SUBSTITUTE(Raw_Text_Fields!G70,CHAR(160)," "))) -> Office Supplies | K69: =PROPER(TRIM(SUBSTITUTE(Raw_Text_Fields!H70,CHAR(160)," "))) -> Paper | L69: Eco Paper 922 | M69: =PROPER(TRIM(SUBSTITUTE(Raw_Text_Fields!I70,CHAR(160)," "))) -> First Class | N69: 7 | O69: 3609.34 | P69: 0.05 | Q69: 24002.11 | R69: 18707.57 | S69: 5294.54 | T69: =PROPER(TRIM(SUBSTITUTE(Raw_Text_Fields!J70,CHAR(160)," "))) -> Paid | U69: =PROPER(TRIM(SUBSTITUTE(Raw_Text_Fields!K70,CHAR(160)," "))) -> Completed | V69: =IF(OR(P69<0,P69>0.5),0,P69) -> 0.05 | W69: =N69*O69*(1-V69) -> 24002.111 | X69: =W69-R69 -> 5294.541 | Y69: =IFERROR(X69/W69,0) -> 0.22058647 | Z69: =C69-B69 -> 4 | AA69: =IF(B69="","",TEXT(B69,"mmm")) -> Feb | AB69: =IF(B69="","",YEAR(B69)) -> 2025 | AD69: =IF(LEFT(AC69&IF(B69="","; Missing Order Date","")&IF(C69="","; Missing Ship Date","")&IF(P69<0,"; Invalid Discount (Negative)","")&IF(P69>0.5,"; Invalid Discount (Too High)","")&IF(Z69<0,"; Invalid Shipping Record (Ship Before Order)","")&IF(ABS(Q69-W69)>1,"; Sales Mismatch","")&IF(ABS(S69-X69)>1,"; Profit Mismatch","")&IF(COUNTIF($A$2:$A$913,A69)>1,"; Duplicate Order ID Conflict",""),2)="; ",MID(AC69&IF(B69="","; Missing Order Date","")&IF(C69="","; Missing Ship Date","")&IF(P69<0,"; Invalid Discount (Negative)","")&IF(P69>0.5,"; Invalid Discount (Too High)","")&IF(Z69<0,"; Invalid Shipping Record (Ship Before Order)","")&IF(ABS(Q69-W69)>1,"; Sales Mismatch","")&IF(ABS(S69-X69)>1,"; Profit Mismatch","")&IF(COUNTIF($A$2:$A$913,A69)>1,"; Duplicate Order ID Conflict",""),3,500),AC69&IF(B69="","; Missing Order Date","")&IF(C69="","; Missing Ship Date","")&IF(P69<0,"; Invalid Discount (Negative)","")&IF(P69>0.5,"; Invalid Discount (Too High)","")&IF(Z69<0,"; Invalid Shipping Record (Ship Before Order)","")&IF(ABS(Q69-W69)>1,"; Sales Mismatch","")&IF(ABS(S69-X69)>1,"; Profit Mismatch","")&IF(COUNTIF($A$2:$A$913,A69)>1,"; Duplicate Order ID Conflict","")) | AE69: =IF(OR(ISNUMBER(SEARCH("Invalid Discount",AD69)),ISNUMBER(SEARCH("Invalid Shipping Record",AD69)),ISNUMBER(SEARCH("Sales Mismatch",AD69)),ISNUMBER(SEARCH("Profit Mismatch",AD69)),ISNUMBER(SEARCH("Duplicate Order ID Conflict",AD69)),ISNUMBER(SEARCH("Missing Order Date",AD69)),ISNUMBER(SEARCH("Missing Ship Date",AD69))),"Invalid",IF(AD69<>"","Warning","Clean")) -> Clean
A70: ORD-2024-10069 | B70: 45606 | C70: 45609 | D70: CUST-6054 | E70: =PROPER(TRIM(SUBSTITUTE(Raw_Text_Fields!B71,CHAR(160)," "))) -> Isha Nair | F70: =PROPER(TRIM(SUBSTITUTE(Raw_Text_Fields!C71,CHAR(160)," "))) -> Corporate | G70: =PROPER(TRIM(SUBSTITUTE(Raw_Text_Fields!D71,CHAR(160)," "))) -> East | H70: =PROPER(TRIM(SUBSTITUTE(Raw_Text_Fields!E71,CHAR(160)," "))) -> Jharkhand | I70: =PROPER(TRIM(SUBSTITUTE(Raw_Text_Fields!F71,CHAR(160)," "))) -> Ranchi | J70: =PROPER(TRIM(SUBSTITUTE(Raw_Text_Fields!G71,CHAR(160)," "))) -> Office Supplies | K70: =PROPER(TRIM(SUBSTITUTE(Raw_Text_Fields!H71,CHAR(160)," "))) -> Storage | L70: Pro Storage 975 | M70: =PROPER(TRIM(SUBSTITUTE(Raw_Text_Fields!I71,CHAR(160)," "))) -> Second Class | N70: 9 | O70: 2211.12 | P70: 0 | Q70: 19900.08 | R70: 10962.66 | S70: 8937.42 | T70: =PROPER(TRIM(SUBSTITUTE(Raw_Text_Fields!J71,CHAR(160)," "))) -> Failed | U70: =PROPER(TRIM(SUBSTITUTE(Raw_Text_Fields!K71,CHAR(160)," "))) -> Returned | V70: =IF(OR(P70<0,P70>0.5),0,P70) -> 0 | W70: =N70*O70*(1-V70) -> 19900.08 | X70: =W70-R70 -> 8937.42 | Y70: =IFERROR(X70/W70,0) -> 0.44911478 | Z70: =C70-B70 -> 3 | AA70: =IF(B70="","",TEXT(B70,"mmm")) -> Nov | AB70: =IF(B70="","",YEAR(B70)) -> 2024 | AD70: =IF(LEFT(AC70&IF(B70="","; Missing Order Date","")&IF(C70="","; Missing Ship Date","")&IF(P70<0,"; Invalid Discount (Negative)","")&IF(P70>0.5,"; Invalid Discount (Too High)","")&IF(Z70<0,"; Invalid Shipping Record (Ship Before Order)","")&IF(ABS(Q70-W70)>1,"; Sales Mismatch","")&IF(ABS(S70-X70)>1,"; Profit Mismatch","")&IF(COUNTIF($A$2:$A$913,A70)>1,"; Duplicate Order ID Conflict",""),2)="; ",MID(AC70&IF(B70="","; Missing Order Date","")&IF(C70="","; Missing Ship Date","")&IF(P70<0,"; Invalid Discount (Negative)","")&IF(P70>0.5,"; Invalid Discount (Too High)","")&IF(Z70<0,"; Invalid Shipping Record (Ship Before Order)","")&IF(ABS(Q70-W70)>1,"; Sales Mismatch","")&IF(ABS(S70-X70)>1,"; Profit Mismatch","")&IF(COUNTIF($A$2:$A$913,A70)>1,"; Duplicate Order ID Conflict",""),3,500),AC70&IF(B70="","; Missing Order Date","")&IF(C70="","; Missing Ship Date","")&IF(P70<0,"; Invalid Discount (Negative)","")&IF(P70>0.5,"; Invalid Discount (Too High)","")&IF(Z70<0,"; Invalid Shipping Record (Ship Before Order)","")&IF(ABS(Q70-W70)>1,"; Sales Mismatch","")&IF(ABS(S70-X70)>1,"; Profit Mismatch","")&IF(COUNTIF($A$2:$A$913,A70)>1,"; Duplicate Order ID Conflict","")) | AE70: =IF(OR(ISNUMBER(SEARCH("Invalid Discount",AD70)),ISNUMBER(SEARCH("Invalid Shipping Record",AD70)),ISNUMBER(SEARCH("Sales Mismatch",AD70)),ISNUMBER(SEARCH("Profit Mismatch",AD70)),ISNUMBER(SEARCH("Duplicate Order ID Conflict",AD70)),ISNUMBER(SEARCH("Missing Order Date",AD70)),ISNUMBER(SEARCH("Missing Ship Date",AD70))),"Invalid",IF(AD70<>"","Warning","Clean")) -> Clean
A71: ORD-2024-10070 | B71: 45391 | C71: 45396 | D71: CUST-5979 | E71: =PROPER(TRIM(SUBSTITUTE(Raw_Text_Fields!B72,CHAR(160)," "))) -> Neha Gupta | F71: =PROPER(TRIM(SUBSTITUTE(Raw_Text_Fields!C72,CHAR(160)," "))) -> Small Business | G71: =PROPER(TRIM(SUBSTITUTE(Raw_Text_Fields!D72,CHAR(160)," "))) -> West | H71: =PROPER(TRIM(SUBSTITUTE(Raw_Text_Fields!E72,CHAR(160)," "))) -> Gujarat | I71: =PROPER(TRIM(SUBSTITUTE(Raw_Text_Fields!F72,CHAR(160)," "))) -> Ahmedabad | J71: =PROPER(TRIM(SUBSTITUTE(Raw_Text_Fields!G72,CHAR(160)," "))) -> Technology | K71: =PROPER(TRIM(SUBSTITUTE(Raw_Text_Fields!H72,CHAR(160)," "))) -> Machines | L71: Prime Machines 782 | M71: =PROPER(TRIM(SUBSTITUTE(Raw_Text_Fields!I72,CHAR(160)," "))) -> Same Day | N71: 7 | O71: 3417.09 | P71: 0.1 | Q71: 21527.67 | R71: 18287.58 | S71: 3240.09 | T71: =PROPER(TRIM(SUBSTITUTE(Raw_Text_Fields!J72,CHAR(160)," "))) -> Refunded | U71: =PROPER(TRIM(SUBSTITUTE(Raw_Text_Fields!K72,CHAR(160)," "))) -> Returned | V71: =IF(OR(P71<0,P71>0.5),0,P71) -> 0.1 | W71: =N71*O71*(1-V71) -> 21527.667 | X71: =W71-R71 -> 3240.087 | Y71: =IFERROR(X71/W71,0) -> 0.15050804 | Z71: =C71-B71 -> 5 | AA71: =IF(B71="","",TEXT(B71,"mmm")) -> Apr | AB71: =IF(B71="","",YEAR(B71)) -> 2024 | AD71: =IF(LEFT(AC71&IF(B71="","; Missing Order Date","")&IF(C71="","; Missing Ship Date","")&IF(P71<0,"; Invalid Discount (Negative)","")&IF(P71>0.5,"; Invalid Discount (Too High)","")&IF(Z71<0,"; Invalid Shipping Record (Ship Before Order)","")&IF(ABS(Q71-W71)>1,"; Sales Mismatch","")&IF(ABS(S71-X71)>1,"; Profit Mismatch","")&IF(COUNTIF($A$2:$A$913,A71)>1,"; Duplicate Order ID Conflict",""),2)="; ",MID(AC71&IF(B71="","; Missing Order Date","")&IF(C71="","; Missing Ship Date","")&IF(P71<0,"; Invalid Discount (Negative)","")&IF(P71>0.5,"; Invalid Discount (Too High)","")&IF(Z71<0,"; Invalid Shipping Record (Ship Before Order)","")&IF(ABS(Q71-W71)>1,"; Sales Mismatch","")&IF(ABS(S71-X71)>1,"; Profit Mismatch","")&IF(COUNTIF($A$2:$A$913,A71)>1,"; Duplicate Order ID Conflict",""),3,500),AC71&IF(B71="","; Missing Order Date","")&IF(C71="","; Missing Ship Date","")&IF(P71<0,"; Invalid Discount (Negative)","")&IF(P71>0.5,"; Invalid Discount (Too High)","")&IF(Z71<0,"; Invalid Shipping Record (Ship Before Order)","")&IF(ABS(Q71-W71)>1,"; Sales Mismatch","")&IF(ABS(S71-X71)>1,"; Profit Mismatch","")&IF(COUNTIF($A$2:$A$913,A71)>1,"; Duplicate Order ID Conflict","")) | AE71: =IF(OR(ISNUMBER(SEARCH("Invalid Discount",AD71)),ISNUMBER(SEARCH("Invalid Shipping Record",AD71)),ISNUMBER(SEARCH("Sales Mismatch",AD71)),ISNUMBER(SEARCH("Profit Mismatch",AD71)),ISNUMBER(SEARCH("Duplicate Order ID Conflict",AD71)),ISNUMBER(SEARCH("Missing Order Date",AD71)),ISNUMBER(SEARCH("Missing Ship Date",AD71))),"Invalid",IF(AD71<>"","Warning","Clean")) -> Clean
A72: ORD-2025-10071 | B72: 45891 | C72: 45896 | D72: CUST-5582 | E72: =PROPER(TRIM(SUBSTITUTE(Raw_Text_Fields!B73,CHAR(160)," "))) -> Karan Malhotra | F72: =PROPER(TRIM(SUBSTITUTE(Raw_Text_Fields!C73,CHAR(160)," "))) -> Corporate | G72: =PROPER(TRIM(SUBSTITUTE(Raw_Text_Fields!D73,CHAR(160)," "))) -> South | H72: =PROPER(TRIM(SUBSTITUTE(Raw_Text_Fields!E73,CHAR(160)," "))) -> Andhra Pradesh | I72: =PROPER(TRIM(SUBSTITUTE(Raw_Text_Fields!F73,CHAR(160)," "))) -> Vijayawada | J72: =PROPER(TRIM(SUBSTITUTE(Raw_Text_Fields!G73,CHAR(160)," "))) -> Technology | K72: =PROPER(TRIM(SUBSTITUTE(Raw_Text_Fields!H73,CHAR(160)," "))) -> Phones | L72: Max Phones 661 | M72: =PROPER(TRIM(SUBSTITUTE(Raw_Text_Fields!I73,CHAR(160)," "))) -> First Class | N72: 2 | O72: 905.87 | P72: 0.15 | Q72: 1539.98 | R72: 1070.2 | S72: 469.78 | T72: =PROPER(TRIM(SUBSTITUTE(Raw_Text_Fields!J73,CHAR(160)," "))) -> Paid | U72: =PROPER(TRIM(SUBSTITUTE(Raw_Text_Fields!K73,CHAR(160)," "))) -> Completed | V72: =IF(OR(P72<0,P72>0.5),0,P72) -> 0.15 | W72: =N72*O72*(1-V72) -> 1539.979 | X72: =W72-R72 -> 469.779 | Y72: =IFERROR(X72/W72,0) -> 0.30505546 | Z72: =C72-B72 -> 5 | AA72: =IF(B72="","",TEXT(B72,"mmm")) -> Aug | AB72: =IF(B72="","",YEAR(B72)) -> 2025 | AD72: =IF(LEFT(AC72&IF(B72="","; Missing Order Date","")&IF(C72="","; Missing Ship Date","")&IF(P72<0,"; Invalid Discount (Negative)","")&IF(P72>0.5,"; Invalid Discount (Too High)","")&IF(Z72<0,"; Invalid Shipping Record (Ship Before Order)","")&IF(ABS(Q72-W72)>1,"; Sales Mismatch","")&IF(ABS(S72-X72)>1,"; Profit Mismatch","")&IF(COUNTIF($A$2:$A$913,A72)>1,"; Duplicate Order ID Conflict",""),2)="; ",MID(AC72&IF(B72="","; Missing Order Date","")&IF(C72="","; Missing Ship Date","")&IF(P72<0,"; Invalid Discount (Negative)","")&IF(P72>0.5,"; Invalid Discount (Too High)","")&IF(Z72<0,"; Invalid Shipping Record (Ship Before Order)","")&IF(ABS(Q72-W72)>1,"; Sales Mismatch","")&IF(ABS(S72-X72)>1,"; Profit Mismatch","")&IF(COUNTIF($A$2:$A$913,A72)>1,"; Duplicate Order ID Conflict",""),3,500),AC72&IF(B72="","; Missing Order Date","")&IF(C72="","; Missing Ship Date","")&IF(P72<0,"; Invalid Discount (Negative)","")&IF(P72>0.5,"; Invalid Discount (Too High)","")&IF(Z72<0,"; Invalid Shipping Record (Ship Before Order)","")&IF(ABS(Q72-W72)>1,"; Sales Mismatch","")&IF(ABS(S72-X72)>1,"; Profit Mismatch","")&IF(COUNTIF($A$2:$A$913,A72)>1,"; Duplicate Order ID Conflict","")) | AE72: =IF(OR(ISNUMBER(SEARCH("Invalid Discount",AD72)),ISNUMBER(SEARCH("Invalid Shipping Record",AD72)),ISNUMBER(SEARCH("Sales Mismatch",AD72)),ISNUMBER(SEARCH("Profit Mismatch",AD72)),ISNUMBER(SEARCH("Duplicate Order ID Conflict",AD72)),ISNUMBER(SEARCH("Missing Order Date",AD72)),ISNUMBER(SEARCH("Missing Ship Date",AD72))),"Invalid",IF(AD72<>"","Warning","Clean")) -> Clean
... A99: ORD-2025-10098 | B99: 45877 | C99: 45880 | D99: CUST-8111 | E99: =PROPER(TRIM(SUBSTITUTE(Raw_Text_Fields!B100,CHAR(160)," "))) -> Diya Patel | F99: =PROPER(TRIM(SUBSTITUTE(Raw_Text_Fields!C100,CHAR(160)," "))) -> Small Business | G99: =PROPER(TRIM(SUBSTITUTE(Raw_Text_Fields!D100,CHAR(160)," "))) -> West | H99: =PROPER(TRIM(SUBSTITUTE(Raw_Text_Fields!E100,CHAR(160)," "))) -> Gujarat | I99: =PROPER(TRIM(SUBSTITUTE(Raw_Text_Fields!F100,CHAR(160)," "))) -> Ahmedabad | J99: =PROPER(TRIM(SUBSTITUTE(Raw_Text_Fields!G100,CHAR(160)," "))) -> Office Supplies | K99: =PROPER(TRIM(SUBSTITUTE(Raw_Text_Fields!H100,CHAR(160)," "))) -> Storage | L99: Basic Storage 656 | M99: =PROPER(TRIM(SUBSTITUTE(Raw_Text_Fields!I100,CHAR(160)," "))) -> Same Day | N99: 5 | O99: 3602.36 | P99: 0.2 | Q99: 14409.44 | R99: 8809.97 | S99: 5599.47 | T99: =PROPER(TRIM(SUBSTITUTE(Raw_Text_Fields!J100,CHAR(160)," "))) -> Pending | U99: =PROPER(TRIM(SUBSTITUTE(Raw_Text_Fields!K100,CHAR(160)," "))) -> Returned | V99: =IF(OR(P99<0,P99>0.5),0,P99) -> 0.2 | W99: =N99*O99*(1-V99) -> 14409.44 | X99: =W99-R99 -> 5599.47 | Y99: =IFERROR(X99/W99,0) -> 0.38859734 | Z99: =C99-B99 -> 3 | AA99: =IF(B99="","",TEXT(B99,"mmm")) -> Aug | AB99: =IF(B99="","",YEAR(B99)) -> 2025 | AD99: =IF(LEFT(AC99&IF(B99="","; Missing Order Date","")&IF(C99="","; Missing Ship Date","")&IF(P99<0,"; Invalid Discount (Negative)","")&IF(P99>0.5,"; Invalid Discount (Too High)","")&IF(Z99<0,"; Invalid Shipping Record (Ship Before Order)","")&IF(ABS(Q99-W99)>1,"; Sales Mismatch","")&IF(ABS(S99-X99)>1,"; Profit Mismatch","")&IF(COUNTIF($A$2:$A$913,A99)>1,"; Duplicate Order ID Conflict",""),2)="; ",MID(AC99&IF(B99="","; Missing Order Date","")&IF(C99="","; Missing Ship Date","")&IF(P99<0,"; Invalid Discount (Negative)","")&IF(P99>0.5,"; Invalid Discount (Too High)","")&IF(Z99<0,"; Invalid Shipping Record (Ship Before Order)","")&IF(ABS(Q99-W99)>1,"; Sales Mismatch","")&IF(ABS(S99-X99)>1,"; Profit Mismatch","")&IF(COUNTIF($A$2:$A$913,A99)>1,"; Duplicate Order ID Conflict",""),3,500),AC99&IF(B99="","; Missing Order Date","")&IF(C99="","; Missing Ship Date","")&IF(P99<0,"; Invalid Discount (Negative)","")&IF(P99>0.5,"; Invalid Discount (Too High)","")&IF(Z99<0,"; Invalid Shipping Record (Ship Before Order)","")&IF(ABS(Q99-W99)>1,"; Sales Mismatch","")&IF(ABS(S99-X99)>1,"; Profit Mismatch","")&IF(COUNTIF($A$2:$A$913,A99)>1,"; Duplicate Order ID Conflict","")) | AE99: =IF(OR(ISNUMBER(SEARCH("Invalid Discount",AD99)),ISNUMBER(SEARCH("Invalid Shipping Record",AD99)),ISNUMBER(SEARCH("Sales Mismatch",AD99)),ISNUMBER(SEARCH("Profit Mismatch",AD99)),ISNUMBER(SEARCH("Duplicate Order ID Conflict",AD99)),ISNUMBER(SEARCH("Missing Order Date",AD99)),ISNUMBER(SEARCH("Missing Ship Date",AD99))),"Invalid",IF(AD99<>"","Warning","Clean")) -> Clean
A100: ORD-2024-10099 | B100: 45317 | C100: 45323 | D100: CUST-5434 | E100: =PROPER(TRIM(SUBSTITUTE(Raw_Text_Fields!B101,CHAR(160)," "))) -> Rohan Mehta | F100: =PROPER(TRIM(SUBSTITUTE(Raw_Text_Fields!C101,CHAR(160)," "))) -> Home Office | G100: =PROPER(TRIM(SUBSTITUTE(Raw_Text_Fields!D101,CHAR(160)," "))) -> South | H100: =PROPER(TRIM(SUBSTITUTE(Raw_Text_Fields!E101,CHAR(160)," "))) -> Kerala | I100: =PROPER(TRIM(SUBSTITUTE(Raw_Text_Fields!F101,CHAR(160)," "))) -> Kochi | J100: =PROPER(TRIM(SUBSTITUTE(Raw_Text_Fields!G101,CHAR(160)," "))) -> Technology | K100: =PROPER(TRIM(SUBSTITUTE(Raw_Text_Fields!H101,CHAR(160)," "))) -> Copiers | L100: Elite Copiers 785 | M100: =PROPER(TRIM(SUBSTITUTE(Raw_Text_Fields!I101,CHAR(160)," "))) -> Unknown | N100: 8 | O100: 2108.93 | P100: 0.1 | Q100: 15184.3 | R100: 11270.74 | S100: 3913.56 | T100: =PROPER(TRIM(SUBSTITUTE(Raw_Text_Fields!J101,CHAR(160)," "))) -> Paid | U100: =PROPER(TRIM(SUBSTITUTE(Raw_Text_Fields!K101,CHAR(160)," "))) -> Completed | V100: =IF(OR(P100<0,P100>0.5),0,P100) -> 0.1 | W100: =N100*O100*(1-V100) -> 15184.296 | X100: =W100-R100 -> 3913.556 | Y100: =IFERROR(X100/W100,0) -> 0.25773707 | Z100: =C100-B100 -> 6 | AA100: =IF(B100="","",TEXT(B100,"mmm")) -> Jan | AB100: =IF(B100="","",YEAR(B100)) -> 2024 | AC100: Missing Ship Mode (filled Unknown) | AD100: =IF(LEFT(AC100&IF(B100="","; Missing Order Date","")&IF(C100="","; Missing Ship Date","")&IF(P100<0,"; Invalid Discount (Negative)","")&IF(P100>0.5,"; Invalid Discount (Too High)","")&IF(Z100<0,"; Invalid Shipping Record (Ship Before Order)","")&IF(ABS(Q100-W100)>1,"; Sales Mismatch","")&IF(ABS(S100-X100)>1,"; Profit Mismatch","")&IF(COUNTIF($A$2:$A$913,A100)>1,"; Duplicate Order ID Conflict",""),2)="; ",MID(AC100&IF(B100="","; Missing Order Date","")&IF(C100="","; Missing Ship Date","")&IF(P100<0,"; Invalid Discount (Negative)","")&IF(P100>0.5,"; Invalid Discount (Too High)","")&IF(Z100<0,"; Invalid Shipping Record (Ship Before Order)","")&IF(ABS(Q100-W100)>1,"; Sales Mismatch","")&IF(ABS(S100-X100)>1,"; Profit Mismatch","")&IF(COUNTIF($A$2:$A$913,A100)>1,"; Duplicate Order ID Conflict",""),3,500),AC100&IF(B100="","; Missing Order Date","")&IF(C100="","; Missing Ship Date","")&IF(P100<0,"; Invalid Discount (Negative)","")&IF(P100>0.5,"; Invalid Discount (Too High)","")&IF(Z100<0,"; Invalid Shipping Record (Ship Before Order)","")&IF(ABS(Q100-W100)>1,"; Sales Mismatch","")&IF(ABS(S100-X100)>1,"; Profit Mismatch","")&IF(COUNTIF($A$2:$A$913,A100)>1,"; Duplicate Order ID Conflict","")) -> Missing Ship Mode (filled Unknown) | AE100: =IF(OR(ISNUMBER(SEARCH("Invalid Discount",AD100)),ISNUMBER(SEARCH("Invalid Shipping Record",AD100)),ISNUMBER(SEARCH("Sales Mismatch",AD100)),ISNUMBER(SEARCH("Profit Mismatch",AD100)),ISNUMBER(SEARCH("Duplicate Order ID Conflict",AD100)),ISNUMBER(SEARCH("Missing Order Date",AD100)),ISNUMBER(SEARCH("Missing Ship Date",AD100))),"Invalid",IF(AD100<>"","Warning","Clean")) -> Warning
A101: ORD-2025-10100 | B101: 45668 | C101: 45668 | D101: CUST-3865 | E101: =PROPER(TRIM(SUBSTITUTE(Raw_Text_Fields!B102,CHAR(160)," "))) -> Aditi Sen | F101: =PROPER(TRIM(SUBSTITUTE(Raw_Text_Fields!C102,CHAR(160)," "))) -> Small Business | G101: =PROPER(TRIM(SUBSTITUTE(Raw_Text_Fields!D102,CHAR(160)," "))) -> West | H101: =PROPER(TRIM(SUBSTITUTE(Raw_Text_Fields!E102,CHAR(160)," "))) -> Rajasthan | I101: =PROPER(TRIM(SUBSTITUTE(Raw_Text_Fields!F102,CHAR(160)," "))) -> Udaipur | J101: =PROPER(TRIM(SUBSTITUTE(Raw_Text_Fields!G102,CHAR(160)," "))) -> Technology | K101: =PROPER(TRIM(SUBSTITUTE(Raw_Text_Fields!H102,CHAR(160)," "))) -> Accessories | L101: Smart Accessories 542 | M101: =PROPER(TRIM(SUBSTITUTE(Raw_Text_Fields!I102,CHAR(160)," "))) -> Same Day | N101: 3 | O101: 2165.29 | P101: 0 | Q101: 6495.87 | R101: 4700.89 | S101: 1794.98 | T101: =PROPER(TRIM(SUBSTITUTE(Raw_Text_Fields!J102,CHAR(160)," "))) -> Paid | U101: =PROPER(TRIM(SUBSTITUTE(Raw_Text_Fields!K102,CHAR(160)," "))) -> Completed | V101: =IF(OR(P101<0,P101>0.5),0,P101) -> 0 | W101: =N101*O101*(1-V101) -> 6495.87 | X101: =W101-R101 -> 1794.98 | Y101: =IFERROR(X101/W101,0) -> 0.27632634 | Z101: =C101-B101 -> 0 | AA101: =IF(B101="","",TEXT(B101,"mmm")) -> Jan | AB101: =IF(B101="","",YEAR(B101)) -> 2025 | AD101: =IF(LEFT(AC101&IF(B101="","; Missing Order Date","")&IF(C101="","; Missing Ship Date","")&IF(P101<0,"; Invalid Discount (Negative)","")&IF(P101>0.5,"; Invalid Discount (Too High)","")&IF(Z101<0,"; Invalid Shipping Record (Ship Before Order)","")&IF(ABS(Q101-W101)>1,"; Sales Mismatch","")&IF(ABS(S101-X101)>1,"; Profit Mismatch","")&IF(COUNTIF($A$2:$A$913,A101)>1,"; Duplicate Order ID Conflict",""),2)="; ",MID(AC101&IF(B101="","; Missing Order Date","")&IF(C101="","; Missing Ship Date","")&IF(P101<0,"; Invalid Discount (Negative)","")&IF(P101>0.5,"; Invalid Discount (Too High)","")&IF(Z101<0,"; Invalid Shipping Record (Ship Before Order)","")&IF(ABS(Q101-W101)>1,"; Sales Mismatch","")&IF(ABS(S101-X101)>1,"; Profit Mismatch","")&IF(COUNTIF($A$2:$A$913,A101)>1,"; Duplicate Order ID Conflict",""),3,500),AC101&IF(B101="","; Missing Order Date","")&IF(C101="","; Missing Ship Date","")&IF(P101<0,"; Invalid Discount (Negative)","")&IF(P101>0.5,"; Invalid Discount (Too High)","")&IF(Z101<0,"; Invalid Shipping Record (Ship Before Order)","")&IF(ABS(Q101-W101)>1,"; Sales Mismatch","")&IF(ABS(S101-X101)>1,"; Profit Mismatch","")&IF(COUNTIF($A$2:$A$913,A101)>1,"; Duplicate Order ID Conflict","")) | AE101: =IF(OR(ISNUMBER(SEARCH("Invalid Discount",AD101)),ISNUMBER(SEARCH("Invalid Shipping Record",AD101)),ISNUMBER(SEARCH("Sales Mismatch",AD101)),ISNUMBER(SEARCH("Profit Mismatch",AD101)),ISNUMBER(SEARCH("Duplicate Order ID Conflict",AD101)),ISNUMBER(SEARCH("Missing Order Date",AD101)),ISNUMBER(SEARCH("Missing Ship Date",AD101))),"Invalid",IF(AD101<>"","Warning","Clean")) -> Clean
A102: ORD-2025-10101 | B102: 45912 | C102: 45918 | D102: CUST-6015 | E102: =PROPER(TRIM(SUBSTITUTE(Raw_Text_Fields!B103,CHAR(160)," "))) -> Aarav Sharma | F102: =PROPER(TRIM(SUBSTITUTE(Raw_Text_Fields!C103,CHAR(160)," "))) -> Home Office | G102: =PROPER(TRIM(SUBSTITUTE(Raw_Text_Fields!D103,CHAR(160)," "))) -> South | H102: =PROPER(TRIM(SUBSTITUTE(Raw_Text_Fields!E103,CHAR(160)," "))) -> Kerala | I102: =PROPER(TRIM(SUBSTITUTE(Raw_Text_Fields!F103,CHAR(160)," "))) -> Kochi | J102: =PROPER(TRIM(SUBSTITUTE(Raw_Text_Fields!G103,CHAR(160)," "))) -> Office Supplies | K102: =PROPER(TRIM(SUBSTITUTE(Raw_Text_Fields!H103,CHAR(160)," "))) -> Storage | L102: Eco Storage 936 | M102: =PROPER(TRIM(SUBSTITUTE(Raw_Text_Fields!I103,CHAR(160)," "))) -> Standard Class | N102: 6 | O102: 1673.8 | P102: 0.05 | Q102: 9540.66 | R102: 5561.49 | S102: 3979.17 | T102: =PROPER(TRIM(SUBSTITUTE(Raw_Text_Fields!J103,CHAR(160)," "))) -> Paid | U102: =PROPER(TRIM(SUBSTITUTE(Raw_Text_Fields!K103,CHAR(160)," "))) -> Completed | V102: =IF(OR(P102<0,P102>0.5),0,P102) -> 0.05 | W102: =N102*O102*(1-V102) -> 9540.66 | X102: =W102-R102 -> 3979.17 | Y102: =IFERROR(X102/W102,0) -> 0.41707492 | Z102: =C102-B102 -> 6 | AA102: =IF(B102="","",TEXT(B102,"mmm")) -> Sep | AB102: =IF(B102="","",YEAR(B102)) -> 2025 | AD102: =IF(LEFT(AC102&IF(B102="","; Missing Order Date","")&IF(C102="","; Missing Ship Date","")&IF(P102<0,"; Invalid Discount (Negative)","")&IF(P102>0.5,"; Invalid Discount (Too High)","")&IF(Z102<0,"; Invalid Shipping Record (Ship Before Order)","")&IF(ABS(Q102-W102)>1,"; Sales Mismatch","")&IF(ABS(S102-X102)>1,"; Profit Mismatch","")&IF(COUNTIF($A$2:$A$913,A102)>1,"; Duplicate Order ID Conflict",""),2)="; ",MID(AC102&IF(B102="","; Missing Order Date","")&IF(C102="","; Missing Ship Date","")&IF(P102<0,"; Invalid Discount (Negative)","")&IF(P102>0.5,"; Invalid Discount (Too High)","")&IF(Z102<0,"; Invalid Shipping Record (Ship Before Order)","")&IF(ABS(Q102-W102)>1,"; Sales Mismatch","")&IF(ABS(S102-X102)>1,"; Profit Mismatch","")&IF(COUNTIF($A$2:$A$913,A102)>1,"; Duplicate Order ID Conflict",""),3,500),AC102&IF(B102="","; Missing Order Date","")&IF(C102="","; Missing Ship Date","")&IF(P102<0,"; Invalid Discount (Negative)","")&IF(P102>0.5,"; Invalid Discount (Too High)","")&IF(Z102<0,"; Invalid Shipping Record (Ship Before Order)","")&IF(ABS(Q102-W102)>1,"; Sales Mismatch","")&IF(ABS(S102-X102)>1,"; Profit Mismatch","")&IF(COUNTIF($A$2:$A$913,A102)>1,"; Duplicate Order ID Conflict","")) | AE102: =IF(OR(ISNUMBER(SEARCH("Invalid Discount",AD102)),ISNUMBER(SEARCH("Invalid Shipping Record",AD102)),ISNUMBER(SEARCH("Sales Mismatch",AD102)),ISNUMBER(SEARCH("Profit Mismatch",AD102)),ISNUMBER(SEARCH("Duplicate Order ID Conflict",AD102)),ISNUMBER(SEARCH("Missing Order Date",AD102)),ISNUMBER(SEARCH("Missing Ship Date",AD102))),"Invalid",IF(AD102<>"","Warning","Clean")) -> Clean
A103: ORD-2024-10102 | B103: 45465 | C103: 45469 | D103: CUST-7909 | E103: =PROPER(TRIM(SUBSTITUTE(Raw_Text_Fields!B104,CHAR(160)," "))) -> Rohan Mehta | F103: =PROPER(TRIM(SUBSTITUTE(Raw_Text_Fields!C104,CHAR(160)," "))) -> Home Office | G103: =PROPER(TRIM(SUBSTITUTE(Raw_Text_Fields!D104,CHAR(160)," "))) -> East | H103: =PROPER(TRIM(SUBSTITUTE(Raw_Text_Fields!E104,CHAR(160)," "))) -> Bihar | I103: =PROPER(TRIM(SUBSTITUTE(Raw_Text_Fields!F104,CHAR(160)," "))) -> Patna | J103: =PROPER(TRIM(SUBSTITUTE(Raw_Text_Fields!G104,CHAR(160)," "))) -> Furniture | K103: =PROPER(TRIM(SUBSTITUTE(Raw_Text_Fields!H104,CHAR(160)," "))) -> Furnishings | L103: Classic Furnishings 682 | M103: =PROPER(TRIM(SUBSTITUTE(Raw_Text_Fields!I104,CHAR(160)," "))) -> First Class | N103: 5 | O103: 4396.52 | P103: 0.25 | Q103: 16486.95 | R103: 12054.14 | S103: 4432.81 | T103: =PROPER(TRIM(SUBSTITUTE(Raw_Text_Fields!J104,CHAR(160)," "))) -> Paid | U103: =PROPER(TRIM(SUBSTITUTE(Raw_Text_Fields!K104,CHAR(160)," "))) -> Completed | V103: =IF(OR(P103<0,P103>0.5),0,P103) -> 0.25 | W103: =N103*O103*(1-V103) -> 16486.95 | X103: =W103-R103 -> 4432.81 | Y103: =IFERROR(X103/W103,0) -> 0.2688678 | Z103: =C103-B103 -> 4 | AA103: =IF(B103="","",TEXT(B103,"mmm")) -> Jun | AB103: =IF(B103="","",YEAR(B103)) -> 2024 | AD103: =IF(LEFT(AC103&IF(B103="","; Missing Order Date","")&IF(C103="","; Missing Ship Date","")&IF(P103<0,"; Invalid Discount (Negative)","")&IF(P103>0.5,"; Invalid Discount (Too High)","")&IF(Z103<0,"; Invalid Shipping Record (Ship Before Order)","")&IF(ABS(Q103-W103)>1,"; Sales Mismatch","")&IF(ABS(S103-X103)>1,"; Profit Mismatch","")&IF(COUNTIF($A$2:$A$913,A103)>1,"; Duplicate Order ID Conflict",""),2)="; ",MID(AC103&IF(B103="","; Missing Order Date","")&IF(C103="","; Missing Ship Date","")&IF(P103<0,"; Invalid Discount (Negative)","")&IF(P103>0.5,"; Invalid Discount (Too High)","")&IF(Z103<0,"; Invalid Shipping Record (Ship Before Order)","")&IF(ABS(Q103-W103)>1,"; Sales Mismatch","")&IF(ABS(S103-X103)>1,"; Profit Mismatch","")&IF(COUNTIF($A$2:$A$913,A103)>1,"; Duplicate Order ID Conflict",""),3,500),AC103&IF(B103="","; Missing Order Date","")&IF(C103="","; Missing Ship Date","")&IF(P103<0,"; Invalid Discount (Negative)","")&IF(P103>0.5,"; Invalid Discount (Too High)","")&IF(Z103<0,"; Invalid Shipping Record (Ship Before Order)","")&IF(ABS(Q103-W103)>1,"; Sales Mismatch","")&IF(ABS(S103-X103)>1,"; Profit Mismatch","")&IF(COUNTIF($A$2:$A$913,A103)>1,"; Duplicate Order ID Conflict","")) | AE103: =IF(OR(ISNUMBER(SEARCH("Invalid Discount",AD103)),ISNUMBER(SEARCH("Invalid Shipping Record",AD103)),ISNUMBER(SEARCH("Sales Mismatch",AD103)),ISNUMBER(SEARCH("Profit Mismatch",AD103)),ISNUMBER(SEARCH("Duplicate Order ID Conflict",AD103)),ISNUMBER(SEARCH("Missing Order Date",AD103)),ISNUMBER(SEARCH("Missing Ship Date",AD103))),"Invalid",IF(AD103<>"","Warning","Clean")) -> Clean
A104: ORD-2025-10103 | B104: 45850 | C104: 45854 | D104: CUST-9603 | E104: =PROPER(TRIM(SUBSTITUTE(Raw_Text_Fields!B105,CHAR(160)," "))) -> Vikram Iyer | F104: =PROPER(TRIM(SUBSTITUTE(Raw_Text_Fields!C105,CHAR(160)," "))) -> Consumer | G104: =PROPER(TRIM(SUBSTITUTE(Raw_Text_Fields!D105,CHAR(160)," "))) -> South | H104: =PROPER(TRIM(SUBSTITUTE(Raw_Text_Fields!E105,CHAR(160)," "))) -> Karnataka | I104: =PROPER(TRIM(SUBSTITUTE(Raw_Text_Fields!F105,CHAR(160)," "))) -> Bengaluru | J104: =PROPER(TRIM(SUBSTITUTE(Raw_Text_Fields!G105,CHAR(160)," "))) -> Furniture | K104: =PROPER(TRIM(SUBSTITUTE(Raw_Text_Fields!H105,CHAR(160)," "))) -> Chairs | L104: Classic Chairs 604 | M104: =PROPER(TRIM(SUBSTITUTE(Raw_Text_Fields!I105,CHAR(160)," "))) -> First Class | N104: 4 | O104: 2865.71 | P104: 0 | Q104: 11462.84 | R104: 8979.78 | S104: 2483.06 | T104: =PROPER(TRIM(SUBSTITUTE(Raw_Text_Fields!J105,CHAR(160)," "))) -> Refunded | U104: =PROPER(TRIM(SUBSTITUTE(Raw_Text_Fields!K105,CHAR(160)," "))) -> Cancelled | V104: =IF(OR(P104<0,P104>0.5),0,P104) -> 0 | W104: =N104*O104*(1-V104) -> 11462.84 | X104: =W104-R104 -> 2483.06 | Y104: =IFERROR(X104/W104,0) -> 0.21661822 | Z104: =C104-B104 -> 4 | AA104: =IF(B104="","",TEXT(B104,"mmm")) -> Jul | AB104: =IF(B104="","",YEAR(B104)) -> 2025 | AD104: =IF(LEFT(AC104&IF(B104="","; Missing Order Date","")&IF(C104="","; Missing Ship Date","")&IF(P104<0,"; Invalid Discount (Negative)","")&IF(P104>0.5,"; Invalid Discount (Too High)","")&IF(Z104<0,"; Invalid Shipping Record (Ship Before Order)","")&IF(ABS(Q104-W104)>1,"; Sales Mismatch","")&IF(ABS(S104-X104)>1,"; Profit Mismatch","")&IF(COUNTIF($A$2:$A$913,A104)>1,"; Duplicate Order ID Conflict",""),2)="; ",MID(AC104&IF(B104="","; Missing Order Date","")&IF(C104="","; Missing Ship Date","")&IF(P104<0,"; Invalid Discount (Negative)","")&IF(P104>0.5,"; Invalid Discount (Too High)","")&IF(Z104<0,"; Invalid Shipping Record (Ship Before Order)","")&IF(ABS(Q104-W104)>1,"; Sales Mismatch","")&IF(ABS(S104-X104)>1,"; Profit Mismatch","")&IF(COUNTIF($A$2:$A$913,A104)>1,"; Duplicate Order ID Conflict",""),3,500),AC104&IF(B104="","; Missing Order Date","")&IF(C104="","; Missing Ship Date","")&IF(P104<0,"; Invalid Discount (Negative)","")&IF(P104>0.5,"; Invalid Discount (Too High)","")&IF(Z104<0,"; Invalid Shipping Record (Ship Before Order)","")&IF(ABS(Q104-W104)>1,"; Sales Mismatch","")&IF(ABS(S104-X104)>1,"; Profit Mismatch","")&IF(COUNTIF($A$2:$A$913,A104)>1,"; Duplicate Order ID Conflict","")) | AE104: =IF(OR(ISNUMBER(SEARCH("Invalid Discount",AD104)),ISNUMBER(SEARCH("Invalid Shipping Record",AD104)),ISNUMBER(SEARCH("Sales Mismatch",AD104)),ISNUMBER(SEARCH("Profit Mismatch",AD104)),ISNUMBER(SEARCH("Duplicate Order ID Conflict",AD104)),ISNUMBER(SEARCH("Missing Order Date",AD104)),ISNUMBER(SEARCH("Missing Ship Date",AD104))),"Invalid",IF(AD104<>"","Warning","Clean")) -> Clean
A105: ORD-2025-10104 | B105: 45779 | C105: 45787 | D105: CUST-6263 | E105: =PROPER(TRIM(SUBSTITUTE(Raw_Text_Fields!B106,CHAR(160)," "))) -> Kabir Singh | F105: =PROPER(TRIM(SUBSTITUTE(Raw_Text_Fields!C106,CHAR(160)," "))) -> Corporate | G105: =PROPER(TRIM(SUBSTITUTE(Raw_Text_Fields!D106,CHAR(160)," "))) -> West | H105: =PROPER(TRIM(SUBSTITUTE(Raw_Text_Fields!E106,CHAR(160)," "))) -> Maharashtra | I105: =PROPER(TRIM(SUBSTITUTE(Raw_Text_Fields!F106,CHAR(160)," "))) -> Mumbai | J105: =PROPER(TRIM(SUBSTITUTE(Raw_Text_Fields!G106,CHAR(160)," "))) -> Furniture | K105: =PROPER(TRIM(SUBSTITUTE(Raw_Text_Fields!H106,CHAR(160)," "))) -> Tables | L105: Prime Tables 377 | M105: =PROPER(TRIM(SUBSTITUTE(Raw_Text_Fields!I106,CHAR(160)," "))) -> First Class | N105: 4 | O105: 2440.34 | P105: 0.2 | Q105: 7809.09 | R105: 6657.75 | S105: 1151.34 | T105: =PROPER(TRIM(SUBSTITUTE(Raw_Text_Fields!J106,CHAR(160)," "))) -> Paid | U105: =PROPER(TRIM(SUBSTITUTE(Raw_Text_Fields!K106,CHAR(160)," "))) -> Completed | V105: =IF(OR(P105<0,P105>0.5),0,P105) -> 0.2 | W105: =N105*O105*(1-V105) -> 7809.088 | X105: =W105-R105 -> 1151.338 | Y105: =IFERROR(X105/W105,0) -> 0.14743565 | Z105: =C105-B105 -> 8 | AA105: =IF(B105="","",TEXT(B105,"mmm")) -> May | AB105: =IF(B105="","",YEAR(B105)) -> 2025 | AD105: =IF(LEFT(AC105&IF(B105="","; Missing Order Date","")&IF(C105="","; Missing Ship Date","")&IF(P105<0,"; Invalid Discount (Negative)","")&IF(P105>0.5,"; Invalid Discount (Too High)","")&IF(Z105<0,"; Invalid Shipping Record (Ship Before Order)","")&IF(ABS(Q105-W105)>1,"; Sales Mismatch","")&IF(ABS(S105-X105)>1,"; Profit Mismatch","")&IF(COUNTIF($A$2:$A$913,A105)>1,"; Duplicate Order ID Conflict",""),2)="; ",MID(AC105&IF(B105="","; Missing Order Date","")&IF(C105="","; Missing Ship Date","")&IF(P105<0,"; Invalid Discount (Negative)","")&IF(P105>0.5,"; Invalid Discount (Too High)","")&IF(Z105<0,"; Invalid Shipping Record (Ship Before Order)","")&IF(ABS(Q105-W105)>1,"; Sales Mismatch","")&IF(ABS(S105-X105)>1,"; Profit Mismatch","")&IF(COUNTIF($A$2:$A$913,A105)>1,"; Duplicate Order ID Conflict",""),3,500),AC105&IF(B105="","; Missing Order Date","")&IF(C105="","; Missing Ship Date","")&IF(P105<0,"; Invalid Discount (Negative)","")&IF(P105>0.5,"; Invalid Discount (Too High)","")&IF(Z105<0,"; Invalid Shipping Record (Ship Before Order)","")&IF(ABS(Q105-W105)>1,"; Sales Mismatch","")&IF(ABS(S105-X105)>1,"; Profit Mismatch","")&IF(COUNTIF($A$2:$A$913,A105)>1,"; Duplicate Order ID Conflict","")) | AE105: =IF(OR(ISNUMBER(SEARCH("Invalid Discount",AD105)),ISNUMBER(SEARCH("Invalid Shipping Record",AD105)),ISNUMBER(SEARCH("Sales Mismatch",AD105)),ISNUMBER(SEARCH("Profit Mismatch",AD105)),ISNUMBER(SEARCH("Duplicate Order ID Conflict",AD105)),ISNUMBER(SEARCH("Missing Order Date",AD105)),ISNUMBER(SEARCH("Missing Ship Date",AD105))),"Invalid",IF(AD105<>"","Warning","Clean")) -> Clean
A106: ORD-2025-10105 | B106: 45689 | C106: 45696 | D106: CUST-1576 | E106: =PROPER(TRIM(SUBSTITUTE(Raw_Text_Fields!B107,CHAR(160)," "))) -> Ananya Rao | F106: =PROPER(TRIM(SUBSTITUTE(Raw_Text_Fields!C107,CHAR(160)," "))) -> Consumer | G106: =PROPER(TRIM(SUBSTITUTE(Raw_Text_Fields!D107,CHAR(160)," "))) -> South | H106: =PROPER(TRIM(SUBSTITUTE(Raw_Text_Fields!E107,CHAR(160)," "))) -> Karnataka | I106: =PROPER(TRIM(SUBSTITUTE(Raw_Text_Fields!F107,CHAR(160)," "))) -> Bengaluru | J106: =PROPER(TRIM(SUBSTITUTE(Raw_Text_Fields!G107,CHAR(160)," "))) -> Office Supplies | K106: =PROPER(TRIM(SUBSTITUTE(Raw_Text_Fields!H107,CHAR(160)," "))) -> Labels | L106: Prime Labels 807 | M106: =PROPER(TRIM(SUBSTITUTE(Raw_Text_Fields!I107,CHAR(160)," "))) -> Same Day | N106: 5 | O106: 2112.54 | P106: 0.25 | Q106: 8260.46 | R106: 5619.95 | S106: 2302.08 | T106: =PROPER(TRIM(SUBSTITUTE(Raw_Text_Fields!J107,CHAR(160)," "))) -> Paid | U106: =PROPER(TRIM(SUBSTITUTE(Raw_Text_Fields!K107,CHAR(160)," "))) -> Cancelled | V106: =IF(OR(P106<0,P106>0.5),0,P106) -> 0.25 | W106: =N106*O106*(1-V106) -> 7922.025 | X106: =W106-R106 -> 2302.075 | Y106: =IFERROR(X106/W106,0) -> 0.29059174 | Z106: =C106-B106 -> 7 | AA106: =IF(B106="","",TEXT(B106,"mmm")) -> Feb | AB106: =IF(B106="","",YEAR(B106)) -> 2025 | AD106: =IF(LEFT(AC106&IF(B106="","; Missing Order Date","")&IF(C106="","; Missing Ship Date","")&IF(P106<0,"; Invalid Discount (Negative)","")&IF(P106>0.5,"; Invalid Discount (Too High)","")&IF(Z106<0,"; Invalid Shipping Record (Ship Before Order)","")&IF(ABS(Q106-W106)>1,"; Sales Mismatch","")&IF(ABS(S106-X106)>1,"; Profit Mismatch","")&IF(COUNTIF($A$2:$A$913,A106)>1,"; Duplicate Order ID Conflict",""),2)="; ",MID(AC106&IF(B106="","; Missing Order Date","")&IF(C106="","; Missing Ship Date","")&IF(P106<0,"; Invalid Discount (Negative)","")&IF(P106>0.5,"; Invalid Discount (Too High)","")&IF(Z106<0,"; Invalid Shipping Record (Ship Before Order)","")&IF(ABS(Q106-W106)>1,"; Sales Mismatch","")&IF(ABS(S106-X106)>1,"; Profit Mismatch","")&IF(COUNTIF($A$2:$A$913,A106)>1,"; Duplicate Order ID Conflict",""),3,500),AC106&IF(B106="","; Missing Order Date","")&IF(C106="","; Missing Ship Date","")&IF(P106<0,"; Invalid Discount (Negative)","")&IF(P106>0.5,"; Invalid Discount (Too High)","")&IF(Z106<0,"; Invalid Shipping Record (Ship Before Order)","")&IF(ABS(Q106-W106)>1,"; Sales Mismatch","")&IF(ABS(S106-X106)>1,"; Profit Mismatch","")&IF(COUNTIF($A$2:$A$913,A106)>1,"; Duplicate Order ID Conflict","")) -> Sales Mismatch | AE106: =IF(OR(ISNUMBER(SEARCH("Invalid Discount",AD106)),ISNUMBER(SEARCH("Invalid Shipping Record",AD106)),ISNUMBER(SEARCH("Sales Mismatch",AD106)),ISNUMBER(SEARCH("Profit Mismatch",AD106)),ISNUMBER(SEARCH("Duplicate Order ID Conflict",AD106)),ISNUMBER(SEARCH("Missing Order Date",AD106)),ISNUMBER(SEARCH("Missing Ship Date",AD106))),"Invalid",IF(AD106<>"","Warning","Clean")) -> Invalid
A107: ORD-2024-10106 | B107: 45467 | C107: 45472 | D107: CUST-6540 | E107: =PROPER(TRIM(SUBSTITUTE(Raw_Text_Fields!B108,CHAR(160)," "))) -> Mira Das | F107: =PROPER(TRIM(SUBSTITUTE(Raw_Text_Fields!C108,CHAR(160)," "))) -> Home Office | G107: =PROPER(TRIM(SUBSTITUTE(Raw_Text_Fields!D108,CHAR(160)," "))) -> East | H107: =PROPER(TRIM(SUBSTITUTE(Raw_Text_Fields!E108,CHAR(160)," "))) -> West Bengal | I107: =PROPER(TRIM(SUBSTITUTE(Raw_Text_Fields!F108,CHAR(160)," "))) -> Kolkata | J107: =PROPER(TRIM(SUBSTITUTE(Raw_Text_Fields!G108,CHAR(160)," "))) -> Furniture | K107: =PROPER(TRIM(SUBSTITUTE(Raw_Text_Fields!H108,CHAR(160)," "))) -> Tables | L107: Eco Tables 575 | M107: =PROPER(TRIM(SUBSTITUTE(Raw_Text_Fields!I108,CHAR(160)," "))) -> Second Class | N107: 2 | O107: 685 | P107: 0.1 | Q107: 1233 | R107: 1006.9 | S107: 226.1 | T107: =PROPER(TRIM(SUBSTITUTE(Raw_Text_Fields!J108,CHAR(160)," "))) -> Paid | U107: =PROPER(TRIM(SUBSTITUTE(Raw_Text_Fields!K108,CHAR(160)," "))) -> Completed | V107: =IF(OR(P107<0,P107>0.5),0,P107) -> 0.1 | W107: =N107*O107*(1-V107) -> 1233 | X107: =W107-R107 -> 226.1 | Y107: =IFERROR(X107/W107,0) -> 0.18337388 | Z107: =C107-B107 -> 5 | AA107: =IF(B107="","",TEXT(B107,"mmm")) -> Jun | AB107: =IF(B107="","",YEAR(B107)) -> 2024 | AD107: =IF(LEFT(AC107&IF(B107="","; Missing Order Date","")&IF(C107="","; Missing Ship Date","")&IF(P107<0,"; Invalid Discount (Negative)","")&IF(P107>0.5,"; Invalid Discount (Too High)","")&IF(Z107<0,"; Invalid Shipping Record (Ship Before Order)","")&IF(ABS(Q107-W107)>1,"; Sales Mismatch","")&IF(ABS(S107-X107)>1,"; Profit Mismatch","")&IF(COUNTIF($A$2:$A$913,A107)>1,"; Duplicate Order ID Conflict",""),2)="; ",MID(AC107&IF(B107="","; Missing Order Date","")&IF(C107="","; Missing Ship Date","")&IF(P107<0,"; Invalid Discount (Negative)","")&IF(P107>0.5,"; Invalid Discount (Too High)","")&IF(Z107<0,"; Invalid Shipping Record (Ship Before Order)","")&IF(ABS(Q107-W107)>1,"; Sales Mismatch","")&IF(ABS(S107-X107)>1,"; Profit Mismatch","")&IF(COUNTIF($A$2:$A$913,A107)>1,"; Duplicate Order ID Conflict",""),3,500),AC107&IF(B107="","; Missing Order Date","")&IF(C107="","; Missing Ship Date","")&IF(P107<0,"; Invalid Discount (Negative)","")&IF(P107>0.5,"; Invalid Discount (Too High)","")&IF(Z107<0,"; Invalid Shipping Record (Ship Before Order)","")&IF(ABS(Q107-W107)>1,"; Sales Mismatch","")&IF(ABS(S107-X107)>1,"; Profit Mismatch","")&IF(COUNTIF($A$2:$A$913,A107)>1,"; Duplicate Order ID Conflict","")) | AE107: =IF(OR(ISNUMBER(SEARCH("Invalid Discount",AD107)),ISNUMBER(SEARCH("Invalid Shipping Record",AD107)),ISNUMBER(SEARCH("Sales Mismatch",AD107)),ISNUMBER(SEARCH("Profit Mismatch",AD107)),ISNUMBER(SEARCH("Duplicate Order ID Conflict",AD107)),ISNUMBER(SEARCH("Missing Order Date",AD107)),ISNUMBER(SEARCH("Missing Ship Date",AD107))),"Invalid",IF(AD107<>"","Warning","Clean")) -> Clean
A108: ORD-2024-10107 | B108: 45342 | C108: 45350 | D108: CUST-4008 | E108: =PROPER(TRIM(SUBSTITUTE(Raw_Text_Fields!B109,CHAR(160)," "))) -> Arjun Bose | F108: =PROPER(TRIM(SUBSTITUTE(Raw_Text_Fields!C109,CHAR(160)," "))) -> Home Office | G108: =PROPER(TRIM(SUBSTITUTE(Raw_Text_Fields!D109,CHAR(160)," "))) -> East | H108: =PROPER(TRIM(SUBSTITUTE(Raw_Text_Fields!E109,CHAR(160)," "))) -> West Bengal | I108: =PROPER(TRIM(SUBSTITUTE(Raw_Text_Fields!F109,CHAR(160)," "))) -> Kolkata | J108: =PROPER(TRIM(SUBSTITUTE(Raw_Text_Fields!G109,CHAR(160)," "))) -> Office Supplies | K108: =PROPER(TRIM(SUBSTITUTE(Raw_Text_Fields!H109,CHAR(160)," "))) -> Paper | L108: Eco Paper 918 | M108: =PROPER(TRIM(SUBSTITUTE(Raw_Text_Fields!I109,CHAR(160)," "))) -> Standard Class | N108: 2 | O108: 4004.04 | P108: 0 | Q108: 7207.27 | R108: 5709.39 | S108: 1497.88 | T108: =PROPER(TRIM(SUBSTITUTE(Raw_Text_Fields!J109,CHAR(160)," "))) -> Paid | U108: =PROPER(TRIM(SUBSTITUTE(Raw_Text_Fields!K109,CHAR(160)," "))) -> Cancelled | V108: =IF(OR(P108<0,P108>0.5),0,P108) -> 0 | W108: =N108*O108*(1-V108) -> 8008.08 | X108: =W108-R108 -> 2298.69 | Y108: =IFERROR(X108/W108,0) -> 0.28704633 | Z108: =C108-B108 -> 8 | AA108: =IF(B108="","",TEXT(B108,"mmm")) -> Feb | AB108: =IF(B108="","",YEAR(B108)) -> 2024 | AC108: Missing Discount (defaulted 0) | AD108: =IF(LEFT(AC108&IF(B108="","; Missing Order Date","")&IF(C108="","; Missing Ship Date","")&IF(P108<0,"; Invalid Discount (Negative)","")&IF(P108>0.5,"; Invalid Discount (Too High)","")&IF(Z108<0,"; Invalid Shipping Record (Ship Before Order)","")&IF(ABS(Q108-W108)>1,"; Sales Mismatch","")&IF(ABS(S108-X108)>1,"; Profit Mismatch","")&IF(COUNTIF($A$2:$A$913,A108)>1,"; Duplicate Order ID Conflict",""),2)="; ",MID(AC108&IF(B108="","; Missing Order Date","")&IF(C108="","; Missing Ship Date","")&IF(P108<0,"; Invalid Discount (Negative)","")&IF(P108>0.5,"; Invalid Discount (Too High)","")&IF(Z108<0,"; Invalid Shipping Record (Ship Before Order)","")&IF(ABS(Q108-W108)>1,"; Sales Mismatch","")&IF(ABS(S108-X108)>1,"; Profit Mismatch","")&IF(COUNTIF($A$2:$A$913,A108)>1,"; Duplicate Order ID Conflict",""),3,500),AC108&IF(B108="","; Missing Order Date","")&IF(C108="","; Missing Ship Date","")&IF(P108<0,"; Invalid Discount (Negative)","")&IF(P108>0.5,"; Invalid Discount (Too High)","")&IF(Z108<0,"; Invalid Shipping Record (Ship Before Order)","")&IF(ABS(Q108-W108)>1,"; Sales Mismatch","")&IF(ABS(S108-X108)>1,"; Profit Mismatch","")&IF(COUNTIF($A$2:$A$913,A108)>1,"; Duplicate Order ID Conflict","")) -> Missing Discount (defaulted 0); Sales Mismatch; Profit Mismatch | AE108: =IF(OR(ISNUMBER(SEARCH("Invalid Discount",AD108)),ISNUMBER(SEARCH("Invalid Shipping Record",AD108)),ISNUMBER(SEARCH("Sales Mismatch",AD108)),ISNUMBER(SEARCH("Profit Mismatch",AD108)),ISNUMBER(SEARCH("Duplicate Order ID Conflict",AD108)),ISNUMBER(SEARCH("Missing Order Date",AD108)),ISNUMBER(SEARCH("Missing Ship Date",AD108))),"Invalid",IF(AD108<>"","Warning","Clean")) -> Invalid
A109: ORD-2024-10108 | B109: 45594 | C109: 45600 | D109: CUST-6604 | E109: =PROPER(TRIM(SUBSTITUTE(Raw_Text_Fields!B110,CHAR(160)," "))) -> Rohan Mehta | F109: =PROPER(TRIM(SUBSTITUTE(Raw_Text_Fields!C110,CHAR(160)," "))) -> Home Office | G109: =PROPER(TRIM(SUBSTITUTE(Raw_Text_Fields!D110,CHAR(160)," "))) -> East | H109: =PROPER(TRIM(SUBSTITUTE(Raw_Text_Fields!E110,CHAR(160)," "))) -> West Bengal | I109: =PROPER(TRIM(SUBSTITUTE(Raw_Text_Fields!F110,CHAR(160)," "))) -> Kolkata | J109: =PROPER(TRIM(SUBSTITUTE(Raw_Text_Fields!G110,CHAR(160)," "))) -> Furniture | K109: =PROPER(TRIM(SUBSTITUTE(Raw_Text_Fields!H110,CHAR(160)," "))) -> Furnishings | L109: Prime Furnishings 952 | M109: =PROPER(TRIM(SUBSTITUTE(Raw_Text_Fields!I110,CHAR(160)," "))) -> First Class | N109: 3 | O109: 4302.89 | P109: 0.05 | Q109: 12263.24 | R109: 8925.57 | S109: 3337.67 | T109: =PROPER(TRIM(SUBSTITUTE(Raw_Text_Fields!J110,CHAR(160)," "))) -> Paid | U109: =PROPER(TRIM(SUBSTITUTE(Raw_Text_Fields!K110,CHAR(160)," "))) -> Completed | V109: =IF(OR(P109<0,P109>0.5),0,P109) -> 0.05 | W109: =N109*O109*(1-V109) -> 12263.237 | X109: =W109-R109 -> 3337.6665 | Y109: =IFERROR(X109/W109,0) -> 0.27216849 | Z109: =C109-B109 -> 6 | AA109: =IF(B109="","",TEXT(B109,"mmm")) -> Oct | AB109: =IF(B109="","",YEAR(B109)) -> 2024 | AD109: =IF(LEFT(AC109&IF(B109="","; Missing Order Date","")&IF(C109="","; Missing Ship Date","")&IF(P109<0,"; Invalid Discount (Negative)","")&IF(P109>0.5,"; Invalid Discount (Too High)","")&IF(Z109<0,"; Invalid Shipping Record (Ship Before Order)","")&IF(ABS(Q109-W109)>1,"; Sales Mismatch","")&IF(ABS(S109-X109)>1,"; Profit Mismatch","")&IF(COUNTIF($A$2:$A$913,A109)>1,"; Duplicate Order ID Conflict",""),2)="; ",MID(AC109&IF(B109="","; Missing Order Date","")&IF(C109="","; Missing Ship Date","")&IF(P109<0,"; Invalid Discount (Negative)","")&IF(P109>0.5,"; Invalid Discount (Too High)","")&IF(Z109<0,"; Invalid Shipping Record (Ship Before Order)","")&IF(ABS(Q109-W109)>1,"; Sales Mismatch","")&IF(ABS(S109-X109)>1,"; Profit Mismatch","")&IF(COUNTIF($A$2:$A$913,A109)>1,"; Duplicate Order ID Conflict",""),3,500),AC109&IF(B109="","; Missing Order Date","")&IF(C109="","; Missing Ship Date","")&IF(P109<0,"; Invalid Discount (Negative)","")&IF(P109>0.5,"; Invalid Discount (Too High)","")&IF(Z109<0,"; Invalid Shipping Record (Ship Before Order)","")&IF(ABS(Q109-W109)>1,"; Sales Mismatch","")&IF(ABS(S109-X109)>1,"; Profit Mismatch","")&IF(COUNTIF($A$2:$A$913,A109)>1,"; Duplicate Order ID Conflict","")) | AE109: =IF(OR(ISNUMBER(SEARCH("Invalid Discount",AD109)),ISNUMBER(SEARCH("Invalid Shipping Record",AD109)),ISNUMBER(SEARCH("Sales Mismatch",AD109)),ISNUMBER(SEARCH("Profit Mismatch",AD109)),ISNUMBER(SEARCH("Duplicate Order ID Conflict",AD109)),ISNUMBER(SEARCH("Missing Order Date",AD109)),ISNUMBER(SEARCH("Missing Ship Date",AD109))),"Invalid",IF(AD109<>"","Warning","Clean")) -> Clean
A110: ORD-2024-10109 | B110: 45519 | C110: 45527 | D110: CUST-4337 | E110: =PROPER(TRIM(SUBSTITUTE(Raw_Text_Fields!B111,CHAR(160)," "))) -> Aditi Sen | F110: =PROPER(TRIM(SUBSTITUTE(Raw_Text_Fields!C111,CHAR(160)," "))) -> Small Business | G110: =PROPER(TRIM(SUBSTITUTE(Raw_Text_Fields!D111,CHAR(160)," "))) -> East | H110: =PROPER(TRIM(SUBSTITUTE(Raw_Text_Fields!E111,CHAR(160)," "))) -> Odisha | I110: =PROPER(TRIM(SUBSTITUTE(Raw_Text_Fields!F111,CHAR(160)," "))) -> Bhubaneswar | J110: =PROPER(TRIM(SUBSTITUTE(Raw_Text_Fields!G111,CHAR(160)," "))) -> Furniture | K110: =PROPER(TRIM(SUBSTITUTE(Raw_Text_Fields!H111,CHAR(160)," "))) -> Bookcases | L110: Prime Bookcases 631 | M110: =PROPER(TRIM(SUBSTITUTE(Raw_Text_Fields!I111,CHAR(160)," "))) -> Same Day | N110: 2 | O110: 537.54 | P110: 0.25 | Q110: 806.31 | R110: 498.5 | S110: 307.81 | T110: =PROPER(TRIM(SUBSTITUTE(Raw_Text_Fields!J111,CHAR(160)," "))) -> Paid | U110: =PROPER(TRIM(SUBSTITUTE(Raw_Text_Fields!K111,CHAR(160)," "))) -> Completed | V110: =IF(OR(P110<0,P110>0.5),0,P110) -> 0.25 | W110: =N110*O110*(1-V110) -> 806.31 | X110: =W110-R110 -> 307.81 | Y110: =IFERROR(X110/W110,0) -> 0.38175144 | Z110: =C110-B110 -> 8 | AA110: =IF(B110="","",TEXT(B110,"mmm")) -> Aug | AB110: =IF(B110="","",YEAR(B110)) -> 2024 | AD110: =IF(LEFT(AC110&IF(B110="","; Missing Order Date","")&IF(C110="","; Missing Ship Date","")&IF(P110<0,"; Invalid Discount (Negative)","")&IF(P110>0.5,"; Invalid Discount (Too High)","")&IF(Z110<0,"; Invalid Shipping Record (Ship Before Order)","")&IF(ABS(Q110-W110)>1,"; Sales Mismatch","")&IF(ABS(S110-X110)>1,"; Profit Mismatch","")&IF(COUNTIF($A$2:$A$913,A110)>1,"; Duplicate Order ID Conflict",""),2)="; ",MID(AC110&IF(B110="","; Missing Order Date","")&IF(C110="","; Missing Ship Date","")&IF(P110<0,"; Invalid Discount (Negative)","")&IF(P110>0.5,"; Invalid Discount (Too High)","")&IF(Z110<0,"; Invalid Shipping Record (Ship Before Order)","")&IF(ABS(Q110-W110)>1,"; Sales Mismatch","")&IF(ABS(S110-X110)>1,"; Profit Mismatch","")&IF(COUNTIF($A$2:$A$913,A110)>1,"; Duplicate Order ID Conflict",""),3,500),AC110&IF(B110="","; Missing Order Date","")&IF(C110="","; Missing Ship Date","")&IF(P110<0,"; Invalid Discount (Negative)","")&IF(P110>0.5,"; Invalid Discount (Too High)","")&IF(Z110<0,"; Invalid Shipping Record (Ship Before Order)","")&IF(ABS(Q110-W110)>1,"; Sales Mismatch","")&IF(ABS(S110-X110)>1,"; Profit Mismatch","")&IF(COUNTIF($A$2:$A$913,A110)>1,"; Duplicate Order ID Conflict","")) | AE110: =IF(OR(ISNUMBER(SEARCH("Invalid Discount",AD110)),ISNUMBER(SEARCH("Invalid Shipping Record",AD110)),ISNUMBER(SEARCH("Sales Mismatch",AD110)),ISNUMBER(SEARCH("Profit Mismatch",AD110)),ISNUMBER(SEARCH("Duplicate Order ID Conflict",AD110)),ISNUMBER(SEARCH("Missing Order Date",AD110)),ISNUMBER(SEARCH("Missing Ship Date",AD110))),"Invalid",IF(AD110<>"","Warning","Clean")) -> Clean
A111: ORD-2025-10110 | B111: 45892 | C111: 45896 | D111: CUST-3740 | E111: =PROPER(TRIM(SUBSTITUTE(Raw_Text_Fields!B112,CHAR(160)," "))) -> Sneha Kapoor | F111: =PROPER(TRIM(SUBSTITUTE(Raw_Text_Fields!C112,CHAR(160)," "))) -> Consumer | G111: =PROPER(TRIM(SUBSTITUTE(Raw_Text_Fields!D112,CHAR(160)," "))) -> North | H111: =PROPER(TRIM(SUBSTITUTE(Raw_Text_Fields!E112,CHAR(160)," "))) -> Delhi | I111: =PROPER(TRIM(SUBSTITUTE(Raw_Text_Fields!F112,CHAR(160)," "))) -> New Delhi | J111: =PROPER(TRIM(SUBSTITUTE(Raw_Text_Fields!G112,CHAR(160)," "))) -> Office Supplies | K111: =PROPER(TRIM(SUBSTITUTE(Raw_Text_Fields!H112,CHAR(160)," "))) -> Binders | L111: Classic Binders 660 | M111: =PROPER(TRIM(SUBSTITUTE(Raw_Text_Fields!I112,CHAR(160)," "))) -> Second Class | N111: 1 | O111: 2788.62 | P111: 0.25 | Q111: 2091.47 | R111: 1317.22 | S111: 774.25 | T111: =PROPER(TRIM(SUBSTITUTE(Raw_Text_Fields!J112,CHAR(160)," "))) -> Paid | U111: =PROPER(TRIM(SUBSTITUTE(Raw_Text_Fields!K112,CHAR(160)," "))) -> Completed | V111: =IF(OR(P111<0,P111>0.5),0,P111) -> 0.25 | W111: =N111*O111*(1-V111) -> 2091.465 | X111: =W111-R111 -> 774.245 | Y111: =IFERROR(X111/W111,0) -> 0.37019266 | Z111: =C111-B111 -> 4 | AA111: =IF(B111="","",TEXT(B111,"mmm")) -> Aug | AB111: =IF(B111="","",YEAR(B111)) -> 2025 | AD111: =IF(LEFT(AC111&IF(B111="","; Missing Order Date","")&IF(C111="","; Missing Ship Date","")&IF(P111<0,"; Invalid Discount (Negative)","")&IF(P111>0.5,"; Invalid Discount (Too High)","")&IF(Z111<0,"; Invalid Shipping Record (Ship Before Order)","")&IF(ABS(Q111-W111)>1,"; Sales Mismatch","")&IF(ABS(S111-X111)>1,"; Profit Mismatch","")&IF(COUNTIF($A$2:$A$913,A111)>1,"; Duplicate Order ID Conflict",""),2)="; ",MID(AC111&IF(B111="","; Missing Order Date","")&IF(C111="","; Missing Ship Date","")&IF(P111<0,"; Invalid Discount (Negative)","")&IF(P111>0.5,"; Invalid Discount (Too High)","")&IF(Z111<0,"; Invalid Shipping Record (Ship Before Order)","")&IF(ABS(Q111-W111)>1,"; Sales Mismatch","")&IF(ABS(S111-X111)>1,"; Profit Mismatch","")&IF(COUNTIF($A$2:$A$913,A111)>1,"; Duplicate Order ID Conflict",""),3,500),AC111&IF(B111="","; Missing Order Date","")&IF(C111="","; Missing Ship Date","")&IF(P111<0,"; Invalid Discount (Negative)","")&IF(P111>0.5,"; Invalid Discount (Too High)","")&IF(Z111<0,"; Invalid Shipping Record (Ship Before Order)","")&IF(ABS(Q111-W111)>1,"; Sales Mismatch","")&IF(ABS(S111-X111)>1,"; Profit Mismatch","")&IF(COUNTIF($A$2:$A$913,A111)>1,"; Duplicate Order ID Conflict","")) | AE111: =IF(OR(ISNUMBER(SEARCH("Invalid Discount",AD111)),ISNUMBER(SEARCH("Invalid Shipping Record",AD111)),ISNUMBER(SEARCH("Sales Mismatch",AD111)),ISNUMBER(SEARCH("Profit Mismatch",AD111)),ISNUMBER(SEARCH("Duplicate Order ID Conflict",AD111)),ISNUMBER(SEARCH("Missing Order Date",AD111)),ISNUMBER(SEARCH("Missing Ship Date",AD111))),"Invalid",IF(AD111<>"","Warning","Clean")) -> Clean
A112: ORD-2024-10111 | B112: 45583 | C112: 45589 | D112: CUST-7128 | E112: =PROPER(TRIM(SUBSTITUTE(Raw_Text_Fields!B113,CHAR(160)," "))) -> Vikram Iyer | F112: =PROPER(TRIM(SUBSTITUTE(Raw_Text_Fields!C113,CHAR(160)," "))) -> Corporate | G112: =PROPER(TRIM(SUBSTITUTE(Raw_Text_Fields!D113,CHAR(160)," "))) -> South | H112: =PROPER(TRIM(SUBSTITUTE(Raw_Text_Fields!E113,CHAR(160)," "))) -> Kerala | I112: =PROPER(TRIM(SUBSTITUTE(Raw_Text_Fields!F113,CHAR(160)," "))) -> Kochi | J112: =PROPER(TRIM(SUBSTITUTE(Raw_Text_Fields!G113,CHAR(160)," "))) -> Office Supplies | K112: =PROPER(TRIM(SUBSTITUTE(Raw_Text_Fields!H113,CHAR(160)," "))) -> Labels | L112: Pro Labels 255 | M112: =PROPER(TRIM(SUBSTITUTE(Raw_Text_Fields!I113,CHAR(160)," "))) -> First Class | N112: 2 | O112: 2250.47 | P112: 0 | Q112: 4500.94 | R112: 2607.73 | S112: 1893.21 | T112: =PROPER(TRIM(SUBSTITUTE(Raw_Text_Fields!J113,CHAR(160)," "))) -> Refunded | U112: =PROPER(TRIM(SUBSTITUTE(Raw_Text_Fields!K113,CHAR(160)," "))) -> Cancelled | V112: =IF(OR(P112<0,P112>0.5),0,P112) -> 0 | W112: =N112*O112*(1-V112) -> 4500.94 | X112: =W112-R112 -> 1893.21 | Y112: =IFERROR(X112/W112,0) -> 0.42062547 | Z112: =C112-B112 -> 6 | AA112: =IF(B112="","",TEXT(B112,"mmm")) -> Oct | AB112: =IF(B112="","",YEAR(B112)) -> 2024 | AD112: =IF(LEFT(AC112&IF(B112="","; Missing Order Date","")&IF(C112="","; Missing Ship Date","")&IF(P112<0,"; Invalid Discount (Negative)","")&IF(P112>0.5,"; Invalid Discount (Too High)","")&IF(Z112<0,"; Invalid Shipping Record (Ship Before Order)","")&IF(ABS(Q112-W112)>1,"; Sales Mismatch","")&IF(ABS(S112-X112)>1,"; Profit Mismatch","")&IF(COUNTIF($A$2:$A$913,A112)>1,"; Duplicate Order ID Conflict",""),2)="; ",MID(AC112&IF(B112="","; Missing Order Date","")&IF(C112="","; Missing Ship Date","")&IF(P112<0,"; Invalid Discount (Negative)","")&IF(P112>0.5,"; Invalid Discount (Too High)","")&IF(Z112<0,"; Invalid Shipping Record (Ship Before Order)","")&IF(ABS(Q112-W112)>1,"; Sales Mismatch","")&IF(ABS(S112-X112)>1,"; Profit Mismatch","")&IF(COUNTIF($A$2:$A$913,A112)>1,"; Duplicate Order ID Conflict",""),3,500),AC112&IF(B112="","; Missing Order Date","")&IF(C112="","; Missing Ship Date","")&IF(P112<0,"; Invalid Discount (Negative)","")&IF(P112>0.5,"; Invalid Discount (Too High)","")&IF(Z112<0,"; Invalid Shipping Record (Ship Before Order)","")&IF(ABS(Q112-W112)>1,"; Sales Mismatch","")&IF(ABS(S112-X112)>1,"; Profit Mismatch","")&IF(COUNTIF($A$2:$A$913,A112)>1,"; Duplicate Order ID Conflict","")) | AE112: =IF(OR(ISNUMBER(SEARCH("Invalid Discount",AD112)),ISNUMBER(SEARCH("Invalid Shipping Record",AD112)),ISNUMBER(SEARCH("Sales Mismatch",AD112)),ISNUMBER(SEARCH("Profit Mismatch",AD112)),ISNUMBER(SEARCH("Duplicate Order ID Conflict",AD112)),ISNUMBER(SEARCH("Missing Order Date",AD112)),ISNUMBER(SEARCH("Missing Ship Date",AD112))),"Invalid",IF(AD112<>"","Warning","Clean")) -> Clean
A113: ORD-2025-10112 | B113: 45835 | C113: 45838 | D113: CUST-4743 | E113: =PROPER(TRIM(SUBSTITUTE(Raw_Text_Fields!B114,CHAR(160)," "))) -> Neha Gupta | F113: =PROPER(TRIM(SUBSTITUTE(Raw_Text_Fields!C114,CHAR(160)," "))) -> Corporate | G113: =PROPER(TRIM(SUBSTITUTE(Raw_Text_Fields!D114,CHAR(160)," "))) -> East | H113: =PROPER(TRIM(SUBSTITUTE(Raw_Text_Fields!E114,CHAR(160)," "))) -> Bihar | I113: =PROPER(TRIM(SUBSTITUTE(Raw_Text_Fields!F114,CHAR(160)," "))) -> Patna | J113: =PROPER(TRIM(SUBSTITUTE(Raw_Text_Fields!G114,CHAR(160)," "))) -> Technology | K113: =PROPER(TRIM(SUBSTITUTE(Raw_Text_Fields!H114,CHAR(160)," "))) -> Accessories | L113: Basic Accessories 187 | M113: =PROPER(TRIM(SUBSTITUTE(Raw_Text_Fields!I114,CHAR(160)," "))) -> First Class | N113: 1 | O113: 1708.44 | P113: 0.05 | Q113: 1623.02 | R113: 1077.46 | S113: 545.56 | T113: =PROPER(TRIM(SUBSTITUTE(Raw_Text_Fields!J114,CHAR(160)," "))) -> Pending | U113: =PROPER(TRIM(SUBSTITUTE(Raw_Text_Fields!K114,CHAR(160)," "))) -> Cancelled | V113: =IF(OR(P113<0,P113>0.5),0,P113) -> 0.05 | W113: =N113*O113*(1-V113) -> 1623.018 | X113: =W113-R113 -> 545.558 | Y113: =IFERROR(X113/W113,0) -> 0.33613798 | Z113: =C113-B113 -> 3 | AA113: =IF(B113="","",TEXT(B113,"mmm")) -> Jun | AB113: =IF(B113="","",YEAR(B113)) -> 2025 | AD113: =IF(LEFT(AC113&IF(B113="","; Missing Order Date","")&IF(C113="","; Missing Ship Date","")&IF(P113<0,"; Invalid Discount (Negative)","")&IF(P113>0.5,"; Invalid Discount (Too High)","")&IF(Z113<0,"; Invalid Shipping Record (Ship Before Order)","")&IF(ABS(Q113-W113)>1,"; Sales Mismatch","")&IF(ABS(S113-X113)>1,"; Profit Mismatch","")&IF(COUNTIF($A$2:$A$913,A113)>1,"; Duplicate Order ID Conflict",""),2)="; ",MID(AC113&IF(B113="","; Missing Order Date","")&IF(C113="","; Missing Ship Date","")&IF(P113<0,"; Invalid Discount (Negative)","")&IF(P113>0.5,"; Invalid Discount (Too High)","")&IF(Z113<0,"; Invalid Shipping Record (Ship Before Order)","")&IF(ABS(Q113-W113)>1,"; Sales Mismatch","")&IF(ABS(S113-X113)>1,"; Profit Mismatch","")&IF(COUNTIF($A$2:$A$913,A113)>1,"; Duplicate Order ID Conflict",""),3,500),AC113&IF(B113="","; Missing Order Date","")&IF(C113="","; Missing Ship Date","")&IF(P113<0,"; Invalid Discount (Negative)","")&IF(P113>0.5,"; Invalid Discount (Too High)","")&IF(Z113<0,"; Invalid Shipping Record (Ship Before Order)","")&IF(ABS(Q113-W113)>1,"; Sales Mismatch","")&IF(ABS(S113-X113)>1,"; Profit Mismatch","")&IF(COUNTIF($A$2:$A$913,A113)>1,"; Duplicate Order ID Conflict","")) | AE113: =IF(OR(ISNUMBER(SEARCH("Invalid Discount",AD113)),ISNUMBER(SEARCH("Invalid Shipping Record",AD113)),ISNUMBER(SEARCH("Sales Mismatch",AD113)),ISNUMBER(SEARCH("Profit Mismatch",AD113)),ISNUMBER(SEARCH("Duplicate Order ID Conflict",AD113)),ISNUMBER(SEARCH("Missing Order Date",AD113)),ISNUMBER(SEARCH("Missing Ship Date",AD113))),"Invalid",IF(AD113<>"","Warning","Clean")) -> Clean
A114: ORD-2024-10113 | B114: 45301 | C114: 45305 | D114: CUST-5213 | E114: =PROPER(TRIM(SUBSTITUTE(Raw_Text_Fields!B115,CHAR(160)," "))) -> Sneha Kapoor | F114: =PROPER(TRIM(SUBSTITUTE(Raw_Text_Fields!C115,CHAR(160)," "))) -> Consumer | G114: =PROPER(TRIM(SUBSTITUTE(Raw_Text_Fields!D115,CHAR(160)," "))) -> Unknown | H114: =PROPER(TRIM(SUBSTITUTE(Raw_Text_Fields!E115,CHAR(160)," "))) -> Gujarat | I114: =PROPER(TRIM(SUBSTITUTE(Raw_Text_Fields!F115,CHAR(160)," "))) -> Ahmedabad | J114: =PROPER(TRIM(SUBSTITUTE(Raw_Text_Fields!G115,CHAR(160)," "))) -> Technology | K114: =PROPER(TRIM(SUBSTITUTE(Raw_Text_Fields!H115,CHAR(160)," "))) -> Accessories | L114: Max Accessories 451 | M114: =PROPER(TRIM(SUBSTITUTE(Raw_Text_Fields!I115,CHAR(160)," "))) -> Standard Class | N114: 3 | O114: 3829.48 | P114: 0.05 | Q114: 10914.02 | R114: 6548.74 | S114: 4365.28 | T114: =PROPER(TRIM(SUBSTITUTE(Raw_Text_Fields!J115,CHAR(160)," "))) -> Paid | U114: =PROPER(TRIM(SUBSTITUTE(Raw_Text_Fields!K115,CHAR(160)," "))) -> Completed | V114: =IF(OR(P114<0,P114>0.5),0,P114) -> 0.05 | W114: =N114*O114*(1-V114) -> 10914.018 | X114: =W114-R114 -> 4365.278 | Y114: =IFERROR(X114/W114,0) -> 0.39996984 | Z114: =C114-B114 -> 4 | AA114: =IF(B114="","",TEXT(B114,"mmm")) -> Jan | AB114: =IF(B114="","",YEAR(B114)) -> 2024 | AC114: Missing Region (filled Unknown) | AD114: =IF(LEFT(AC114&IF(B114="","; Missing Order Date","")&IF(C114="","; Missing Ship Date","")&IF(P114<0,"; Invalid Discount (Negative)","")&IF(P114>0.5,"; Invalid Discount (Too High)","")&IF(Z114<0,"; Invalid Shipping Record (Ship Before Order)","")&IF(ABS(Q114-W114)>1,"; Sales Mismatch","")&IF(ABS(S114-X114)>1,"; Profit Mismatch","")&IF(COUNTIF($A$2:$A$913,A114)>1,"; Duplicate Order ID Conflict",""),2)="; ",MID(AC114&IF(B114="","; Missing Order Date","")&IF(C114="","; Missing Ship Date","")&IF(P114<0,"; Invalid Discount (Negative)","")&IF(P114>0.5,"; Invalid Discount (Too High)","")&IF(Z114<0,"; Invalid Shipping Record (Ship Before Order)","")&IF(ABS(Q114-W114)>1,"; Sales Mismatch","")&IF(ABS(S114-X114)>1,"; Profit Mismatch","")&IF(COUNTIF($A$2:$A$913,A114)>1,"; Duplicate Order ID Conflict",""),3,500),AC114&IF(B114="","; Missing Order Date","")&IF(C114="","; Missing Ship Date","")&IF(P114<0,"; Invalid Discount (Negative)","")&IF(P114>0.5,"; Invalid Discount (Too High)","")&IF(Z114<0,"; Invalid Shipping Record (Ship Before Order)","")&IF(ABS(Q114-W114)>1,"; Sales Mismatch","")&IF(ABS(S114-X114)>1,"; Profit Mismatch","")&IF(COUNTIF($A$2:$A$913,A114)>1,"; Duplicate Order ID Conflict","")) -> Missing Region (filled Unknown) | AE114: =IF(OR(ISNUMBER(SEARCH("Invalid Discount",AD114)),ISNUMBER(SEARCH("Invalid Shipping Record",AD114)),ISNUMBER(SEARCH("Sales Mismatch",AD114)),ISNUMBER(SEARCH("Profit Mismatch",AD114)),ISNUMBER(SEARCH("Duplicate Order ID Conflict",AD114)),ISNUMBER(SEARCH("Missing Order Date",AD114)),ISNUMBER(SEARCH("Missing Ship Date",AD114))),"Invalid",IF(AD114<>"","Warning","Clean")) -> Warning
A115: ORD-2024-10114 | B115: 45334 | C115: 45334 | D115: CUST-4989 | E115: =PROPER(TRIM(SUBSTITUTE(Raw_Text_Fields!B116,CHAR(160)," "))) -> Isha Nair | F115: =PROPER(TRIM(SUBSTITUTE(Raw_Text_Fields!C116,CHAR(160)," "))) -> Home Office | G115: =PROPER(TRIM(SUBSTITUTE(Raw_Text_Fields!D116,CHAR(160)," "))) -> South | H115: =PROPER(TRIM(SUBSTITUTE(Raw_Text_Fields!E116,CHAR(160)," "))) -> Tamil Nadu | I115: =PROPER(TRIM(SUBSTITUTE(Raw_Text_Fields!F116,CHAR(160)," "))) -> Chennai | J115: =PROPER(TRIM(SUBSTITUTE(Raw_Text_Fields!G116,CHAR(160)," "))) -> Furniture | K115: =PROPER(TRIM(SUBSTITUTE(Raw_Text_Fields!H116,CHAR(160)," "))) -> Tables | L115: Classic Tables 752 | M115: =PROPER(TRIM(SUBSTITUTE(Raw_Text_Fields!I116,CHAR(160)," "))) -> Standard Class | N115: 3 | O115: 1089.15 | P115: 0.25 | Q115: 2450.59 | R115: 1639.89 | S115: 810.7 | T115: =PROPER(TRIM(SUBSTITUTE(Raw_Text_Fields!J116,CHAR(160)," "))) -> Paid | U115: =PROPER(TRIM(SUBSTITUTE(Raw_Text_Fields!K116,CHAR(160)," "))) -> Completed | V115: =IF(OR(P115<0,P115>0.5),0,P115) -> 0.25 | W115: =N115*O115*(1-V115) -> 2450.5875 | X115: =W115-R115 -> 810.6975 | Y115: =IFERROR(X115/W115,0) -> 0.33081761 | Z115: =C115-B115 -> 0 | AA115: =IF(B115="","",TEXT(B115,"mmm")) -> Feb | AB115: =IF(B115="","",YEAR(B115)) -> 2024 | AD115: =IF(LEFT(AC115&IF(B115="","; Missing Order Date","")&IF(C115="","; Missing Ship Date","")&IF(P115<0,"; Invalid Discount (Negative)","")&IF(P115>0.5,"; Invalid Discount (Too High)","")&IF(Z115<0,"; Invalid Shipping Record (Ship Before Order)","")&IF(ABS(Q115-W115)>1,"; Sales Mismatch","")&IF(ABS(S115-X115)>1,"; Profit Mismatch","")&IF(COUNTIF($A$2:$A$913,A115)>1,"; Duplicate Order ID Conflict",""),2)="; ",MID(AC115&IF(B115="","; Missing Order Date","")&IF(C115="","; Missing Ship Date","")&IF(P115<0,"; Invalid Discount (Negative)","")&IF(P115>0.5,"; Invalid Discount (Too High)","")&IF(Z115<0,"; Invalid Shipping Record (Ship Before Order)","")&IF(ABS(Q115-W115)>1,"; Sales Mismatch","")&IF(ABS(S115-X115)>1,"; Profit Mismatch","")&IF(COUNTIF($A$2:$A$913,A115)>1,"; Duplicate Order ID Conflict",""),3,500),AC115&IF(B115="","; Missing Order Date","")&IF(C115="","; Missing Ship Date","")&IF(P115<0,"; Invalid Discount (Negative)","")&IF(P115>0.5,"; Invalid Discount (Too High)","")&IF(Z115<0,"; Invalid Shipping Record (Ship Before Order)","")&IF(ABS(Q115-W115)>1,"; Sales Mismatch","")&IF(ABS(S115-X115)>1,"; Profit Mismatch","")&IF(COUNTIF($A$2:$A$913,A115)>1,"; Duplicate Order ID Conflict","")) | AE115: =IF(OR(ISNUMBER(SEARCH("Invalid Discount",AD115)),ISNUMBER(SEARCH("Invalid Shipping Record",AD115)),ISNUMBER(SEARCH("Sales Mismatch",AD115)),ISNUMBER(SEARCH("Profit Mismatch",AD115)),ISNUMBER(SEARCH("Duplicate Order ID Conflict",AD115)),ISNUMBER(SEARCH("Missing Order Date",AD115)),ISNUMBER(SEARCH("Missing Ship Date",AD115))),"Invalid",IF(AD115<>"","Warning","Clean")) -> Clean
A116: ORD-2024-10115 | B116: 45560 | C116: 45565 | D116: CUST-2927 | E116: =PROPER(TRIM(SUBSTITUTE(Raw_Text_Fields!B117,CHAR(160)," "))) -> Neha Gupta | F116: =PROPER(TRIM(SUBSTITUTE(Raw_Text_Fields!C117,CHAR(160)," "))) -> Small Business | G116: =PROPER(TRIM(SUBSTITUTE(Raw_Text_Fields!D117,CHAR(160)," "))) -> North | H116: =PROPER(TRIM(SUBSTITUTE(Raw_Text_Fields!E117,CHAR(160)," "))) -> Rajasthan | I116: =PROPER(TRIM(SUBSTITUTE(Raw_Text_Fields!F117,CHAR(160)," "))) -> Jaipur | J116: =PROPER(TRIM(SUBSTITUTE(Raw_Text_Fields!G117,CHAR(160)," "))) -> Technology | K116: =PROPER(TRIM(SUBSTITUTE(Raw_Text_Fields!H117,CHAR(160)," "))) -> Accessories | L116: Eco Accessories 452 | M116: =PROPER(TRIM(SUBSTITUTE(Raw_Text_Fields!I117,CHAR(160)," "))) -> Second Class | N116: 1 | O116: 4388.4 | P116: 0.1 | Q116: 3949.56 | R116: 3186.73 | S116: 762.83 | T116: =PROPER(TRIM(SUBSTITUTE(Raw_Text_Fields!J117,CHAR(160)," "))) -> Pending | U116: =PROPER(TRIM(SUBSTITUTE(Raw_Text_Fields!K117,CHAR(160)," "))) -> Cancelled | V116: =IF(OR(P116<0,P116>0.5),0,P116) -> 0.1 | W116: =N116*O116*(1-V116) -> 3949.56 | X116: =W116-R116 -> 762.83 | Y116: =IFERROR(X116/W116,0) -> 0.19314303 | Z116: =C116-B116 -> 5 | AA116: =IF(B116="","",TEXT(B116,"mmm")) -> Sep | AB116: =IF(B116="","",YEAR(B116)) -> 2024 | AD116: =IF(LEFT(AC116&IF(B116="","; Missing Order Date","")&IF(C116="","; Missing Ship Date","")&IF(P116<0,"; Invalid Discount (Negative)","")&IF(P116>0.5,"; Invalid Discount (Too High)","")&IF(Z116<0,"; Invalid Shipping Record (Ship Before Order)","")&IF(ABS(Q116-W116)>1,"; Sales Mismatch","")&IF(ABS(S116-X116)>1,"; Profit Mismatch","")&IF(COUNTIF($A$2:$A$913,A116)>1,"; Duplicate Order ID Conflict",""),2)="; ",MID(AC116&IF(B116="","; Missing Order Date","")&IF(C116="","; Missing Ship Date","")&IF(P116<0,"; Invalid Discount (Negative)","")&IF(P116>0.5,"; Invalid Discount (Too High)","")&IF(Z116<0,"; Invalid Shipping Record (Ship Before Order)","")&IF(ABS(Q116-W116)>1,"; Sales Mismatch","")&IF(ABS(S116-X116)>1,"; Profit Mismatch","")&IF(COUNTIF($A$2:$A$913,A116)>1,"; Duplicate Order ID Conflict",""),3,500),AC116&IF(B116="","; Missing Order Date","")&IF(C116="","; Missing Ship Date","")&IF(P116<0,"; Invalid Discount (Negative)","")&IF(P116>0.5,"; Invalid Discount (Too High)","")&IF(Z116<0,"; Invalid Shipping Record (Ship Before Order)","")&IF(ABS(Q116-W116)>1,"; Sales Mismatch","")&IF(ABS(S116-X116)>1,"; Profit Mismatch","")&IF(COUNTIF($A$2:$A$913,A116)>1,"; Duplicate Order ID Conflict","")) | AE116: =IF(OR(ISNUMBER(SEARCH("Invalid Discount",AD116)),ISNUMBER(SEARCH("Invalid Shipping Record",AD116)),ISNUMBER(SEARCH("Sales Mismatch",AD116)),ISNUMBER(SEARCH("Profit Mismatch",AD116)),ISNUMBER(SEARCH("Duplicate Order ID Conflict",AD116)),ISNUMBER(SEARCH("Missing Order Date",AD116)),ISNUMBER(SEARCH("Missing Ship Date",AD116))),"Invalid",IF(AD116<>"","Warning","Clean")) -> Clean
A117: ORD-2024-10116 | B117: 45653 | C117: 45658 | D117: CUST-7764 | E117: =PROPER(TRIM(SUBSTITUTE(Raw_Text_Fields!B118,CHAR(160)," "))) -> Kabir Singh | F117: =PROPER(TRIM(SUBSTITUTE(Raw_Text_Fields!C118,CHAR(160)," "))) -> Corporate | G117: =PROPER(TRIM(SUBSTITUTE(Raw_Text_Fields!D118,CHAR(160)," "))) -> South | H117: =PROPER(TRIM(SUBSTITUTE(Raw_Text_Fields!E118,CHAR(160)," "))) -> Tamil Nadu | I117: =PROPER(TRIM(SUBSTITUTE(Raw_Text_Fields!F118,CHAR(160)," "))) -> Chennai | J117: =PROPER(TRIM(SUBSTITUTE(Raw_Text_Fields!G118,CHAR(160)," "))) -> Office Supplies | K117: =PROPER(TRIM(SUBSTITUTE(Raw_Text_Fields!H118,CHAR(160)," "))) -> Binders | L117: Classic Binders 203 | M117: =PROPER(TRIM(SUBSTITUTE(Raw_Text_Fields!I118,CHAR(160)," "))) -> Same Day | N117: 2 | O117: 446.34 | P117: 0.15 | Q117: 758.78 | R117: 490.74 | S117: 268.04 | T117: =PROPER(TRIM(SUBSTITUTE(Raw_Text_Fields!J118,CHAR(160)," "))) -> Paid | U117: =PROPER(TRIM(SUBSTITUTE(Raw_Text_Fields!K118,CHAR(160)," "))) -> Cancelled | V117: =IF(OR(P117<0,P117>0.5),0,P117) -> 0.15 | W117: =N117*O117*(1-V117) -> 758.778 | X117: =W117-R117 -> 268.038 | Y117: =IFERROR(X117/W117,0) -> 0.35324957 | Z117: =C117-B117 -> 5 | AA117: =IF(B117="","",TEXT(B117,"mmm")) -> Dec | AB117: =IF(B117="","",YEAR(B117)) -> 2024 | AD117: =IF(LEFT(AC117&IF(B117="","; Missing Order Date","")&IF(C117="","; Missing Ship Date","")&IF(P117<0,"; Invalid Discount (Negative)","")&IF(P117>0.5,"; Invalid Discount (Too High)","")&IF(Z117<0,"; Invalid Shipping Record (Ship Before Order)","")&IF(ABS(Q117-W117)>1,"; Sales Mismatch","")&IF(ABS(S117-X117)>1,"; Profit Mismatch","")&IF(COUNTIF($A$2:$A$913,A117)>1,"; Duplicate Order ID Conflict",""),2)="; ",MID(AC117&IF(B117="","; Missing Order Date","")&IF(C117="","; Missing Ship Date","")&IF(P117<0,"; Invalid Discount (Negative)","")&IF(P117>0.5,"; Invalid Discount (Too High)","")&IF(Z117<0,"; Invalid Shipping Record (Ship Before Order)","")&IF(ABS(Q117-W117)>1,"; Sales Mismatch","")&IF(ABS(S117-X117)>1,"; Profit Mismatch","")&IF(COUNTIF($A$2:$A$913,A117)>1,"; Duplicate Order ID Conflict",""),3,500),AC117&IF(B117="","; Missing Order Date","")&IF(C117="","; Missing Ship Date","")&IF(P117<0,"; Invalid Discount (Negative)","")&IF(P117>0.5,"; Invalid Discount (Too High)","")&IF(Z117<0,"; Invalid Shipping Record (Ship Before Order)","")&IF(ABS(Q117-W117)>1,"; Sales Mismatch","")&IF(ABS(S117-X117)>1,"; Profit Mismatch","")&IF(COUNTIF($A$2:$A$913,A117)>1,"; Duplicate Order ID Conflict","")) | AE117: =IF(OR(ISNUMBER(SEARCH("Invalid Discount",AD117)),ISNUMBER(SEARCH("Invalid Shipping Record",AD117)),ISNUMBER(SEARCH("Sales Mismatch",AD117)),ISNUMBER(SEARCH("Profit Mismatch",AD117)),ISNUMBER(SEARCH("Duplicate Order ID Conflict",AD117)),ISNUMBER(SEARCH("Missing Order Date",AD117)),ISNUMBER(SEARCH("Missing Ship Date",AD117))),"Invalid",IF(AD117<>"","Warning","Clean")) -> Clean
A118: ORD-2025-10117 | B118: 45703 | C118: 45707 | D118: CUST-3632 | E118: =PROPER(TRIM(SUBSTITUTE(Raw_Text_Fields!B119,CHAR(160)," "))) -> Ananya Rao | F118: =PROPER(TRIM(SUBSTITUTE(Raw_Text_Fields!C119,CHAR(160)," "))) -> Small Business | G118: =PROPER(TRIM(SUBSTITUTE(Raw_Text_Fields!D119,CHAR(160)," "))) -> Unknown | H118: =PROPER(TRIM(SUBSTITUTE(Raw_Text_Fields!E119,CHAR(160)," "))) -> Madhya Pradesh | I118: =PROPER(TRIM(SUBSTITUTE(Raw_Text_Fields!F119,CHAR(160)," "))) -> Indore | J118: =PROPER(TRIM(SUBSTITUTE(Raw_Text_Fields!G119,CHAR(160)," "))) -> Office Supplies | K118: =PROPER(TRIM(SUBSTITUTE(Raw_Text_Fields!H119,CHAR(160)," "))) -> Binders | L118: Basic Binders 859 | M118: =PROPER(TRIM(SUBSTITUTE(Raw_Text_Fields!I119,CHAR(160)," "))) -> First Class | N118: 9 | O118: 531.99 | P118: 0.25 | Q118: 3590.93 | R118: 3061.39 | S118: 529.54 | T118: =PROPER(TRIM(SUBSTITUTE(Raw_Text_Fields!J119,CHAR(160)," "))) -> Failed | U118: =PROPER(TRIM(SUBSTITUTE(Raw_Text_Fields!K119,CHAR(160)," "))) -> Cancelled | V118: =IF(OR(P118<0,P118>0.5),0,P118) -> 0.25 | W118: =N118*O118*(1-V118) -> 3590.9325 | X118: =W118-R118 -> 529.5425 | Y118: =IFERROR(X118/W118,0) -> 0.14746657 | Z118: =C118-B118 -> 4 | AA118: =IF(B118="","",TEXT(B118,"mmm")) -> Feb | AB118: =IF(B118="","",YEAR(B118)) -> 2025 | AC118: Missing Region (filled Unknown) | AD118: =IF(LEFT(AC118&IF(B118="","; Missing Order Date","")&IF(C118="","; Missing Ship Date","")&IF(P118<0,"; Invalid Discount (Negative)","")&IF(P118>0.5,"; Invalid Discount (Too High)","")&IF(Z118<0,"; Invalid Shipping Record (Ship Before Order)","")&IF(ABS(Q118-W118)>1,"; Sales Mismatch","")&IF(ABS(S118-X118)>1,"; Profit Mismatch","")&IF(COUNTIF($A$2:$A$913,A118)>1,"; Duplicate Order ID Conflict",""),2)="; ",MID(AC118&IF(B118="","; Missing Order Date","")&IF(C118="","; Missing Ship Date","")&IF(P118<0,"; Invalid Discount (Negative)","")&IF(P118>0.5,"; Invalid Discount (Too High)","")&IF(Z118<0,"; Invalid Shipping Record (Ship Before Order)","")&IF(ABS(Q118-W118)>1,"; Sales Mismatch","")&IF(ABS(S118-X118)>1,"; Profit Mismatch","")&IF(COUNTIF($A$2:$A$913,A118)>1,"; Duplicate Order ID Conflict",""),3,500),AC118&IF(B118="","; Missing Order Date","")&IF(C118="","; Missing Ship Date","")&IF(P118<0,"; Invalid Discount (Negative)","")&IF(P118>0.5,"; Invalid Discount (Too High)","")&IF(Z118<0,"; Invalid Shipping Record (Ship Before Order)","")&IF(ABS(Q118-W118)>1,"; Sales Mismatch","")&IF(ABS(S118-X118)>1,"; Profit Mismatch","")&IF(COUNTIF($A$2:$A$913,A118)>1,"; Duplicate Order ID Conflict","")) -> Missing Region (filled Unknown) | AE118: =IF(OR(ISNUMBER(SEARCH("Invalid Discount",AD118)),ISNUMBER(SEARCH("Invalid Shipping Record",AD118)),ISNUMBER(SEARCH("Sales Mismatch",AD118)),ISNUMBER(SEARCH("Profit Mismatch",AD118)),ISNUMBER(SEARCH("Duplicate Order ID Conflict",AD118)),ISNUMBER(SEARCH("Missing Order Date",AD118)),ISNUMBER(SEARCH("Missing Ship Date",AD118))),"Invalid",IF(AD118<>"","Warning","Clean")) -> Warning
A119: ORD-2024-10118 | B119: 45337 | C119: 45339 | D119: CUST-9608 | E119: =PROPER(TRIM(SUBSTITUTE(Raw_Text_Fields!B120,CHAR(160)," "))) -> Mira Das | F119: =PROPER(TRIM(SUBSTITUTE(Raw_Text_Fields!C120,CHAR(160)," "))) -> Home Office | G119: =PROPER(TRIM(SUBSTITUTE(Raw_Text_Fields!D120,CHAR(160)," "))) -> South | H119: =PROPER(TRIM(SUBSTITUTE(Raw_Text_Fields!E120,CHAR(160)," "))) -> Tamil Nadu | I119: =PROPER(TRIM(SUBSTITUTE(Raw_Text_Fields!F120,CHAR(160)," "))) -> Chennai | J119: =PROPER(TRIM(SUBSTITUTE(Raw_Text_Fields!G120,CHAR(160)," "))) -> Technology | K119: =PROPER(TRIM(SUBSTITUTE(Raw_Text_Fields!H120,CHAR(160)," "))) -> Machines | L119: Elite Machines 705 | M119: =PROPER(TRIM(SUBSTITUTE(Raw_Text_Fields!I120,CHAR(160)," "))) -> Standard Class | N119: 9 | O119: 3324.55 | P119: 0.7 | Q119: 25432.81 | R119: 20370.16 | S119: 5062.65 | T119: =PROPER(TRIM(SUBSTITUTE(Raw_Text_Fields!J120,CHAR(160)," "))) -> Paid | U119: =PROPER(TRIM(SUBSTITUTE(Raw_Text_Fields!K120,CHAR(160)," "))) -> Completed | V119: =IF(OR(P119<0,P119>0.5),0,P119) -> 0 | W119: =N119*O119*(1-V119) -> 29920.95 | X119: =W119-R119 -> 9550.79 | Y119: =IFERROR(X119/W119,0) -> 0.31920076 | Z119: =C119-B119 -> 2 | AA119: =IF(B119="","",TEXT(B119,"mmm")) -> Feb | AB119: =IF(B119="","",YEAR(B119)) -> 2024 | AD119: =IF(LEFT(AC119&IF(B119="","; Missing Order Date","")&IF(C119="","; Missing Ship Date","")&IF(P119<0,"; Invalid Discount (Negative)","")&IF(P119>0.5,"; Invalid Discount (Too High)","")&IF(Z119<0,"; Invalid Shipping Record (Ship Before Order)","")&IF(ABS(Q119-W119)>1,"; Sales Mismatch","")&IF(ABS(S119-X119)>1,"; Profit Mismatch","")&IF(COUNTIF($A$2:$A$913,A119)>1,"; Duplicate Order ID Conflict",""),2)="; ",MID(AC119&IF(B119="","; Missing Order Date","")&IF(C119="","; Missing Ship Date","")&IF(P119<0,"; Invalid Discount (Negative)","")&IF(P119>0.5,"; Invalid Discount (Too High)","")&IF(Z119<0,"; Invalid Shipping Record (Ship Before Order)","")&IF(ABS(Q119-W119)>1,"; Sales Mismatch","")&IF(ABS(S119-X119)>1,"; Profit Mismatch","")&IF(COUNTIF($A$2:$A$913,A119)>1,"; Duplicate Order ID Conflict",""),3,500),AC119&IF(B119="","; Missing Order Date","")&IF(C119="","; Missing Ship Date","")&IF(P119<0,"; Invalid Discount (Negative)","")&IF(P119>0.5,"; Invalid Discount (Too High)","")&IF(Z119<0,"; Invalid Shipping Record (Ship Before Order)","")&IF(ABS(Q119-W119)>1,"; Sales Mismatch","")&IF(ABS(S119-X119)>1,"; Profit Mismatch","")&IF(COUNTIF($A$2:$A$913,A119)>1,"; Duplicate Order ID Conflict","")) -> Invalid Discount (Too High); Sales Mismatch; Profit Mismatch | AE119: =IF(OR(ISNUMBER(SEARCH("Invalid Discount",AD119)),ISNUMBER(SEARCH("Invalid Shipping Record",AD119)),ISNUMBER(SEARCH("Sales Mismatch",AD119)),ISNUMBER(SEARCH("Profit Mismatch",AD119)),ISNUMBER(SEARCH("Duplicate Order ID Conflict",AD119)),ISNUMBER(SEARCH("Missing Order Date",AD119)),ISNUMBER(SEARCH("Missing Ship Date",AD119))),"Invalid",IF(AD119<>"","Warning","Clean")) -> Invalid
A120: ORD-2024-10119 | B120: 45453 | C120: 45461 | D120: CUST-9135 | E120: =PROPER(TRIM(SUBSTITUTE(Raw_Text_Fields!B121,CHAR(160)," "))) -> Vikram Iyer | F120: =PROPER(TRIM(SUBSTITUTE(Raw_Text_Fields!C121,CHAR(160)," "))) -> Home Office | G120: =PROPER(TRIM(SUBSTITUTE(Raw_Text_Fields!D121,CHAR(160)," "))) -> South | H120: =PROPER(TRIM(SUBSTITUTE(Raw_Text_Fields!E121,CHAR(160)," "))) -> Andhra Pradesh | I120: =PROPER(TRIM(SUBSTITUTE(Raw_Text_Fields!F121,CHAR(160)," "))) -> Vijayawada | J120: =PROPER(TRIM(SUBSTITUTE(Raw_Text_Fields!G121,CHAR(160)," "))) -> Technology | K120: =PROPER(TRIM(SUBSTITUTE(Raw_Text_Fields!H121,CHAR(160)," "))) -> Copiers | L120: Pro Copiers 208 | M120: =PROPER(TRIM(SUBSTITUTE(Raw_Text_Fields!I121,CHAR(160)," "))) -> Same Day | N120: 5 | O120: 1580.27 | P120: 0.2 | Q120: 6321.08 | R120: 4407.22 | S120: 1913.86 | T120: =PROPER(TRIM(SUBSTITUTE(Raw_Text_Fields!J121,CHAR(160)," "))) -> Paid | U120: =PROPER(TRIM(SUBSTITUTE(Raw_Text_Fields!K121,CHAR(160)," "))) -> Completed | V120: =IF(OR(P120<0,P120>0.5),0,P120) -> 0.2 | W120: =N120*O120*(1-V120) -> 6321.08 | X120: =W120-R120 -> 1913.86 | Y120: =IFERROR(X120/W120,0) -> 0.30277421 | Z120: =C120-B120 -> 8 | AA120: =IF(B120="","",TEXT(B120,"mmm")) -> Jun | AB120: =IF(B120="","",YEAR(B120)) -> 2024 | AD120: =IF(LEFT(AC120&IF(B120="","; Missing Order Date","")&IF(C120="","; Missing Ship Date","")&IF(P120<0,"; Invalid Discount (Negative)","")&IF(P120>0.5,"; Invalid Discount (Too High)","")&IF(Z120<0,"; Invalid Shipping Record (Ship Before Order)","")&IF(ABS(Q120-W120)>1,"; Sales Mismatch","")&IF(ABS(S120-X120)>1,"; Profit Mismatch","")&IF(COUNTIF($A$2:$A$913,A120)>1,"; Duplicate Order ID Conflict",""),2)="; ",MID(AC120&IF(B120="","; Missing Order Date","")&IF(C120="","; Missing Ship Date","")&IF(P120<0,"; Invalid Discount (Negative)","")&IF(P120>0.5,"; Invalid Discount (Too High)","")&IF(Z120<0,"; Invalid Shipping Record (Ship Before Order)","")&IF(ABS(Q120-W120)>1,"; Sales Mismatch","")&IF(ABS(S120-X120)>1,"; Profit Mismatch","")&IF(COUNTIF($A$2:$A$913,A120)>1,"; Duplicate Order ID Conflict",""),3,500),AC120&IF(B120="","; Missing Order Date","")&IF(C120="","; Missing Ship Date","")&IF(P120<0,"; Invalid Discount (Negative)","")&IF(P120>0.5,"; Invalid Discount (Too High)","")&IF(Z120<0,"; Invalid Shipping Record (Ship Before Order)","")&IF(ABS(Q120-W120)>1,"; Sales Mismatch","")&IF(ABS(S120-X120)>1,"; Profit Mismatch","")&IF(COUNTIF($A$2:$A$913,A120)>1,"; Duplicate Order ID Conflict","")) | AE120: =IF(OR(ISNUMBER(SEARCH("Invalid Discount",AD120)),ISNUMBER(SEARCH("Invalid Shipping Record",AD120)),ISNUMBER(SEARCH("Sales Mismatch",AD120)),ISNUMBER(SEARCH("Profit Mismatch",AD120)),ISNUMBER(SEARCH("Duplicate Order ID Conflict",AD120)),ISNUMBER(SEARCH("Missing Order Date",AD120)),ISNUMBER(SEARCH("Missing Ship Date",AD120))),"Invalid",IF(AD120<>"","Warning","Clean")) -> Clean
A121: ORD-2024-10120 | B121: 45455 | C121: 45462 | D121: CUST-7861 | E121: =PROPER(TRIM(SUBSTITUTE(Raw_Text_Fields!B122,CHAR(160)," "))) -> Aditi Sen | F121: =PROPER(TRIM(SUBSTITUTE(Raw_Text_Fields!C122,CHAR(160)," "))) -> Small Business | G121: =PROPER(TRIM(SUBSTITUTE(Raw_Text_Fields!D122,CHAR(160)," "))) -> South | H121: =PROPER(TRIM(SUBSTITUTE(Raw_Text_Fields!E122,CHAR(160)," "))) -> Kerala | I121: =PROPER(TRIM(SUBSTITUTE(Raw_Text_Fields!F122,CHAR(160)," "))) -> Kochi | J121: =PROPER(TRIM(SUBSTITUTE(Raw_Text_Fields!G122,CHAR(160)," "))) -> Furniture | K121: =PROPER(TRIM(SUBSTITUTE(Raw_Text_Fields!H122,CHAR(160)," "))) -> Chairs | L121: Elite Chairs 921 | M121: =PROPER(TRIM(SUBSTITUTE(Raw_Text_Fields!I122,CHAR(160)," "))) -> Standard Class | N121: 8 | O121: 314.05 | P121: 0.25 | Q121: 1884.3 | R121: 1517.69 | S121: 366.61 | T121: =PROPER(TRIM(SUBSTITUTE(Raw_Text_Fields!J122,CHAR(160)," "))) -> Refunded | U121: =PROPER(TRIM(SUBSTITUTE(Raw_Text_Fields!K122,CHAR(160)," "))) -> Returned | V121: =IF(OR(P121<0,P121>0.5),0,P121) -> 0.25 | W121: =N121*O121*(1-V121) -> 1884.3 | X121: =W121-R121 -> 366.61 | Y121: =IFERROR(X121/W121,0) -> 0.19456031 | Z121: =C121-B121 -> 7 | AA121: =IF(B121="","",TEXT(B121,"mmm")) -> Jun | AB121: =IF(B121="","",YEAR(B121)) -> 2024 | AD121: =IF(LEFT(AC121&IF(B121="","; Missing Order Date","")&IF(C121="","; Missing Ship Date","")&IF(P121<0,"; Invalid Discount (Negative)","")&IF(P121>0.5,"; Invalid Discount (Too High)","")&IF(Z121<0,"; Invalid Shipping Record (Ship Before Order)","")&IF(ABS(Q121-W121)>1,"; Sales Mismatch","")&IF(ABS(S121-X121)>1,"; Profit Mismatch","")&IF(COUNTIF($A$2:$A$913,A121)>1,"; Duplicate Order ID Conflict",""),2)="; ",MID(AC121&IF(B121="","; Missing Order Date","")&IF(C121="","; Missing Ship Date","")&IF(P121<0,"; Invalid Discount (Negative)","")&IF(P121>0.5,"; Invalid Discount (Too High)","")&IF(Z121<0,"; Invalid Shipping Record (Ship Before Order)","")&IF(ABS(Q121-W121)>1,"; Sales Mismatch","")&IF(ABS(S121-X121)>1,"; Profit Mismatch","")&IF(COUNTIF($A$2:$A$913,A121)>1,"; Duplicate Order ID Conflict",""),3,500),AC121&IF(B121="","; Missing Order Date","")&IF(C121="","; Missing Ship Date","")&IF(P121<0,"; Invalid Discount (Negative)","")&IF(P121>0.5,"; Invalid Discount (Too High)","")&IF(Z121<0,"; Invalid Shipping Record (Ship Before Order)","")&IF(ABS(Q121-W121)>1,"; Sales Mismatch","")&IF(ABS(S121-X121)>1,"; Profit Mismatch","")&IF(COUNTIF($A$2:$A$913,A121)>1,"; Duplicate Order ID Conflict","")) | AE121: =IF(OR(ISNUMBER(SEARCH("Invalid Discount",AD121)),ISNUMBER(SEARCH("Invalid Shipping Record",AD121)),ISNUMBER(SEARCH("Sales Mismatch",AD121)),ISNUMBER(SEARCH("Profit Mismatch",AD121)),ISNUMBER(SEARCH("Duplicate Order ID Conflict",AD121)),ISNUMBER(SEARCH("Missing Order Date",AD121)),ISNUMBER(SEARCH("Missing Ship Date",AD121))),"Invalid",IF(AD121<>"","Warning","Clean")) -> Clean
A122: ORD-2024-10121 | B122: 45514 | C122: 45522 | D122: CUST-6096 | E122: =PROPER(TRIM(SUBSTITUTE(Raw_Text_Fields!B123,CHAR(160)," "))) -> Sneha Kapoor | F122: =PROPER(TRIM(SUBSTITUTE(Raw_Text_Fields!C123,CHAR(160)," "))) -> Small Business | G122: =PROPER(TRIM(SUBSTITUTE(Raw_Text_Fields!D123,CHAR(160)," "))) -> East | H122: =PROPER(TRIM(SUBSTITUTE(Raw_Text_Fields!E123,CHAR(160)," "))) -> Bihar | I122: =PROPER(TRIM(SUBSTITUTE(Raw_Text_Fields!F123,CHAR(160)," "))) -> Patna | J122: =PROPER(TRIM(SUBSTITUTE(Raw_Text_Fields!G123,CHAR(160)," "))) -> Technology | K122: =PROPER(TRIM(SUBSTITUTE(Raw_Text_Fields!H123,CHAR(160)," "))) -> Phones | L122: Prime Phones 540 | M122: =PROPER(TRIM(SUBSTITUTE(Raw_Text_Fields!I123,CHAR(160)," "))) -> Standard Class | N122: 1 | O122: 1823.67 | P122: 0.2 | Q122: 1458.94 | R122: 893.2 | S122: 565.74 | T122: =PROPER(TRIM(SUBSTITUTE(Raw_Text_Fields!J123,CHAR(160)," "))) -> Paid | U122: =PROPER(TRIM(SUBSTITUTE(Raw_Text_Fields!K123,CHAR(160)," "))) -> Returned | V122: =IF(OR(P122<0,P122>0.5),0,P122) -> 0.2 | W122: =N122*O122*(1-V122) -> 1458.936 | X122: =W122-R122 -> 565.736 | Y122: =IFERROR(X122/W122,0) -> 0.38777301 | Z122: =C122-B122 -> 8 | AA122: =IF(B122="","",TEXT(B122,"mmm")) -> Aug | AB122: =IF(B122="","",YEAR(B122)) -> 2024 | AD122: =IF(LEFT(AC122&IF(B122="","; Missing Order Date","")&IF(C122="","; Missing Ship Date","")&IF(P122<0,"; Invalid Discount (Negative)","")&IF(P122>0.5,"; Invalid Discount (Too High)","")&IF(Z122<0,"; Invalid Shipping Record (Ship Before Order)","")&IF(ABS(Q122-W122)>1,"; Sales Mismatch","")&IF(ABS(S122-X122)>1,"; Profit Mismatch","")&IF(COUNTIF($A$2:$A$913,A122)>1,"; Duplicate Order ID Conflict",""),2)="; ",MID(AC122&IF(B122="","; Missing Order Date","")&IF(C122="","; Missing Ship Date","")&IF(P122<0,"; Invalid Discount (Negative)","")&IF(P122>0.5,"; Invalid Discount (Too High)","")&IF(Z122<0,"; Invalid Shipping Record (Ship Before Order)","")&IF(ABS(Q122-W122)>1,"; Sales Mismatch","")&IF(ABS(S122-X122)>1,"; Profit Mismatch","")&IF(COUNTIF($A$2:$A$913,A122)>1,"; Duplicate Order ID Conflict",""),3,500),AC122&IF(B122="","; Missing Order Date","")&IF(C122="","; Missing Ship Date","")&IF(P122<0,"; Invalid Discount (Negative)","")&IF(P122>0.5,"; Invalid Discount (Too High)","")&IF(Z122<0,"; Invalid Shipping Record (Ship Before Order)","")&IF(ABS(Q122-W122)>1,"; Sales Mismatch","")&IF(ABS(S122-X122)>1,"; Profit Mismatch","")&IF(COUNTIF($A$2:$A$913,A122)>1,"; Duplicate Order ID Conflict","")) | AE122: =IF(OR(ISNUMBER(SEARCH("Invalid Discount",AD122)),ISNUMBER(SEARCH("Invalid Shipping Record",AD122)),ISNUMBER(SEARCH("Sales Mismatch",AD122)),ISNUMBER(SEARCH("Profit Mismatch",AD122)),ISNUMBER(SEARCH("Duplicate Order ID Conflict",AD122)),ISNUMBER(SEARCH("Missing Order Date",AD122)),ISNUMBER(SEARCH("Missing Ship Date",AD122))),"Invalid",IF(AD122<>"","Warning","Clean")) -> Clean
A123: ORD-2025-10122 | B123: 45891 | C123: 45895 | D123: CUST-2044 | E123: =PROPER(TRIM(SUBSTITUTE(Raw_Text_Fields!B124,CHAR(160)," "))) -> Kabir Singh | F123: =PROPER(TRIM(SUBSTITUTE(Raw_Text_Fields!C124,CHAR(160)," "))) -> Small Business | G123: =PROPER(TRIM(SUBSTITUTE(Raw_Text_Fields!D124,CHAR(160)," "))) -> South | H123: =PROPER(TRIM(SUBSTITUTE(Raw_Text_Fields!E124,CHAR(160)," "))) -> Andhra Pradesh | I123: =PROPER(TRIM(SUBSTITUTE(Raw_Text_Fields!F124,CHAR(160)," "))) -> Vijayawada | J123: =PROPER(TRIM(SUBSTITUTE(Raw_Text_Fields!G124,CHAR(160)," "))) -> Technology | K123: =PROPER(TRIM(SUBSTITUTE(Raw_Text_Fields!H124,CHAR(160)," "))) -> Machines | L123: Max Machines 948 | M123: =PROPER(TRIM(SUBSTITUTE(Raw_Text_Fields!I124,CHAR(160)," "))) -> Second Class | N123: 5 | O123: 3482.92 | P123: 0 | Q123: 17414.6 | R123: 11760.91 | S123: 5653.69 | T123: =PROPER(TRIM(SUBSTITUTE(Raw_Text_Fields!J124,CHAR(160)," "))) -> Refunded | U123: =PROPER(TRIM(SUBSTITUTE(Raw_Text_Fields!K124,CHAR(160)," "))) -> Cancelled | V123: =IF(OR(P123<0,P123>0.5),0,P123) -> 0 | W123: =N123*O123*(1-V123) -> 17414.6 | X123: =W123-R123 -> 5653.69 | Y123: =IFERROR(X123/W123,0) -> 0.3246523 | Z123: =C123-B123 -> 4 | AA123: =IF(B123="","",TEXT(B123,"mmm")) -> Aug | AB123: =IF(B123="","",YEAR(B123)) -> 2025 | AD123: =IF(LEFT(AC123&IF(B123="","; Missing Order Date","")&IF(C123="","; Missing Ship Date","")&IF(P123<0,"; Invalid Discount (Negative)","")&IF(P123>0.5,"; Invalid Discount (Too High)","")&IF(Z123<0,"; Invalid Shipping Record (Ship Before Order)","")&IF(ABS(Q123-W123)>1,"; Sales Mismatch","")&IF(ABS(S123-X123)>1,"; Profit Mismatch","")&IF(COUNTIF($A$2:$A$913,A123)>1,"; Duplicate Order ID Conflict",""),2)="; ",MID(AC123&IF(B123="","; Missing Order Date","")&IF(C123="","; Missing Ship Date","")&IF(P123<0,"; Invalid Discount (Negative)","")&IF(P123>0.5,"; Invalid Discount (Too High)","")&IF(Z123<0,"; Invalid Shipping Record (Ship Before Order)","")&IF(ABS(Q123-W123)>1,"; Sales Mismatch","")&IF(ABS(S123-X123)>1,"; Profit Mismatch","")&IF(COUNTIF($A$2:$A$913,A123)>1,"; Duplicate Order ID Conflict",""),3,500),AC123&IF(B123="","; Missing Order Date","")&IF(C123="","; Missing Ship Date","")&IF(P123<0,"; Invalid Discount (Negative)","")&IF(P123>0.5,"; Invalid Discount (Too High)","")&IF(Z123<0,"; Invalid Shipping Record (Ship Before Order)","")&IF(ABS(Q123-W123)>1,"; Sales Mismatch","")&IF(ABS(S123-X123)>1,"; Profit Mismatch","")&IF(COUNTIF($A$2:$A$913,A123)>1,"; Duplicate Order ID Conflict","")) | AE123: =IF(OR(ISNUMBER(SEARCH("Invalid Discount",AD123)),ISNUMBER(SEARCH("Invalid Shipping Record",AD123)),ISNUMBER(SEARCH("Sales Mismatch",AD123)),ISNUMBER(SEARCH("Profit Mismatch",AD123)),ISNUMBER(SEARCH("Duplicate Order ID Conflict",AD123)),ISNUMBER(SEARCH("Missing Order Date",AD123)),ISNUMBER(SEARCH("Missing Ship Date",AD123))),"Invalid",IF(AD123<>"","Warning","Clean")) -> Clean
A124: ORD-2024-10123 | B124: 45626 | C124: 45630 | D124: CUST-1721 | E124: =PROPER(TRIM(SUBSTITUTE(Raw_Text_Fields!B125,CHAR(160)," "))) -> Ananya Rao | F124: =PROPER(TRIM(SUBSTITUTE(Raw_Text_Fields!C125,CHAR(160)," "))) -> Small Business | G124: =PROPER(TRIM(SUBSTITUTE(Raw_Text_Fields!D125,CHAR(160)," "))) -> East | H124: =PROPER(TRIM(SUBSTITUTE(Raw_Text_Fields!E125,CHAR(160)," "))) -> Assam | I124: =PROPER(TRIM(SUBSTITUTE(Raw_Text_Fields!F125,CHAR(160)," "))) -> Guwahati | J124: =PROPER(TRIM(SUBSTITUTE(Raw_Text_Fields!G125,CHAR(160)," "))) -> Furniture | K124: =PROPER(TRIM(SUBSTITUTE(Raw_Text_Fields!H125,CHAR(160)," "))) -> Chairs | L124: Max Chairs 786 | M124: =PROPER(TRIM(SUBSTITUTE(Raw_Text_Fields!I125,CHAR(160)," "))) -> Second Class | N124: 3 | O124: 170.35 | P124: 0 | Q124: 511.05 | R124: 367.18 | S124: 143.87 | T124: =PROPER(TRIM(SUBSTITUTE(Raw_Text_Fields!J125,CHAR(160)," "))) -> Paid | U124: =PROPER(TRIM(SUBSTITUTE(Raw_Text_Fields!K125,CHAR(160)," "))) -> Completed | V124: =IF(OR(P124<0,P124>0.5),0,P124) -> 0 | W124: =N124*O124*(1-V124) -> 511.05 | X124: =W124-R124 -> 143.87 | Y124: =IFERROR(X124/W124,0) -> 0.28151844 | Z124: =C124-B124 -> 4 | AA124: =IF(B124="","",TEXT(B124,"mmm")) -> Nov | AB124: =IF(B124="","",YEAR(B124)) -> 2024 | AD124: =IF(LEFT(AC124&IF(B124="","; Missing Order Date","")&IF(C124="","; Missing Ship Date","")&IF(P124<0,"; Invalid Discount (Negative)","")&IF(P124>0.5,"; Invalid Discount (Too High)","")&IF(Z124<0,"; Invalid Shipping Record (Ship Before Order)","")&IF(ABS(Q124-W124)>1,"; Sales Mismatch","")&IF(ABS(S124-X124)>1,"; Profit Mismatch","")&IF(COUNTIF($A$2:$A$913,A124)>1,"; Duplicate Order ID Conflict",""),2)="; ",MID(AC124&IF(B124="","; Missing Order Date","")&IF(C124="","; Missing Ship Date","")&IF(P124<0,"; Invalid Discount (Negative)","")&IF(P124>0.5,"; Invalid Discount (Too High)","")&IF(Z124<0,"; Invalid Shipping Record (Ship Before Order)","")&IF(ABS(Q124-W124)>1,"; Sales Mismatch","")&IF(ABS(S124-X124)>1,"; Profit Mismatch","")&IF(COUNTIF($A$2:$A$913,A124)>1,"; Duplicate Order ID Conflict",""),3,500),AC124&IF(B124="","; Missing Order Date","")&IF(C124="","; Missing Ship Date","")&IF(P124<0,"; Invalid Discount (Negative)","")&IF(P124>0.5,"; Invalid Discount (Too High)","")&IF(Z124<0,"; Invalid Shipping Record (Ship Before Order)","")&IF(ABS(Q124-W124)>1,"; Sales Mismatch","")&IF(ABS(S124-X124)>1,"; Profit Mismatch","")&IF(COUNTIF($A$2:$A$913,A124)>1,"; Duplicate Order ID Conflict","")) | AE124: =IF(OR(ISNUMBER(SEARCH("Invalid Discount",AD124)),ISNUMBER(SEARCH("Invalid Shipping Record",AD124)),ISNUMBER(SEARCH("Sales Mismatch",AD124)),ISNUMBER(SEARCH("Profit Mismatch",AD124)),ISNUMBER(SEARCH("Duplicate Order ID Conflict",AD124)),ISNUMBER(SEARCH("Missing Order Date",AD124)),ISNUMBER(SEARCH("Missing Ship Date",AD124))),"Invalid",IF(AD124<>"","Warning","Clean")) -> Clean
A125: ORD-2024-10124 | B125: 45436 | C125: 45437 | D125: CUST-1007 | E125: =PROPER(TRIM(SUBSTITUTE(Raw_Text_Fields!B126,CHAR(160)," "))) -> Sneha Kapoor | F125: =PROPER(TRIM(SUBSTITUTE(Raw_Text_Fields!C126,CHAR(160)," "))) -> Small Business | G125: =PROPER(TRIM(SUBSTITUTE(Raw_Text_Fields!D126,CHAR(160)," "))) -> North | H125: =PROPER(TRIM(SUBSTITUTE(Raw_Text_Fields!E126,CHAR(160)," "))) -> Punjab | I125: =PROPER(TRIM(SUBSTITUTE(Raw_Text_Fields!F126,CHAR(160)," "))) -> Ludhiana | J125: =PROPER(TRIM(SUBSTITUTE(Raw_Text_Fields!G126,CHAR(160)," "))) -> Technology | K125: =PROPER(TRIM(SUBSTITUTE(Raw_Text_Fields!H126,CHAR(160)," "))) -> Copiers | L125: Max Copiers 970 | M125: =PROPER(TRIM(SUBSTITUTE(Raw_Text_Fields!I126,CHAR(160)," "))) -> Same Day | N125: 1 | O125: 634.13 | P125: 0 | Q125: 634.13 | R125: 453.35 | S125: 180.78 | T125: =PROPER(TRIM(SUBSTITUTE(Raw_Text_Fields!J126,CHAR(160)," "))) -> Refunded | U125: =PROPER(TRIM(SUBSTITUTE(Raw_Text_Fields!K126,CHAR(160)," "))) -> Cancelled | V125: =IF(OR(P125<0,P125>0.5),0,P125) -> 0 | W125: =N125*O125*(1-V125) -> 634.13 | X125: =W125-R125 -> 180.78 | Y125: =IFERROR(X125/W125,0) -> 0.2850835 | Z125: =C125-B125 -> 1 | AA125: =IF(B125="","",TEXT(B125,"mmm")) -> May | AB125: =IF(B125="","",YEAR(B125)) -> 2024 | AD125: =IF(LEFT(AC125&IF(B125="","; Missing Order Date","")&IF(C125="","; Missing Ship Date","")&IF(P125<0,"; Invalid Discount (Negative)","")&IF(P125>0.5,"; Invalid Discount (Too High)","")&IF(Z125<0,"; Invalid Shipping Record (Ship Before Order)","")&IF(ABS(Q125-W125)>1,"; Sales Mismatch","")&IF(ABS(S125-X125)>1,"; Profit Mismatch","")&IF(COUNTIF($A$2:$A$913,A125)>1,"; Duplicate Order ID Conflict",""),2)="; ",MID(AC125&IF(B125="","; Missing Order Date","")&IF(C125="","; Missing Ship Date","")&IF(P125<0,"; Invalid Discount (Negative)","")&IF(P125>0.5,"; Invalid Discount (Too High)","")&IF(Z125<0,"; Invalid Shipping Record (Ship Before Order)","")&IF(ABS(Q125-W125)>1,"; Sales Mismatch","")&IF(ABS(S125-X125)>1,"; Profit Mismatch","")&IF(COUNTIF($A$2:$A$913,A125)>1,"; Duplicate Order ID Conflict",""),3,500),AC125&IF(B125="","; Missing Order Date","")&IF(C125="","; Missing Ship Date","")&IF(P125<0,"; Invalid Discount (Negative)","")&IF(P125>0.5,"; Invalid Discount (Too High)","")&IF(Z125<0,"; Invalid Shipping Record (Ship Before Order)","")&IF(ABS(Q125-W125)>1,"; Sales Mismatch","")&IF(ABS(S125-X125)>1,"; Profit Mismatch","")&IF(COUNTIF($A$2:$A$913,A125)>1,"; Duplicate Order ID Conflict","")) -> Duplicate Order ID Conflict | AE125: =IF(OR(ISNUMBER(SEARCH("Invalid Discount",AD125)),ISNUMBER(SEARCH("Invalid Shipping Record",AD125)),ISNUMBER(SEARCH("Sales Mismatch",AD125)),ISNUMBER(SEARCH("Profit Mismatch",AD125)),ISNUMBER(SEARCH("Duplicate Order ID Conflict",AD125)),ISNUMBER(SEARCH("Missing Order Date",AD125)),ISNUMBER(SEARCH("Missing Ship Date",AD125))),"Invalid",IF(AD125<>"","Warning","Clean")) -> Invalid
A126: ORD-2024-10125 | B126: 45494 | C126: 45497 | D126: CUST-4450 | E126: =PROPER(TRIM(SUBSTITUTE(Raw_Text_Fields!B127,CHAR(160)," "))) -> Isha Nair | F126: =PROPER(TRIM(SUBSTITUTE(Raw_Text_Fields!C127,CHAR(160)," "))) -> Corporate | G126: =PROPER(TRIM(SUBSTITUTE(Raw_Text_Fields!D127,CHAR(160)," "))) -> South | H126: =PROPER(TRIM(SUBSTITUTE(Raw_Text_Fields!E127,CHAR(160)," "))) -> Karnataka | I126: =PROPER(TRIM(SUBSTITUTE(Raw_Text_Fields!F127,CHAR(160)," "))) -> Bengaluru | J126: =PROPER(TRIM(SUBSTITUTE(Raw_Text_Fields!G127,CHAR(160)," "))) -> Technology | K126: =PROPER(TRIM(SUBSTITUTE(Raw_Text_Fields!H127,CHAR(160)," "))) -> Copiers | L126: Pro Copiers 769 | M126: =PROPER(TRIM(SUBSTITUTE(Raw_Text_Fields!I127,CHAR(160)," "))) -> Standard Class | N126: 9 | O126: 465.06 | P126: -0.15 | Q126: 4185.54 | R126: 3443.74 | S126: 741.8 | T126: =PROPER(TRIM(SUBSTITUTE(Raw_Text_Fields!J127,CHAR(160)," "))) -> Paid | U126: =PROPER(TRIM(SUBSTITUTE(Raw_Text_Fields!K127,CHAR(160)," "))) -> Completed | V126: =IF(OR(P126<0,P126>0.5),0,P126) -> 0 | W126: =N126*O126*(1-V126) -> 4185.54 | X126: =W126-R126 -> 741.8 | Y126: =IFERROR(X126/W126,0) -> 0.17722922 | Z126: =C126-B126 -> 3 | AA126: =IF(B126="","",TEXT(B126,"mmm")) -> Jul | AB126: =IF(B126="","",YEAR(B126)) -> 2024 | AD126: =IF(LEFT(AC126&IF(B126="","; Missing Order Date","")&IF(C126="","; Missing Ship Date","")&IF(P126<0,"; Invalid Discount (Negative)","")&IF(P126>0.5,"; Invalid Discount (Too High)","")&IF(Z126<0,"; Invalid Shipping Record (Ship Before Order)","")&IF(ABS(Q126-W126)>1,"; Sales Mismatch","")&IF(ABS(S126-X126)>1,"; Profit Mismatch","")&IF(COUNTIF($A$2:$A$913,A126)>1,"; Duplicate Order ID Conflict",""),2)="; ",MID(AC126&IF(B126="","; Missing Order Date","")&IF(C126="","; Missing Ship Date","")&IF(P126<0,"; Invalid Discount (Negative)","")&IF(P126>0.5,"; Invalid Discount (Too High)","")&IF(Z126<0,"; Invalid Shipping Record (Ship Before Order)","")&IF(ABS(Q126-W126)>1,"; Sales Mismatch","")&IF(ABS(S126-X126)>1,"; Profit Mismatch","")&IF(COUNTIF($A$2:$A$913,A126)>1,"; Duplicate Order ID Conflict",""),3,500),AC126&IF(B126="","; Missing Order Date","")&IF(C126="","; Missing Ship Date","")&IF(P126<0,"; Invalid Discount (Negative)","")&IF(P126>0.5,"; Invalid Discount (Too High)","")&IF(Z126<0,"; Invalid Shipping Record (Ship Before Order)","")&IF(ABS(Q126-W126)>1,"; Sales Mismatch","")&IF(ABS(S126-X126)>1,"; Profit Mismatch","")&IF(COUNTIF($A$2:$A$913,A126)>1,"; Duplicate Order ID Conflict","")) -> Invalid Discount (Negative) | AE126: =IF(OR(ISNUMBER(SEARCH("Invalid Discount",AD126)),ISNUMBER(SEARCH("Invalid Shipping Record",AD126)),ISNUMBER(SEARCH("Sales Mismatch",AD126)),ISNUMBER(SEARCH("Profit Mismatch",AD126)),ISNUMBER(SEARCH("Duplicate Order ID Conflict",AD126)),ISNUMBER(SEARCH("Missing Order Date",AD126)),ISNUMBER(SEARCH("Missing Ship Date",AD126))),"Invalid",IF(AD126<>"","Warning","Clean")) -> Invalid
